Workbook
Name _dataMtr: '12'!$B$5:$S$331
Name _itemMtr: '12'!$B$5:$B$331
Name data: [1]Menu!$A$42:$B$44
Name data: [2]Menu!$A$42:$B$44
Name data: [3]Menu!$A$42:$B$44
Name data: [4]Menu!$A$42:$B$44
Name data: [4]Menu!$A$42:$B$44
Name data: [4]Menu!$A$42:$B$44
Name data: [4]Menu!$A$42:$B$44
Name data: Menu!$A$42:$B$44
Name data_koso: #REF!
Name data_m: #REF!
Name data1: #REF!
Name item: [1]Menu!$A$42:$A$44
Name item: [2]Menu!$A$42:$A$44
Name item: [3]Menu!$A$42:$A$44
Name item: [4]Menu!$A$42:$A$44
Name item: [4]Menu!$A$42:$A$44
Name item: [4]Menu!$A$42:$A$44
Name item: [4]Menu!$A$42:$A$44
Name item: Menu!$A$42:$A$44
Name item_koso: #REF!
Name item_m: #REF!
Name item1: #REF!
Name lineno: '50'!$B$8:$B$40
Name lineno: '51'!#REF!
Name lineno: #REF!
Name status: #REF!
Name ti: #REF!

Sheet Menu
A1: Table of Contents - Qualification of the Maintenance Asset List
A3: ELINS | C3: Qty | E3: MECHANICAL | G3: Qty | I3: CIVIL | K3: Qty
A4: 1 | B4: CONTROL SYSTEM (DCS & RACK ROOM) | C4: ='1'!D79 -> 69 | D4: =C4/C4 -> 1 | E4: =A28+1 -> 26 | F4: AGITATOR | G4: ='26'!D38 -> 17 | H4: =G4/G4 -> 1 | I4: 52 | J4: BUILDING | K4: ='52'!C24 -> 14 | L4: =K4/K4 -> 1
A5: =A4+1 -> 2 | B5: CONTROL VALVE | C5: ='2'!C754 -> 711 | D5: =C5/C5 -> 1 | E5: =E4+1 -> 27 | F5: GEAR PUMP | G5: ='27'!D31 -> 13 | H5: =G5/G5 -> 1 | I5: =I4+1 -> 53 | J5: SHELTER | K5: ='53'!C36 -> 26 | L5: =K5/K5 -> 1
A6: =A5+1 -> 3 | B6: FLOW METER | C6: ='3'!D415 -> 383 | D6: =C6/C6 -> 1 | E6: =E5+1 -> 28 | F6: RECIPROCATING PUMP | G6: ='28'!D50 -> 31 | H6: =G6/G6 -> 1 | K6: =SUM(K4:K5) -> 40 | L6: =AVERAGE(L4:L5) -> 1
A7: =A6+1 -> 4 | B7: PRESSURE INSTRUMENT | C7: ='4'!D359 -> 323 | D7: =C7/C7 -> 1 | E7: =E6+1 -> 29 | F7: CENTRIFUGAL PUMP | G7: ='29'!D140 -> 121 | H7: =G7/G7 -> 1
A8: =A7+1 -> 5 | B8: PRESSURE GAUGE | C8: ='5'!D720 -> 683 | D8: =C8/C8 -> 1 | E8: =E7+1 -> 30 | F8: BLOWER | G8: ='30'!D40 -> 19 | H8: =G8/G8 -> 1
A9: =A8+1 -> 6 | B9: TEMPERATURE INSTRUMENT | C9: ='6'!D501 -> 468 | D9: =C9/C9 -> 1 | E9: =E8+1 -> 31 | F9: COMPRESSOR | G9: ='31'!D35 -> 20 | H9: =G9/G9 -> 1
A10: =A9+1 -> 7 | B10: TEMPERATURE GAUGE | C10: ='7'!D212 -> 192 | D10: =C10/C10 -> 1 | E10: =E9+1 -> 32 | F10: Package Unit | G10: ='32'!D67 -> 50 | H10: =G10/G10 -> 1
A11: =A10+1 -> 8 | B11: LEVEL INSTRUMENT | C11: ='8'!D327 -> 298 | D11: =C11/C11 -> 1 | E11: =E10+1 -> 33 | F11: SEPARATOR | G11: ='33'!D38 -> 20 | H11: =G11/G11 -> 1
A12: =A11+1 -> 9 | B12: LEVEL GAUGE | C12: ='9'!D200 -> 176 | D12: =C12/C12 -> 1 | E12: =E11+1 -> 34 | F12: TANK | G12: ='34'!D93 -> 77 | H12: =G12/G12 -> 1
A13: =A12+1 -> 10 | B13: ANALYZER | C13: ='10'!F57 -> 37 | D13: =C13/C13 -> 1 | E13: =E12+1 -> 35 | F13: DRUM | G13: ='35'!D117 -> 98 | H13: =G13/G13 -> 1
A14: =A13+1 -> 11 | B14: MISCELLENOUS (GD,VS,HY,HC,PY,TY, RD) | C14: ='11'!F125 -> 114 | D14: =C14/C14 -> 1 | E14: =E13+1 -> 36 | F14: TOWER | G14: ='36'!D50 -> 34 | H14: =G14/G14 -> 1
A15: =A14+1 -> 12 | B15: MOTOR | C15: ='12'!C470 -> 435 | D15: =C15/C15 -> 1 | E15: =E14+1 -> 37 | F15: REAKTOR | G15: ='37'!D33 -> 13 | H15: =G15/G15 -> 1
A16: =A15+1 -> 13 | B16: TRANSFORMER | C16: ='13'!C21 -> 10 | D16: =C16/C16 -> 1 | E16: =E15+1 -> 38 | F16: HEAT EXCHANGER (STHE, PHE) | G16: ='38'!D178 -> 158 | H16: =G16/G16 -> 1
A17: =A16+1 -> 14 | B17: BATTERY | C17: ='14'!C278 -> 268 | D17: =C17/C17 -> 1 | E17: =E16+1 -> 39 | F17: FILTER | G17: ='39'!D63 -> 45 | H17: =G17/G17 -> 1
A18: =A17+1 -> 15 | B18: PANEL LISTRIK | C18: ='15'!C55 -> 46 | D18: =C18/C18 -> 1 | E18: =E17+1 -> 40 | F18: CANNED PUMP | G18: ='40'!D142 -> 123 | H18: =G18/G18 -> 1
A19: =A18+1 -> 16 | B19: PANEL INSTRUMENT | C19: ='16'!C60 -> 36 | D19: =C19/C19 -> 1 | E19: 41 | F19: EJECTOR | G19: ='41'!D29 -> 4 | H19: =G19/G19 -> 1
A20: =A19+1 -> 17 | B20: RECEIPTACLE | C20: ='17'!C123 -> 114 | D20: =C20/C20 -> 1 | E20: 42 | F20: SAFETY VALVE | G20: ='42'!D196 -> 167 | H20: =G20/G20 -> 1
A21: =A20+1 -> 18 | B21: PAGING SYSTEM | C21: ='18'!E43 -> 34 | D21: =C21/C21 -> 1 | E21: 43 | F21: STEAM TRAP | G21: ='43'!D41 -> 27 | H21: =G21/G21 -> 1
A22: =A21+1 -> 19 | B22: AIR CONDITIONING | C22: ='19'!B65 -> 55 | D22: =C22/C22 -> 1 | E22: 44 | F22: STRAINER | G22: ='44'!D73 -> 62 | H22: =G22/G22 -> 1
A23: =A22+1 -> 20 | B23: FASILITAS (SNORKLIFT, PENGUSIR TIKUS, PABX) | C23: ='20'!D40 -> 31 | D23: =C23/C23 -> 1 | E23: 45 | F23: STATIC MIXER | G23: ='45'!D40 -> 9 | H23: =G23/G23 -> 1
A24: =A23+1 -> 21 | B24: CATHODIC PROTECTION | C24: ='21'!C35 -> 26 | D24: =C24/C24 -> 1 | E24: 46 | F24: HEAT EXCHANGER (AIR FIN COOLER) | G24: ='46'!D70 -> 47 | H24: =G24/G24 -> 1
A25: =A24+1 -> 22 | B25: GROUNDING | C25: ='22'!C83 -> 73 | D25: =C25/C25 -> 1 | E25: 47 | F25: PIPING LIST SYN GAS | G25: ='47'!B508 -> 499 | H25: =G25/G25 -> 1
A26: =A25+1 -> 23 | B26: JUNCTION BOX | C26: ='23'!C132 -> 122 | D26: =C26/C26 -> 1 | E26: 47-1 | F26: VALVE LIST SYN GAS | G26: ='47-1'!A814 -> 520 | H26: ='47-1'!F815 -> 0.99617347
A27: =A26+1 -> 24 | B27: CUBICLE | C27: ='24'!G356 -> 335 | D27: =C27/C27 -> 1 | E27: 48 | F27: PIPING LIST OCTANOL | G27: ='48'!C2087 -> 2078 | H27: =G27/2078 -> 1
A28: =A27+1 -> 25 | B28: PLC & SCADA | C28: ='25'!D24 -> 12 | D28: =C28/C28 -> 1 | E28: 48-1 | F28: VALVE LIST OCTANOL | G28: ='48-1'!E2199 -> 556 | H28: ='48-1'!C2205 -> 0.9985563
A29: 25-1 | B29: BREATHER VALVE | C29: ='25-1'!B73 -> 43 | D29: =C29/C29 -> 1 | E29: 49 | F29: PIPING LIST UTILITY | G29: ='49'!A429 -> 420 | H29: =G29/G29 -> 1
A30: 25-2 | B30: SWITCHGEAR 20KV & 6.3 KV | C30: ='25-2'!D40 -> 31 | D30: =C30/C30 -> 1 | E30: 49-1 | F30: VALVE LIST UTILITY | G30: ='49-1'!I629 -> 419 | H30: ='49-1'!J629 -> 0.99761905
A31: 25-3 | B31: PERALATAN LABORAT | C31: ='25-3'!D32 -> 22 | D31: =C31/C31 -> 1 | E31: 50 | F31: PIPING LIST CO2 GAS | G31: ='50'!A42 -> 33 | H31: =G31/G31 -> 1
A32: 25-4 | B32: ROAD LIGHTING | C32: ='25-4'!D107 -> 97 | D32: =C32/C32 -> 1 | E32: 50-1 | F32: VALVE LIST CO2 GAS | G32: ='50-1'!A45 -> 33 | H32: =G32/G32 -> 1
A33: 25-5 | B33: ALAT UKUR | C33: ='25-5'!A60 -> 39 | D33: =C33/C33 -> 1 | E33: 51 | F33: PIPING LIST CO2 LIQUID | G33: ='51'!A114 -> 105 | H33: =G33/G33 -> 1
A34: 25-6 | B34: CABLE | C34: ='25-6'!A1507 -> 1448 | D34: ='25-6'!E1507/C34 -> 0.99585635 | E34: 51-1 | F34: VALVE LIST CO2 LIQUID | G34: ='51-1'!A130 -> 105 | H34: =G34/G34 -> 1
B35: Total equipment | C35: =SUM(C4:C34) -> 6731 | D35: =AVERAGE(D32:D34) -> 0.99861878
B36: Total progress terecord | C36: =D30+H29 -> 2 | G36: =SUM(G4:G35) -> 5923 | H36: =AVERAGE(H25:H34) -> 0.99923488 | J36: Total Progress : | L36: =AVERAGE(D35,H36,L6) -> 0.99928456
B37: Note:
B38: Criteria= C : Critical; S : Safety; E : Environment
B39: Criteria Level= *: 1 criteria, **: 2 Criteria, ***: 3 Criteria
B40: Criteria Point= 5: *, 25: **, 125: ***
A42: 1 | B42: 5
A43: 2 | B43: 25
A44: 3 | B44: 125

Sheet 53
D1: SHELTER
A3: NO | B3: Code | C3: NAME | D3: LOCATION | E3: Area | F3: SIZE | G3: Category | I3: COMPLEX GRADE | J3: REMARK
C4: SHELTER | G4: Score | H4: Grade
A6: 1 | C6: Shelter RO | D6: Gate 2 | E6: Utility
A7: =A6+1 -> 2 | C7: Shelter Chemical | D7: Gate 2 | E7: Utility
A8: =A7+1 -> 3 | C8: Shelter Maintenance | D8: Gate 2 | E8: Utility
A9: =A8+1 -> 4 | C9: Waste Shelter ( B3 ) | D9: Gate 2 | E9: Utility
A10: =A9+1 -> 5 | C10: Foam trailer shelter | D10: Gate 2 | E10: Utility
A11: =A10+1 -> 6 | C11: Shelter RO SWWT | D11: Gate 2 | E11: Utility
A12: =A11+1 -> 7 | C12: Shelter H-923 | D12: Gate 2 | E12: Utility
A13: =A12+1 -> 8 | C13: Shelter H-922 | D13: Gate 2 | E13: Utility
A14: =A13+1 -> 9 | C14: Shelter N2 Generator | D14: Gate 2 | E14: Utility
A15: =A14+1 -> 10 | C15: Shelter Chiller & comp udara | D15: Gate 2 | E15: Utility
A16: =A15+1 -> 11 | C16: Shelter Inject Chemical cooling tower | D16: Gate 2 | E16: Utility
A17: =A16+1 -> 12 | C17: Shelter C-412, C-150 | D17: Gate 2 | E17: Octanol
A18: =A17+1 -> 13 | C18: Shelter D-102 | D18: Gate 2 | E18: Octanol
... A31: =A30+1 -> 26 | C31: POS-6 Shelter | D31: Gate 2 | E31: -
D32: Gate 2 | E32: -
A36: Total Asset : | C36: =COUNTA(C6:C34) -> 26

Sheet 52
D1: BUILDING / GEDUNG
A3: NO | B3: Code | C3: NAME | D3: LOCATION | E3: SIZE | F3: Category | H3: COMPLEX GRADE | I3: REMARK
C4: Building / Gedung | F4: Score | G4: Grade
A6: 1 | C6: Maintenance | D6: Gate 2
A7: 2 | C7: Safety | D7: Gate 2
A8: 3 | C8: Laboratory | D8: Gate 2
A9: 4 | C9: EDG | D9: Gate 2
A10: 5 | C10: Main Subtation | D10: Gate 2
A11: 6 | C11: MCR | D11: Gate 2
A12: 7 | C12: Office produksi | D12: Gate 2
A13: 8 | C13: A/C Room | D13: Gate 2
A14: 9 | C14: Rack room | D14: Gate 2
A15: 10 | C15: A/C Room | D15: Gate 2
A16: 11 | C16: LSS | D16: Gate 2
A17: 12 | C17: Analyzer room Octanol | D17: Gate 2
... A19: 14 | C19: MCC Room | D19: Gate 2
F22: =IF(ISERROR(INDEX(data,MATCH(LEN(H22),item,0),2))," ",INDEX(data,MATCH(LEN(H22),item,0),2))
A24: Total Asset : | C24: =COUNTA(C6:C21) -> 14

Sheet 51-1
C1: EQUIPMENT LIST | F1: Document No. | I1: : MNTC-ME
F2: Revision | I2: : 0
F3: Date of issue | I3: : 2025
A4: PT. PETRO OXO NUSANTARA | F4: Page | I4: :
A5: VALVE LIST CO2 LIQUID
A7: NO | B7: Code | C7: Line Number piping + accecories | D7: Diameter | E7: SCH | F7: Valve | G7: Material | H7: Remark
A9: CO2 Liquid
A10: 1 | B10: 510362 | C10: CG-B365R-A-P36128
A11: =A10+1 -> 2 | B11: 510363 | C11: CG-B365R-A-P36146
A12: =A11+1 -> 3 | B12: 510364 | C12: CG-B365R-A-P36149
A13: =A12+1 -> 4 | B13: 510365 | C13: CG-E150-A-P11502
A14: =A13+1 -> 5 | B14: 510366 | C14: CG-E150-A-P11502
A15: =A14+1 -> 6 | B15: 510367 | C15: CG-E150-A-P12301
A16: =A15+1 -> 7 | B16: 510368 | C16: CG-E150-A-P12302 | D16: 6" | E16: 150 | F16: BV2 | G16: SS316 | H16: Butterfly Valve
D17: 1" | E17: - | F17: BLV1 | G17: SS | H17: Ball Valve
A18: =A16+1 -> 8 | B18: 510369 | C18: CG-E150-A-P12302 | D18: 1/2" | E18: - | F18: BLV1 | H18: Ball Valve
A19: =A18+1 -> 9 | B19: 510374 | C19: CG-E435-A-P11607 | D19: 1 | E19: - | F19: BLV1 | G19: SS | H19: Ball Valve
D20: 1 | E20: 300 | F20: CV1 | G20: SS | H20: Check Valve
D21: 1/2 | E21: - | F21: BLV1 | G21: SS | H21: Ball Valve
A22: =A19+1 -> 10 | B22: 510375 | C22: CG-E435-A-P36127 | D22: 1 | E22: - | F22: BLV1 | G22: SS | H22: Ball Valve
D23: 1/2 | E23: - | F23: BLV1 | G23: SS | H23: Ball Valve
A24: =A22+1 -> 11 | B24: 510376 | C24: CG-E150-A-P67901 | D24: 1/2 | E24: - | F24: NV2 | H24: Needle Valve
A25: =A24+1 -> 12 | B25: 510377 | C25: CG-E150-A-P67901 | D25: 1/2 | E25: - | F25: NV4 | H25: Needle Valve
A26: =A25+1 -> 13 | B26: 510378 | C26: CG-E150-A-P67901 | D26: 1/2 | E26: - | F26: NV3 | H26: Needle Valve
A27: =A26+1 -> 14 | B27: 510379 | C27: CG-E150-A-P67901 | D27: 1/2 | E27: - | F27: NV3 | H27: Needle Valve
A28: =A27+1 -> 15 | B28: 510380 | C28: CG-F435-A-P20138 | D28: 1 | E28: - | F28: BLV1 | G28: SS | H28: Ball Valve
A29: =A28+1 -> 16 | B29: 510381 | C29: CG-F435-A-P20138 | D29: 2 | E29: - | F29: BLV2 | G29: SS | H29: Ball Valve
A30: =A29+1 -> 17 | B30: 510382 | C30: CG-F435-A-P33531
A31: =A30+1 -> 18 | B31: 510383 | C31: CL-B365R-A-P37315
A32: =A31+1 -> 19 | B32: 510384 | C32: CW-A150-A-P11420
A33: =A32+1 -> 20 | B33: 510385 | C33: CW-A150-A-P11226
A34: =A33+1 -> 21 | B34: 510386 | C34: CW-A150-A- P50102 | D34: 14 | E34: 150 | F34: BV1 | G34: SS316 | H34: Butterfly Valve
D35: 1 | F35: BLV1 | G35: SS | H35: Ball Valve
D36: 1/2 | F36: BLV1 | H36: Ball Valve
A37: =A34+1 -> 22 | B37: 510387 | C37: CO-A150-A-P10114
A38: =A37+1 -> 23 | B38: 510388 | C38: CW-A150-A- P50106
A39: =A38+1 -> 24 | B39: 510389 | C39: CW-A150-A- P50108
A40: =A39+1 -> 25 | B40: 510390 | C40: CW-A150-A-P50113
A41: =A40+1 -> 26 | B41: 510391 | C41: CW-A150-A-P10116
A42: =A41+1 -> 27 | B42: 510392 | C42: CW-A150-A- P40123
A43: =A42+1 -> 28 | B43: 510393 | C43: CO-A150-A-P10120
A44: =A43+1 -> 29 | B44: 510394 | C44: CW-A150-A- P11509
A45: =A44+1 -> 30 | B45: 510395 | C45: CW-A150-A-P11410
A46: =A45+1 -> 31 | B46: 510396 | C46: CO-A150-A-P10320
A47: =A46+1 -> 32 | B47: 510397 | C47: CW-A150-A-P50101 | D47: 14 | E47: 150 | F47: BV1 | G47: SS316 | H47: Butterfly Valve
D48: 1 | F48: BLV1 | G48: SS | H48: Ball Valve
D49: 1/2 | F49: BLV1 | H49: Ball Valve
A50: =A47+1 -> 33 | B50: 510398 | C50: CW-A150-A-P50107
A51: =A50+1 -> 34 | B51: 510399 | C51: CW-A150-A-P11418
A52: =A51+1 -> 35 | B52: 510400 | C52: CW-A150-A-P10117
A53: =A52+1 -> 36 | B53: 510401 | C53: CO-A150-A-P10115
A54: =A53+1 -> 37 | B54: 510402 | C54: CO-A150-A-P10314
A55: =A54+1 -> 38 | B55: 510406 | C55: CW-A150-A-P50111
A56: =A55+1 -> 39 | B56: 510407 | C56: FG-A150-A-P10101 | D56: 1/2 | F56: BLV2 | H56: Ball Valve
A57: =A56+1 -> 40 | B57: 510408 | C57: FG-E150-A-P11209 | D57: 1/2 | F57: BLV2 | H57: Ball Valve
A58: =A57+1 -> 41 | B58: 510409 | C58: CW-A150-A-P50120
A59: =A58+1 -> 42 | B59: 510410 | C59: FG-E150-A-P10102 | D59: 1/2 | F59: BLV2 | H59: Ball Valve
A60: =A59+1 -> 43 | B60: 510411 | C60: CW-A150-A-P50119
A61: =A60+1 -> 44 | B61: 510412 | C61: FG-A150-A-P10122 | D61: 1-1/2 | F61: BLV1 | G61: CS | H61: Ball Valve
A62: =A61+1 -> 45 | B62: 510413 | C62: FG-A150-A-P10121 | D62: 1-1/2 | F62: BLV1 | G62: CS | H62: Ball Valve
A63: =A62+1 -> 46 | B63: 510414 | C63: CW-A150-A-P50121
A64: =A63+1 -> 47 | B64: 510415 | C64: FG-E150-A-P11302
A65: =A64+1 -> 48 | B65: 510416 | C65: FG-E150-A-P11302 | D65: 1/2 | F65: BLV2 | H65: Ball Valve
A66: =A65+1 -> 49 | B66: 510417 | C66: FG-E150-A-P11427 | D66: 1/2 | F66: NDV1 | H66: Needle Valve
A67: =A66+1 -> 50 | B67: 510418 | C67: FG-E150-A-P11428 | D67: 1/2 | F67: NDV1 | H67: Needle Valve
A68: =A67+1 -> 51 | B68: 510419 | C68: FG-E150-A-P11435 | D68: 1/2 | F68: NDV1 | H68: Needle Valve
A69: =A68+1 -> 52 | B69: 510420 | C69: FG-E150-A-P11425 | D69: 1/2 | F69: NDV1 | H69: Needle Valve
A70: =A69+1 -> 53 | B70: 510421 | C70: FG-E150-A-P11426 | D70: 1/2 | F70: NDV1 | H70: Needle Valve
A71: =A70+1 -> 54 | B71: 510422 | C71: FG-E150-A-P11310 | D71: 16 | E71: 150 | F71: CV1 | G71: SS316 | H71: Check Valve
D72: 1/2 | E72: - | F72: BLV1 | G72: SS | H72: Ball Valve
A73: =A71+1 -> 55 | B73: 510424 | C73: FG-E150-A-P11304 | D73: 1 | F73: BLV1 | G73: SS | H73: Ball Valve
A74: =A73+1 -> 56 | B74: 510425 | C74: FG-E150-A-P11433 | D74: 1/2 | F74: NDV1 | H74: Needle Valve
A75: =A74+1 -> 57 | B75: 510426 | C75: FG-E150-A-P11434 | D75: 1/2 | F75: NDV1 | H75: Needle Valve
A76: =A75+1 -> 58 | B76: 510427 | C76: ME-E150-A-P10443
A77: =A76+1 -> 59 | B77: 510428 | C77: ME-E150-A-P10301
A78: =A77+1 -> 60 | B78: 510429 | C78: ME-E150-A-P11414 | D78: 1/2 | E78: - | F78: BLV1 | G78: SS | H78: Ball Valve
A79: =A78+1 -> 61 | B79: 510430 | C79: FG-E150-A-P11436 | D79: 1/2 | F79: NDV1 | H79: Needle Valve
A80: =A79+1 -> 62 | B80: 510431 | C80: ME-E150-A-P11417
A81: =A80+1 -> 63 | B81: 510432 | C81: ME-E150-A-P11460 | D81: 1/2 | E81: - | F81: BLV1 | G81: SS | H81: Ball Valve
A82: =A81+1 -> 64 | B82: 510433 | C82: ME-E150-A-P11440
A83: =A82+1 -> 65 | B83: 510434 | C83: ME-E150-A-P11500 | D83: 1/2 | F83: NDV1 | H83: Needle Valve
A84: =A83+1 -> 66 | B84: 510435 | C84: ME-E150-A-P11500 | D84: 1/2 | F84: NDV1 | H84: Needle Valve
A85: =A84+1 -> 67 | B85: 510436 | C85: ME-E150-A-P11500 | D85: 1/2 | F85: NDV1 | H85: Needle Valve
A86: =A85+1 -> 68 | B86: 510437 | C86: ME-E150-A-P11530
A87: =A86+1 -> 69 | B87: 510438 | C87: ME-E150-A-P11602
A88: =A87+1 -> 70 | B88: 510439 | C88: ME-E150-A-P11504
A89: =A88+1 -> 71 | B89: 510440 | C89: ME-E150-A-P11531
A90: =A89+1 -> 72 | B90: 510441 | C90: ME-E150-A-P11508
A91: =A90+1 -> 73 | B91: 510442 | C91: ME-E150-A-P11605
A92: =A91+1 -> 74 | B92: 510443 | C92: ME-E150-A-P11605 | D92: 1/2 | F92: BLV1 | H92: Ball Valve
D93: 1/2 | F93: NDV1 | H93: Needle Valve
A94: =A92+1 -> 75 | B94: 510444 | C94: ME-E150-A-P11615 | D94: 1/2 | F94: NDV1 | H94: Needle Valve
A95: =A94+1 -> 76 | B95: 510445 | C95: ME-E150-A-P11631 | D95: 1/2 | E95: - | F95: BLV1 | G95: SS | H95: Ball Valve
A96: =A95+1 -> 77 | B96: 510446 | C96: PW-E150-A-P10420
A97: =A96+1 -> 78 | B97: 510447 | C97: PW-E150-A-P11461
A98: =A97+1 -> 79 | B98: 510448 | C98: PW-E150-A-P11507
A99: =A98+1 -> 80 | B99: 510449 | C99: PW-E150-A-P12310 | D99: 1 | F99: BLV1 | G99: SS | H99: Ball Valve
A100: =A99+1 -> 81 | B100: 510450 | C100: PW-E150-A-P12309
A101: =A100+1 -> 82 | B101: 510451 | C101: PW-E150-A-P11303 | D101: 2 | F101: BLV1 | G101: SS | H101: Ball Valve
A102: =A101+1 -> 83 | B102: 510452 | C102: PW-E150-A-P12308 | D102: 2 | F102: BLV2 | G102: SS | H102: Ball Valve
...

Sheet 51
C1: ASSET LIST | G1: Document No. | J1: : MNTC-ME
G2: Revision | J2: : 0
G3: Date of issue | J3: : 2025
A4: PT. PETRO OXO NUSANTARA | G4: Page | J4: :
A5: PIPING LIST CO2 LIQUID
A7: No | B7: Line No. | C7: Size | D7: Service | E7: Fluid | F7: Material | G7: Insulation | H7: PAGE NO. | I7: Drawing | J7: Pipe length ( mm )
A8: 1 | B8: CG-B365R-A-P36128 | C8: 3" | D8: Carbon Dioxide Gaseous | E8: Gas | F8: CS low temp | H8: 510362 | I8: =HYPERLINK("\\CAD-PC\1Data\3.Documentation\Isometric DWG\Line List & Data Inspeksi\29. Isometric CO2 Liquid\" & H8 &" A" & ".pdf", "Drawing") -> Drawing
A9: =A8+1 -> 2 | B9: CG-B365R-A-P36146 | C9: 1" | D9: Carbon Dioxide Gaseous | E9: Gas | F9: CS low temp | H9: 510363 | I9: =HYPERLINK("\\CAD-PC\1Data\3.Documentation\Isometric DWG\Line List & Data Inspeksi\29. Isometric CO2 Liquid\" & H9 &" A" & ".pdf", "Drawing") -> Drawing
A10: =A9+1 -> 3 | B10: CG-B365R-A-P36149 | C10: 2 | D10: Carbon Dioxide Gaseous | E10: Gas | F10: CS low temp | H10: 510364 | I10: =HYPERLINK("\\CAD-PC\1Data\3.Documentation\Isometric DWG\Line List & Data Inspeksi\29. Isometric CO2 Liquid\" & H10 &" A" & ".pdf", "Drawing") -> Drawing
A11: =A10+1 -> 4 | B11: CG-E150-A-P11502 | C11: 12 | D11: Carbon Dioxide Gaseous | E11: Gas | F11: SS304 | H11: 510365 | I11: =HYPERLINK("\\CAD-PC\1Data\3.Documentation\Isometric DWG\Line List & Data Inspeksi\29. Isometric CO2 Liquid\" & H11 &" A" & ".pdf", "Drawing") -> Drawing
A12: =A11+1 -> 5 | B12: CG-E150-A-P11502 | C12: 12 | D12: Carbon Dioxide Gaseous | E12: Gas | F12: SS304 | H12: 510366 | I12: =HYPERLINK("\\CAD-PC\1Data\3.Documentation\Isometric DWG\Line List & Data Inspeksi\29. Isometric CO2 Liquid\" & H12 &" A" & ".pdf", "Drawing") -> Drawing
A13: =A12+1 -> 6 | B13: CG-E150-A-P12301 | C13: 10 | D13: Carbon Dioxide Gaseous | E13: Gas | F13: SS304 | H13: 510367 | I13: =HYPERLINK("\\CAD-PC\1Data\3.Documentation\Isometric DWG\Line List & Data Inspeksi\29. Isometric CO2 Liquid\" & H13 &" A" & ".pdf", "Drawing") -> Drawing
A14: =A13+1 -> 7 | B14: CG-E150-A-P12302 | C14: 10 | D14: Carbon Dioxide Gaseous | E14: Gas | F14: SS304 | H14: 510368 | I14: =HYPERLINK("\\CAD-PC\1Data\3.Documentation\Isometric DWG\Line List & Data Inspeksi\29. Isometric CO2 Liquid\" & H14 &" A" & ".pdf", "Drawing") -> Drawing
A15: =A14+1 -> 8 | B15: CG-E150-A-P12302 | C15: 10 | D15: Carbon Dioxide Gaseous | E15: Gas | F15: SS304 | H15: 510369 | I15: =HYPERLINK("\\CAD-PC\1Data\3.Documentation\Isometric DWG\Line List & Data Inspeksi\29. Isometric CO2 Liquid\" & H15 &" A" & ".pdf", "Drawing") -> Drawing
A16: =A15+1 -> 9 | B16: CG-E435-A-P11607 | C16: 1 | D16: Carbon Dioxide Gaseous | E16: Gas | F16: CS | H16: 510374 | I16: =HYPERLINK("\\CAD-PC\1Data\3.Documentation\Isometric DWG\Line List & Data Inspeksi\29. Isometric CO2 Liquid\" & H16 &" A" & ".pdf", "Drawing") -> Drawing
A17: =A16+1 -> 10 | B17: CG-E435-A-P36127 | C17: 2 | D17: Carbon Dioxide Gaseous | E17: Gas | F17: CS | H17: 510375 | I17: =HYPERLINK("\\CAD-PC\1Data\3.Documentation\Isometric DWG\Line List & Data Inspeksi\29. Isometric CO2 Liquid\" & H17 &" A" & ".pdf", "Drawing") -> Drawing
A18: =A17+1 -> 11 | B18: CG-E150-A-P67901 | C18: 1 | D18: Carbon Dioxide Gaseous | E18: Gas | F18: SS304 | H18: 510376 | I18: =HYPERLINK("\\CAD-PC\1Data\3.Documentation\Isometric DWG\Line List & Data Inspeksi\29. Isometric CO2 Liquid\" & H18 &" A" & ".pdf", "Drawing") -> Drawing
A19: =A18+1 -> 12 | B19: CG-E150-A-P67901 | C19: 1 | D19: Carbon Dioxide Gaseous | E19: Gas | F19: SS304 | H19: 510377 | I19: =HYPERLINK("\\CAD-PC\1Data\3.Documentation\Isometric DWG\Line List & Data Inspeksi\29. Isometric CO2 Liquid\" & H19 &" A" & ".pdf", "Drawing") -> Drawing
A20: =A19+1 -> 13 | B20: CG-E150-A-P67901 | D20: Carbon Dioxide Gaseous | E20: Gas | F20: SS304 | H20: 510378 | I20: =HYPERLINK("\\CAD-PC\1Data\3.Documentation\Isometric DWG\Line List & Data Inspeksi\29. Isometric CO2 Liquid\" & H20 &" A" & ".pdf", "Drawing") -> Drawing
A21: =A20+1 -> 14 | B21: CG-E150-A-P67901 | D21: Carbon Dioxide Gaseous | E21: Gas | F21: SS304 | H21: 510379 | I21: =HYPERLINK("\\CAD-PC\1Data\3.Documentation\Isometric DWG\Line List & Data Inspeksi\29. Isometric CO2 Liquid\" & H21 &" A" & ".pdf", "Drawing") -> Drawing
A22: =A21+1 -> 15 | B22: CG-F435-A-P20138 | D22: Carbon Dioxide Gaseous | E22: Gas | F22: CS | H22: 510380 | I22: =HYPERLINK("\\CAD-PC\1Data\3.Documentation\Isometric DWG\Line List & Data Inspeksi\29. Isometric CO2 Liquid\" & H22 &" A" & ".pdf", "Drawing") -> Drawing
A23: =A22+1 -> 16 | B23: CG-F435-A-P20138 | D23: Carbon Dioxide Gaseous | E23: Gas | F23: CS | H23: 510381 | I23: =HYPERLINK("\\CAD-PC\1Data\3.Documentation\Isometric DWG\Line List & Data Inspeksi\29. Isometric CO2 Liquid\" & H23 &" A" & ".pdf", "Drawing") -> Drawing
A24: =A23+1 -> 17 | B24: CG-F435-A-P33531 | D24: Carbon Dioxide Gaseous | E24: Gas | F24: CS | H24: 510382 | I24: =HYPERLINK("\\CAD-PC\1Data\3.Documentation\Isometric DWG\Line List & Data Inspeksi\29. Isometric CO2 Liquid\" & H24 &" A" & ".pdf", "Drawing") -> Drawing
A25: =A24+1 -> 18 | B25: CL-B365R-A-P37315 | D25: Carbon Dioxide Liquid | E25: Liquid | F25: CS low temp | H25: 510383 | I25: =HYPERLINK("\\CAD-PC\1Data\3.Documentation\Isometric DWG\Line List & Data Inspeksi\29. Isometric CO2 Liquid\" & H25 &" A" & ".pdf", "Drawing") -> Drawing
A26: =A25+1 -> 19 | B26: CW-A150-A-P11420 | D26: Cooling Water | E26: Water | F26: CS | H26: 510384 | I26: =HYPERLINK("\\CAD-PC\1Data\3.Documentation\Isometric DWG\Line List & Data Inspeksi\29. Isometric CO2 Liquid\" & H26 &" A" & ".pdf", "Drawing") -> Drawing
A27: =A26+1 -> 20 | B27: CW-A150-A-P11226 | D27: Cooling Water | E27: Water | F27: CS | H27: 510385 | I27: =HYPERLINK("\\CAD-PC\1Data\3.Documentation\Isometric DWG\Line List & Data Inspeksi\29. Isometric CO2 Liquid\" & H27 &" A" & ".pdf", "Drawing") -> Drawing
A28: =A27+1 -> 21 | B28: CW-A150-A- P50102 | D28: Cooling Water | E28: Water | F28: CS | H28: 510386 | I28: =HYPERLINK("\\CAD-PC\1Data\3.Documentation\Isometric DWG\Line List & Data Inspeksi\29. Isometric CO2 Liquid\" & H28 &" A" & ".pdf", "Drawing") -> Drawing
A29: =A28+1 -> 22 | B29: CO-A150-A-P10114 | D29: Condensate | E29: Water | F29: CS | H29: 510387 | I29: =HYPERLINK("\\CAD-PC\1Data\3.Documentation\Isometric DWG\Line List & Data Inspeksi\29. Isometric CO2 Liquid\" & H29 &" A" & ".pdf", "Drawing") -> Drawing
A30: =A29+1 -> 23 | B30: CW-A150-A- P50106 | D30: Cooling Water | E30: Water | F30: CS | H30: 510388 | I30: =HYPERLINK("\\CAD-PC\1Data\3.Documentation\Isometric DWG\Line List & Data Inspeksi\29. Isometric CO2 Liquid\" & H30 &" A" & ".pdf", "Drawing") -> Drawing
A31: =A30+1 -> 24 | B31: CW-A150-A- P50108 | D31: Cooling Water | E31: Water | F31: CS | H31: 510389 | I31: =HYPERLINK("\\CAD-PC\1Data\3.Documentation\Isometric DWG\Line List & Data Inspeksi\29. Isometric CO2 Liquid\" & H31 &" A" & ".pdf", "Drawing") -> Drawing
... A95: =A94+1 -> 88 | B95: RG-B365R-A-P38145 | D95: Refrigerant Gaseous | E95: Gas | F95: CS low temp | H95: 510457 | I95: =HYPERLINK("\\CAD-PC\1Data\3.Documentation\Isometric DWG\Line List & Data Inspeksi\29. Isometric CO2 Liquid\" & H95 &" A" & ".pdf", "Drawing") -> Drawing
A96: =A95+1 -> 89 | B96: RG-B365R-A-P47114 | C96: 2" | D96: Refrigerant Gaseous | E96: Gas | F96: CS low temp | H96: 510458 | I96: =HYPERLINK("\\CAD-PC\1Data\3.Documentation\Isometric DWG\Line List & Data Inspeksi\29. Isometric CO2 Liquid\" & H96 &" A" & ".pdf", "Drawing") -> Drawing
A97: =A96+1 -> 90 | B97: RL-B365R-A-P47108 | D97: Refrigerant Liquid | E97: Liquid | F97: CS low temp | H97: 510459 | I97: =HYPERLINK("\\CAD-PC\1Data\3.Documentation\Isometric DWG\Line List & Data Inspeksi\29. Isometric CO2 Liquid\" & H97 &" A" & ".pdf", "Drawing") -> Drawing
A98: =A97+1 -> 91 | B98: RG-A450-A-P40119 | D98: Refrigerant Gaseous | E98: Gas | F98: CS | H98: 510460 | I98: =HYPERLINK("\\CAD-PC\1Data\3.Documentation\Isometric DWG\Line List & Data Inspeksi\29. Isometric CO2 Liquid\" & H98 &" A" & ".pdf", "Drawing") -> Drawing
A99: =A98+1 -> 92 | B99: RW-E150-A-P11421 | D99: Raw Water | E99: Water | F99: SS304 | H99: 510462 | I99: =HYPERLINK("\\CAD-PC\1Data\3.Documentation\Isometric DWG\Line List & Data Inspeksi\29. Isometric CO2 Liquid\" & H99 &" A" & ".pdf", "Drawing") -> Drawing
A100: =A99+1 -> 93 | B100: RW-E150-A-P12303 | D100: Raw Water | E100: Water | F100: SS304 | H100: 510464 | I100: =HYPERLINK("\\CAD-PC\1Data\3.Documentation\Isometric DWG\Line List & Data Inspeksi\29. Isometric CO2 Liquid\" & H100 &" A" & ".pdf", "Drawing") -> Drawing
A101: =A100+1 -> 94 | B101: RW-E150-A-P12303 | D101: Raw Water | E101: Water | F101: SS304 | H101: 510465 | I101: =HYPERLINK("\\CAD-PC\1Data\3.Documentation\Isometric DWG\Line List & Data Inspeksi\29. Isometric CO2 Liquid\" & H101 &" A" & ".pdf", "Drawing") -> Drawing
A102: =A101+1 -> 95 | B102: SC-F150-A-P11208 | D102: Sodium Carbonate | E102: Chemical Solution | F102: SS316 | H102: 510466 | I102: =HYPERLINK("\\CAD-PC\1Data\3.Documentation\Isometric DWG\Line List & Data Inspeksi\29. Isometric CO2 Liquid\" & H102 &" A" & ".pdf", "Drawing") -> Drawing
A103: =A102+1 -> 96 | B103: SC-F150-A-P11203 | D103: Sodium Carbonate | E103: Chemical Solution | F103: SS316 | H103: 510467 | I103: =HYPERLINK("\\CAD-PC\1Data\3.Documentation\Isometric DWG\Line List & Data Inspeksi\29. Isometric CO2 Liquid\" & H103 &" A" & ".pdf", "Drawing") -> Drawing
A104: =A103+1 -> 97 | B104: SC-F150-A-P11204 | D104: Sodium Carbonate | E104: Chemical Solution | F104: SS316 | H104: 510468 | I104: =HYPERLINK("\\CAD-PC\1Data\3.Documentation\Isometric DWG\Line List & Data Inspeksi\29. Isometric CO2 Liquid\" & H104 &" A" & ".pdf", "Drawing") -> Drawing
A105: =A104+1 -> 98 | B105: SC-F150-A-P11202 | D105: Sodium Carbonate | E105: Chemical Solution | F105: SS316 | H105: 510470 | I105: =HYPERLINK("\\CAD-PC\1Data\3.Documentation\Isometric DWG\Line List & Data Inspeksi\29. Isometric CO2 Liquid\" & H105 &" A" & ".pdf", "Drawing") -> Drawing
A106: =A105+1 -> 99 | B106: SC-F150-A-P11201 | D106: Sodium Carbonate | E106: Chemical Solution | F106: SS316 | H106: 510471 | I106: =HYPERLINK("\\CAD-PC\1Data\3.Documentation\Isometric DWG\Line List & Data Inspeksi\29. Isometric CO2 Liquid\" & H106 &" A" & ".pdf", "Drawing") -> Drawing
A107: =A106+1 -> 100 | B107: ST-A16-P10313 | D107: Steam | E107: Steam | F107: CS | H107: 510472 | I107: =HYPERLINK("\\CAD-PC\1Data\3.Documentation\Isometric DWG\Line List & Data Inspeksi\29. Isometric CO2 Liquid\" & H107 &" A" & ".pdf", "Drawing") -> Drawing
A108: =A107+1 -> 101 | B108: ST-A16-P10310 | D108: Steam | E108: Steam | F108: CS | H108: 510473 | I108: =HYPERLINK("\\CAD-PC\1Data\3.Documentation\Isometric DWG\Line List & Data Inspeksi\29. Isometric CO2 Liquid\" & H108 &" A" & ".pdf", "Drawing") -> Drawing
... A110: =A109+1 -> 103 | B110: ST-A16-P10312 | D110: Steam | E110: Steam | F110: CS | H110: 510475 | I110: =HYPERLINK("\\CAD-PC\1Data\3.Documentation\Isometric DWG\Line List & Data Inspeksi\29. Isometric CO2 Liquid\" & H110 &" A" & ".pdf", "Drawing") -> Drawing
A111: =A110+1 -> 104 | B111: TW-E150-A-P11432 | F111: SS304 | H111: 510476 | I111: =HYPERLINK("\\CAD-PC\1Data\3.Documentation\Isometric DWG\Line List & Data Inspeksi\29. Isometric CO2 Liquid\" & H111 &" A" & ".pdf", "Drawing") -> Drawing
A112: =A111+1 -> 105 | B112: TW-E150-A-P10322 | F112: SS304 | H112: 510477 | I112: =HYPERLINK("\\CAD-PC\1Data\3.Documentation\Isometric DWG\Line List & Data Inspeksi\29. Isometric CO2 Liquid\" & H112 &" A" & ".pdf", "Drawing") -> Drawing
A114: =COUNTA(A8:A112) -> 105

Sheet 50-1
C1: EQUIPMENT LIST | F1: Document No. | I1: : MNTC-ME
F2: Revision | I2: : 0
F3: Date of issue | I3: : 2025
A4: PT. PETRO OXO NUSANTARA | F4: Page | I4: :
A5: VALVE LIST CO2 GAS
A7: NO | B7: Code | C7: Line Number piping + accecories | D7: Diameter | E7: SCH | F7: Valve | G7: Material | H7: Remark
A9: CO2 Gas
A10: 1 | B10: 134542 | C10: CG-E150A-P11502-1 | D10: 4" | E10: 10S | F10: CV1
A11: =A10+1 -> 2 | B11: 134543 | C11: CG-E150A-P12301
A12: =A11+1 -> 3 | B12: 134544 | C12: CG-E150A-P12302 | D12: 6" | E12: 10S | F12: BV1 | H12: Butterfly Valve
A13: =A12+1 -> 4 | B13: 134545 | C13: CO-A150A-P10305-1
A14: =A13+1 -> 5 | B14: 134546 | C14: CW-A150A-P50302-1 1/2
A15: =A14+1 -> 6 | B15: 134547 | C15: CW-A150A-P50302-1 2/2 | D15: 1/2" | E15: - | F15: BLV1 | H15: Ball Valve
A16: =A15+1 -> 7 | B16: 134548 | C16: CW-A150A-P50302-2
A17: =A16+1 -> 8 | B17: 134549 | C17: FG-A150A-P11201 | D17: 1/2" | E17: - | F17: BLV1 | H17: Ball Valve
A18: =A17+1 -> 9 | B18: 134550 | C18: FG-E150A-P11202 | D18: 1/2" | E18: - | F18: NDV1, BLV1 | H18: Needle & Ball Valve
A19: =A18+1 -> 10 | B19: 134551 | C19: FG-E150A-P11302 | D19: 1/2" | E19: - | F19: BLV2 | H19: Ball Valve
A20: =A19+1 -> 11 | B20: 134552 | C20: HV-11203-01 | D20: 1/2" | E20: - | F20: BLV1 | H20: Ball Valve
A21: =A20+1 -> 12 | B21: 134553 | C21: HV-11558-35 | D21: 1/2" | E21: - | F21: NDV1 | H21: Needle Valve
A22: =A21+1 -> 13 | B22: 134554 | C22: ME-E150A-P11501-3
A23: =A22+1 -> 14 | B23: 134555 | C23: ME-E150A-P10302 | D23: 1/2" | E23: - | F23: BLV1 | H23: Ball Valve
A24: =A23+1 -> 15 | B24: 134556 | C24: ME-E150A-P10402
A25: =A24+1 -> 16 | B25: 134557 | C25: ME-E150A-P10410-1
A26: =A25+1 -> 17 | B26: 134558 | C26: ME-E150A-P10410-2
A27: =A26+1 -> 18 | B27: 134559 | C27: ME-E150A-P11402-1 | D27: 1/2" | E27: - | F27: BLV1 | H27: Ball Valve
A28: =A27+1 -> 19 | B28: 134572 | C28: ME-E150A-P11403-2
A29: =A28+1 -> 20 | B29: 134835 | C29: ME-E150A-P11503-1 | D29: 1/2" | E29: - | F29: BLV1 | H29: Ball Valve
A30: =A29+1 -> 21 | B30: 134836 | C30: ME-E150A-P11504
A31: =A30+1 -> 22 | B31: 134837 | C31: PW-E150A-P10405
A32: =A31+1 -> 23 | B32: 134838 | C32: PW-E150A-P11204-1
A33: =A32+1 -> 24 | B33: 134839 | C33: PW-E150A-P11204-3
A34: =A33+1 -> 25 | B34: 134840 | C34: PW-E150A-P11208 | D34: 1" | E34: - | F34: BLV1 | H34: Ball Valve
A35: =A34+1 -> 26 | B35: 134841 | C35: PW-E150A-P11404-1
A36: =A35+1 -> 27 | B36: 134842 | C36: PW-E150A-P11405
A37: =A36+1 -> 28 | B37: 134843 | C37: PW-E150A-P11505-2
A38: =A37+1 -> 29 | B38: 134844 | C38: PW-E150A-P11558-1
A39: =A38+1 -> 30 | B39: 134845 | C39: PW-E150A-P11558 | D39: 1" | E39: - | F39: BLV1 | H39: Ball Valve
A40: =A39+1 -> 31 | B40: 134846 | C40: RW-E150A-P12303 | D40: 1" | E40: - | F40: BLV1,CV1 | H40: Ball Valve, Check Valve
D41: 1/2" | E41: - | F41: NDV1, BLV1 | H41: Needle & Ball Valve
A42: =A40+1 -> 32 | B42: 134847 | C42: SC-E150A-P11203 | D42: 1/2" | E42: - | F42: CV1 | G42: PVC | H42: Check Valve
A43: =A42+1 -> 33 | B43: 134848 | C43: ST-A150A-P10303
A45: =COUNTA(A10:A43) -> 33 | C45: Tidak ada manualoperating valve, ada drawing isometric
C46: tidak ada drawing isometric

Sheet 50
C1: ASSET LIST | G1: Document No. | J1: : MNTC-ME
G2: Revision | J2: : 0
G3: Date of issue | J3: : 2025
A4: PT. PETRO OXO NUSANTARA | G4: Page | J4: :
A5: PIPING LIST CO2 GAS
A7: No | B7: Line No. | C7: Size | D7: Service | E7: Fluid | F7: Material | G7: Insulation | H7: PAGE NO. | I7: Drawing | J7: Pipe length ( mm )
A8: 1 | B8: CG-E150A-P11502-1 | D8: Carbon Dioxide Gaseous | E8: Gas | F8: SS304 | H8: 134542 | I8: =HYPERLINK("\\CAD-PC\1Data\3.Documentation\Isometric DWG\Line List & Data Inspeksi\29. Isometric CO2 Gas\" & H8 & ".pdf", "Drawing") -> Drawing
A9: =A8+1 -> 2 | B9: CG-E150A-P12301 | D9: Carbon Dioxide Gaseous | E9: Gas | F9: SS304 | H9: 134543 | I9: =HYPERLINK("\\CAD-PC\1Data\3.Documentation\Isometric DWG\Line List & Data Inspeksi\29. Isometric CO2 Gas\" & H9 & ".pdf", "Drawing") -> Drawing
A10: =A9+1 -> 3 | B10: CG-E150A-P12302 | D10: Carbon Dioxide Gaseous | E10: Gas | F10: SS304 | H10: 134544 | I10: =HYPERLINK("\\CAD-PC\1Data\3.Documentation\Isometric DWG\Line List & Data Inspeksi\29. Isometric CO2 Gas\" & H10 & ".pdf", "Drawing") -> Drawing
A11: =A10+1 -> 4 | B11: CO-A150A-P10305-1 | D11: Condensate | E11: Water | F11: CS | H11: 134545 | I11: =HYPERLINK("\\CAD-PC\1Data\3.Documentation\Isometric DWG\Line List & Data Inspeksi\29. Isometric CO2 Gas\" & H11 & ".pdf", "Drawing") -> Drawing
A12: =A11+1 -> 5 | B12: CW-A150A-P50302-1 1/2 | D12: Cooling Water | E12: Water | F12: CS | H12: 134546 | I12: =HYPERLINK("\\CAD-PC\1Data\3.Documentation\Isometric DWG\Line List & Data Inspeksi\29. Isometric CO2 Gas\" & H12 & ".pdf", "Drawing") -> Drawing
A13: =A12+1 -> 6 | B13: CW-A150A-P50302-1 2/2 | D13: Cooling Water | E13: Water | F13: CS | H13: 134547 | I13: =HYPERLINK("\\CAD-PC\1Data\3.Documentation\Isometric DWG\Line List & Data Inspeksi\29. Isometric CO2 Gas\" & H13 & ".pdf", "Drawing") -> Drawing
A14: =A13+1 -> 7 | B14: CW-A150A-P50302-2 | D14: Cooling Water | E14: Water | F14: CS | H14: 134548 | I14: =HYPERLINK("\\CAD-PC\1Data\3.Documentation\Isometric DWG\Line List & Data Inspeksi\29. Isometric CO2 Gas\" & H14 & ".pdf", "Drawing") -> Drawing
A15: =A14+1 -> 8 | B15: FG-A150A-P11201 | D15: Flue Gas | E15: Gas | F15: CS | H15: 134549 | I15: =HYPERLINK("\\CAD-PC\1Data\3.Documentation\Isometric DWG\Line List & Data Inspeksi\29. Isometric CO2 Gas\" & H15 & ".pdf", "Drawing") -> Drawing
A16: =A15+1 -> 9 | B16: FG-E150A-P11202 | D16: Flue Gas | E16: Gas | F16: SS304 | H16: 134550 | I16: =HYPERLINK("\\CAD-PC\1Data\3.Documentation\Isometric DWG\Line List & Data Inspeksi\29. Isometric CO2 Gas\" & H16 & ".pdf", "Drawing") -> Drawing
A17: =A16+1 -> 10 | B17: FG-E150A-P11302 | D17: Flue Gas | E17: Gas | F17: SS304 | H17: 134551 | I17: =HYPERLINK("\\CAD-PC\1Data\3.Documentation\Isometric DWG\Line List & Data Inspeksi\29. Isometric CO2 Gas\" & H17 & ".pdf", "Drawing") -> Drawing
A18: =A17+1 -> 11 | B18: HV-11203-01 | H18: 134552 | I18: =HYPERLINK("\\CAD-PC\1Data\3.Documentation\Isometric DWG\Line List & Data Inspeksi\29. Isometric CO2 Gas\" & H18 & ".pdf", "Drawing") -> Drawing
A19: =A18+1 -> 12 | B19: HV-11558-35 | H19: 134553 | I19: =HYPERLINK("\\CAD-PC\1Data\3.Documentation\Isometric DWG\Line List & Data Inspeksi\29. Isometric CO2 Gas\" & H19 & ".pdf", "Drawing") -> Drawing
A20: =A19+1 -> 13 | B20: ME-E150A-P11501-3 | D20: Monoethanolamine Solution | E20: Chemical Solution | F20: SS304 | H20: 134554 | I20: =HYPERLINK("\\CAD-PC\1Data\3.Documentation\Isometric DWG\Line List & Data Inspeksi\29. Isometric CO2 Gas\" & H20 & ".pdf", "Drawing") -> Drawing
A21: =A20+1 -> 14 | B21: ME-E150A-P10302 | D21: Monoethanolamine Solution | E21: Chemical Solution | F21: SS304 | H21: 134555 | I21: =HYPERLINK("\\CAD-PC\1Data\3.Documentation\Isometric DWG\Line List & Data Inspeksi\29. Isometric CO2 Gas\" & H21 & ".pdf", "Drawing") -> Drawing
A22: =A21+1 -> 15 | B22: ME-E150A-P10402 | D22: Monoethanolamine Solution | E22: Chemical Solution | F22: SS304 | H22: 134556 | I22: =HYPERLINK("\\CAD-PC\1Data\3.Documentation\Isometric DWG\Line List & Data Inspeksi\29. Isometric CO2 Gas\" & H22 & ".pdf", "Drawing") -> Drawing
A23: =A22+1 -> 16 | B23: ME-E150A-P10410-1 | D23: Monoethanolamine Solution | E23: Chemical Solution | F23: SS304 | H23: 134557 | I23: =HYPERLINK("\\CAD-PC\1Data\3.Documentation\Isometric DWG\Line List & Data Inspeksi\29. Isometric CO2 Gas\" & H23 & ".pdf", "Drawing") -> Drawing
A24: =A23+1 -> 17 | B24: ME-E150A-P10410-2 | D24: Monoethanolamine Solution | E24: Chemical Solution | F24: SS304 | H24: 134558 | I24: =HYPERLINK("\\CAD-PC\1Data\3.Documentation\Isometric DWG\Line List & Data Inspeksi\29. Isometric CO2 Gas\" & H24 & ".pdf", "Drawing") -> Drawing
A25: =A24+1 -> 18 | B25: ME-E150A-P11402-1 | D25: Monoethanolamine Solution | E25: Chemical Solution | F25: SS304 | H25: 134559 | I25: =HYPERLINK("\\CAD-PC\1Data\3.Documentation\Isometric DWG\Line List & Data Inspeksi\29. Isometric CO2 Gas\" & H25 & ".pdf", "Drawing") -> Drawing
A26: =A25+1 -> 19 | B26: ME-E150A-P11403-2 | D26: Monoethanolamine Solution | E26: Chemical Solution | F26: SS304 | H26: 134572 | I26: =HYPERLINK("\\CAD-PC\1Data\3.Documentation\Isometric DWG\Line List & Data Inspeksi\29. Isometric CO2 Gas\" & H26 & ".pdf", "Drawing") -> Drawing
A27: =A26+1 -> 20 | B27: ME-E150A-P11503-1 | D27: Monoethanolamine Solution | E27: Chemical Solution | F27: SS304 | H27: 134835 | I27: =HYPERLINK("\\CAD-PC\1Data\3.Documentation\Isometric DWG\Line List & Data Inspeksi\29. Isometric CO2 Gas\" & H27 & ".pdf", "Drawing") -> Drawing
A28: =A27+1 -> 21 | B28: ME-E150A-P11504 | D28: Monoethanolamine Solution | E28: Chemical Solution | F28: SS304 | H28: 134836 | I28: =HYPERLINK("\\CAD-PC\1Data\3.Documentation\Isometric DWG\Line List & Data Inspeksi\29. Isometric CO2 Gas\" & H28 & ".pdf", "Drawing") -> Drawing
A29: =A28+1 -> 22 | B29: PW-E150A-P10405 | D29: Process Water | E29: Gas | F29: SS304 | H29: 134837 | I29: =HYPERLINK("\\CAD-PC\1Data\3.Documentation\Isometric DWG\Line List & Data Inspeksi\29. Isometric CO2 Gas\" & H29 & ".pdf", "Drawing") -> Drawing
A30: =A29+1 -> 23 | B30: PW-E150A-P11204-1 | D30: Process Water | E30: Gas | F30: SS304 | H30: 134838 | I30: =HYPERLINK("\\CAD-PC\1Data\3.Documentation\Isometric DWG\Line List & Data Inspeksi\29. Isometric CO2 Gas\" & H30 & ".pdf", "Drawing") -> Drawing
A31: =A30+1 -> 24 | B31: PW-E150A-P11204-3 | D31: Process Water | E31: Gas | F31: SS304 | H31: 134839 | I31: =HYPERLINK("\\CAD-PC\1Data\3.Documentation\Isometric DWG\Line List & Data Inspeksi\29. Isometric CO2 Gas\" & H31 & ".pdf", "Drawing") -> Drawing
... A40: =A39+1 -> 33 | B40: ST-A150A-P10303 | D40: Steam | E40: Steam | F40: CS | H40: 134848 | I40: =HYPERLINK("\\CAD-PC\1Data\3.Documentation\Isometric DWG\Line List & Data Inspeksi\29. Isometric CO2 Gas\" & H40 & ".pdf", "Drawing") -> Drawing
A42: =COUNTA(A8:A40) -> 33

Sheet 49-1
C1: EQUIPMENT LIST | F1: Document No. | H1: : MNTC-ME
F2: Revision | H2: : 0
F3: Date of issue | H3: : 2025
A4: PT. PETRO OXO NUSANTARA | F4: Page | H4: :
A5: VALVE LIST UTILITY
A7: NO | B7: Code | C7: Line Number piping + accecories | D7: Diameter | E7: Rating | F7: Valve | G7: Material | H7: Remark
A9: UTILITY
A10: 1 | B10: G011 | C10: 2"-BBD-9201 -AG 1B-H25 | D10: =LEFT(C10, FIND("""", C10)) -> 2" | I10: 1
A11: 2 | B11: G021 | C11: 2"-BFW-8507-AG 1B-P | D11: =LEFT(C11, FIND("""", C11)) -> 2" | I11: 1
A12: 3 | B12: G022 | C12: 2"-BFW-8505-AG 1B-P (1/2) (2/2) | D12: =LEFT(C12, FIND("""", C12)) -> 2" | E12: 150 | F12: GV | I12: 1
D13: 1/2" | E13: 150 | F13: GV
D14: 2" | E14: 150 | F14: CV
A15: 4 | B15: G023 | C15: 3"-BFW-8503-AG 1 B-P | D15: =LEFT(C15, FIND("""", C15)) -> 3" | E15: 150 | F15: GV | I15: 1
D16: 1/2" | E16: 150 | F16: GV
A17: 5 | B17: G024 | C17: 2-1/2"-BFW-8508- AG1B-P | D17: =LEFT(C17, FIND("""", C17)) -> 2-1/2" | I17: 1
A18: 6 | B18: G025 | C18: 8"-BFW-9201 -AG 1B-H25 | D18: =LEFT(C18, FIND("""", C18)) -> 8" | I18: 1
A19: 7 | B19: G026 | C19: 8"-BFW-9201-AG 1B-H25 | D19: =LEFT(C19, FIND("""", C19)) -> 8" | E19: 150 | F19: GV1 | G19: SS | I19: 1
D20: 3/4" | E20: 150 | F20: GV1 | G20: SS | I20: 1
A21: 8 | B21: G027 | C21: 8"-BFW-9201 -AG 1B-H25 | D21: =LEFT(C21, FIND("""", C21)) -> 8" | E21: 150 | F21: GV1 | I21: 1
A22: 9 | B22: G028 | C22: 4"-BFW-9202-BG4A- H25 | D22: =LEFT(C22, FIND("""", C22)) -> 4" | I22: 1
A23: 10 | B23: G029 | C23: 6"-BFW-9202-BG4A-H25 (1/2) | D23: =LEFT(C23, FIND("""", C23)) -> 6" | E23: 300 | F23: GV1 | I23: 1
A24: 11 | B24: G030 | C24: 6"-BFW-9202-BG4A-H25 (2/2) | D24: =LEFT(C24, FIND("""", C24)) -> 6" | E24: 300 | F24: GV1 | I24: 1
A25: 12 | B25: G031 | C25: 3"-BFW-9205-AG1 B-H25 | D25: =LEFT(C25, FIND("""", C25)) -> 3" | I25: 1
A26: 13 | B26: G032 | C26: 3"-BFW-9205-AG 1B-H25 | D26: =LEFT(C26, FIND("""", C26)) -> 3" | E26: 300 | F26: GV1 | I26: 1
A27: 14 | B27: G033 | C27: 3"-BFW-9205-AG 1B-H25 | D27: =LEFT(C27, FIND("""", C27)) -> 3" | E27: 300 | F27: GV1 | I27: 1
A28: 15 | B28: G051 | C28: 2"-CWR-9421 -AG 1A | D28: =LEFT(C28, FIND("""", C28)) -> 2" | I28: 1
A29: 16 | B29: G052 | C29: 2"-CWR-8000-AG1A | D29: =LEFT(C29, FIND("""", C29)) -> 2" | I29: 1
A30: 17 | B30: G061 | C30: 2"-CWR-9406-AG 1A | D30: =LEFT(C30, FIND("""", C30)) -> 2" | E30: 150 | F30: BV | I30: 1
A31: 18 | B31: G062 | C31: 20"-CWR-9451-AG1A | D31: =LEFT(C31, FIND("""", C31)) -> 20" | E31: 150 | F31: BV2 | I31: 1
A32: 19 | B32: G063 | C32: 4"-CWR-8501-AG1A | D32: =LEFT(C32, FIND("""", C32)) -> 4" | E32: 150 | F32: GLV | I32: 1
A33: 20 | B33: G064 | C33: 2"-CWR-8000-AG 1A | D33: =LEFT(C33, FIND("""", C33)) -> 2" | E33: 150 | F33: GV1 | I33: 1
A34: 21 | B34: G065 | C34: 8"-CWR-9401 -AG 1A | D34: =LEFT(C34, FIND("""", C34)) -> 8"
A35: 22 | B35: G067 | C35: 4"-CWR-9410-AG1A | D35: =LEFT(C35, FIND("""", C35)) -> 4" | E35: 150 | F35: BV1 | I35: 1
A36: 23 | B36: G068 | C36: 2"-WCR-9403-AG 1A | D36: =LEFT(C36, FIND("""", C36)) -> 2" | E36: 150 | F36: BV2 | I36: 1
A37: 24 | B37: G091 | C37: 28"-CWS-9400-AG 1A | D37: =LEFT(C37, FIND("""", C37)) -> 28" | E37: 150 | F37: BV1 | I37: 1
A38: 25 | B38: G092 | C38: 28"-CWS-9400-AG 1A | D38: =LEFT(C38, FIND("""", C38)) -> 28" | E38: 150 | F38: BV1 | I38: 1
A39: 26 | B39: G093 | C39: 2"-CWS-9406-AG 1A | D39: =LEFT(C39, FIND("""", C39)) -> 2" | I39: 1
A40: 27 | B40: G094 | C40: 6"-CWS-9407-AG 1A | D40: =LEFT(C40, FIND("""", C40)) -> 6" | I40: 1
A41: 28 | B41: G095 | C41: 20"-CWS-9451 -AG 1A (1/2) (2/2) | D41: =LEFT(C41, FIND("""", C41)) -> 20" | E41: 150 | F41: CV | I41: 1
D42: 20" | E42: 150 | F42: BV
D43: 3/4" | E43: 150 | F43: GV2
D44: 1/2" | E44: 150 | F44: GV
A45: 29 | B45: G096 | C45: 20"-CWS-9451 -AG 1A (1/2) (2/2) | D45: =LEFT(C45, FIND("""", C45)) -> 20" | E45: 150 | F45: CV | I45: 1
D46: 20" | E46: 150 | F46: BV
D47: 3/4"" | E47: 150 | F47: GV2
D48: 1/2" | E48: 150 | F48: GV
A49: 30 | B49: G097 | C49: 6"-CWS-9406-AG 1A | D49: =LEFT(C49, FIND("""", C49)) -> 6" | E49: 150 | F49: BV | I49: 1
D50: 1/2" | E50: 150 | F50: GV
A51: 31 | B51: G098 | C51: 4"-CWS-8501 -AG 1A | D51: =LEFT(C51, FIND("""", C51)) -> 4" | E51: 150 | F51: GV | I51: 1
D52: 1/2" | E52: 150 | F52: GV
A53: 32 | B53: G099 | C53: 8"-CWS-9401-AG 1A | D53: =LEFT(C53, FIND("""", C53)) -> 8"
A54: 33 | B54: G101 | C54: 4"-CWS-9410-AG1A | D54: =LEFT(C54, FIND("""", C54)) -> 4" | E54: 150 | F54: BV1 | I54: 1
A55: 34 | B55: G102 | C55: 2"-CWS-9403-AG 1A | D55: =LEFT(C55, FIND("""", C55)) -> 2" | E55: 150 | F55: CV1 | I55: 1
D56: 2" | E56: 150 | F56: BV3
A57: 35 | B57: G121 | C57: 4"-DMW-9301-AS1A | D57: =LEFT(C57, FIND("""", C57)) -> 4" | I57: 1
A58: 36 | B58: G122 | C58: 6"-DMW-9302-AS1A | D58: =LEFT(C58, FIND("""", C58)) -> 6" | E58: 150 | F58: BV1 | I58: 1
A59: 37 | B59: G123 | C59: 4"-DMW-9302-AS1A | D59: =LEFT(C59, FIND("""", C59)) -> 4" | E59: 150 | F59: GV2 | I59: 1
D60: 3/4" | E60: 150 | F60: GV2
A61: 38 | B61: G124 | C61: 4"-DM W-9303-AS1A (1/2) (2/2) | D61: =LEFT(C61, FIND("""", C61)) -> 4" | E61: 150 | F61: GV2 | I61: 1
D62: 3/4" | E62: 150 | F62: GV2
D63: 1/2" | E63: 150 | F63: GV2
A64: 39 | B64: G125 | C64: 4"-D M W-9304-AS1A | D64: =LEFT(C64, FIND("""", C64)) -> 4" | E64: 150 | F64: GV2 | I64: 1
D65: 3/4" | E65: 150 | F65: GV2
A66: 40 | B66: G126 | C66: 4"-DMW-9305-AS1A (1/2) (2/2) | D66: =LEFT(C66, FIND("""", C66)) -> 4" | E66: 150 | F66: GV2 | I66: 1
D67: 3/4" | E67: 150 | F67: GV2
D68: 1/2" | E68: 150 | F68: GV2
A69: 41 | B69: G127 | C69: 4"-DM W-9305-AS1A | D69: =LEFT(C69, FIND("""", C69)) -> 4" | I69: 1
A70: 42 | B70: G128 | C70: 3"-DMW-9308-AS1A | D70: =LEFT(C70, FIND("""", C70)) -> 3" | E70: 150 | F70: GV1 | I70: 1
A71: 43 | B71: G129 | C71: 3"-DMW-9311-AG1A | D71: =LEFT(C71, FIND("""", C71)) -> 3" | I71: 1
A72: 44 | B72: G141 | C72: 18"-FFW-7501 -AG 1A (1/2) (2/2) | D72: =LEFT(C72, FIND("""", C72)) -> 18" | E72: 150 | F72: GV | I72: 1
D73: 12" | E73: 150 | F73: GV
D74: 3/4" | E74: 150 | F74: GV
D75: 1/2" | E75: 150 | F75: GV
A76: 45 | B76: G142 | C76: 4"-FFW-7502-AG1A | D76: =LEFT(C76, FIND("""", C76)) -> 4" | E76: 150 | F76: BV | I76: 1
D77: 3/4" | E77: 150 | F77: GV
A78: 46 | B78: G143 | C78: 12"-FFW-7503-AG1A (1/2) (2/2) | D78: =LEFT(C78, FIND("""", C78)) -> 12" | E78: 150 | F78: BV | I78: 1
D79: 12" | E79: 150 | F79: CV
D80: 1/2" | E80: 150 | F80: GV
A81: 47 | B81: G144 | C81: 12"-FFW-7503-AG 1A (1/2) (2/2) | D81: =LEFT(C81, FIND("""", C81)) -> 12" | E81: 150 | F81: CV | I81: 1
D82: 12" | E82: 150 | F82: BV
D83: 3/4" | E83: 150 | F83: GV
D84: 1/2" | E84: 150 | F84: GV2
A85: 48 | B85: G145 | C85: 12"-FFW-7503-AG 1A (1/2) (2/2) | D85: =LEFT(C85, FIND("""", C85)) -> 12" | E85: 150 | F85: CV | I85: 1
D86: 12" | E86: 150 | F86: BV
D87: 3/4" | E87: 150 | F87: GV
D88: 1/2" | E88: 150 | F88: GV2
A89: 49 | B89: G146 | C89: 4"-FFW-7504-AG1A (1/2) (2/2) | D89: =LEFT(C89, FIND("""", C89)) -> 4" | E89: 150 | F89: CV | I89: 1
D90: 4" | E90: 150 | F90: BV
D91: 3/4" | E91: 150 | F91: GV
D92: 1/2" | E92: 150 | F92: GV
A93: 50 | B93: G147 | C93: 12"-FFW-7505-AG1A | D93: =LEFT(C93, FIND("""", C93)) -> 12" | E93: 150 | F93: BV | I93: 1
D94: 8" | E94: 150 | F94: BV
A95: 51 | B95: G148 | C95: 12"-FFW-7505-AG1A | D95: =LEFT(C95, FIND("""", C95)) -> 12" | E95: 150 | F95: BV | I95: 1
D96: 8" | E96: 150 | F96: BV
A97: 52 | B97: G149 | C97: 12"-FFW-7505-AG 1A | D97: =LEFT(C97, FIND("""", C97)) -> 12" | E97: 150 | F97: BV | I97: 1
D98: 8" | E98: 150 | F98: BV
A99: 53 | B99: G150 | C99: 12"-FFW-7505-AG 1A | D99: 3/4" | E99: 150 | F99: GV | I99: 1
A100: 54 | B100: G151 | C100: 12"-FFW-7505-AG 1A | D100: 3/4" | E100: 150 | F100: GV | I100: 1
A101: 55 | B101: G152 | C101: 2-1/2"-FFW-7506- AG1A | D101: =LEFT(C101, FIND("""", C101)) -> 2-1/2" | E101: 150 | F101: BV | I101: 1
A102: 56 | B102: G161 | C102: 2"-FNG-8501 -AG 1C | D102: =LEFT(C102, FIND("""", C102)) -> 2" | I102: 1
...

Sheet 49
C1: EQUIPMENT LIST | G1: Document No. | J1: : MNTC-ME
G2: Revision | J2: : 0
G3: Date of issue | J3: : 2025
A4: PT. PETRO OXO NUSANTARA | G4: Page | J4: :
A5: PIPING LIST UTILITY & TANK YARD
A7: No | B7: Line No. | C7: Size | D7: Service | E7: Fluid | F7: Material | G7: Insulation | H7: Drawing | I7: PAGE NO. | J7: Pipe length ( mm )
A8: 1 | B8: 2"-BBD-9201 -AG 1B-H25 | C8: =LEFT(B8, FIND("""", B8)) -> 2" | D8: Boiler Blow Down | E8: Water | F8: CS | G8: Hot | H8: =HYPERLINK("\\CAD-PC\1Data\3.Documentation\Isometric DWG MHI\" & I8 & ".pdf", "Drawing") -> Drawing | I8: G011
A9: 2 | B9: 2"-BFW-8507-AG 1B-P | C9: =LEFT(B9, FIND("""", B9)) -> 2" | D9: Boiler Feed Water | E9: Water | F9: CS | H9: =HYPERLINK("\\CAD-PC\1Data\3.Documentation\Isometric DWG MHI\" & I9 & ".pdf", "Drawing") -> Drawing | I9: G021
A10: 3 | B10: 2"-BFW-8505-AG 1B-P (1/2) (2/2) | C10: =LEFT(B10, FIND("""", B10)) -> 2" | D10: Boiler Feed Water | E10: Water | F10: CS | H10: =HYPERLINK("\\CAD-PC\1Data\3.Documentation\Isometric DWG MHI\" & I10 & ".pdf", "Drawing") -> Drawing | I10: G022
A11: 4 | B11: 3"-BFW-8503-AG 1 B-P | C11: =LEFT(B11, FIND("""", B11)) -> 3" | D11: Boiler Feed Water | E11: Water | F11: CS | H11: =HYPERLINK("\\CAD-PC\1Data\3.Documentation\Isometric DWG MHI\" & I11 & ".pdf", "Drawing") -> Drawing | I11: G023
A12: 5 | B12: 2-1/2"-BFW-8508- AG1B-P | C12: =LEFT(B12, FIND("""", B12)) -> 2-1/2" | D12: Boiler Feed Water | E12: Water | F12: CS | H12: =HYPERLINK("\\CAD-PC\1Data\3.Documentation\Isometric DWG MHI\" & I12 & ".pdf", "Drawing") -> Drawing | I12: G024
A13: 6 | B13: 8"-BFW-9201 -AG 1B-H25 | C13: =LEFT(B13, FIND("""", B13)) -> 8" | D13: Boiler Feed Water | E13: Water | F13: CS | G13: Hot | H13: =HYPERLINK("\\CAD-PC\1Data\3.Documentation\Isometric DWG MHI\" & I13 & ".pdf", "Drawing") -> Drawing | I13: G025
A14: 7 | B14: 8"-BFW-9201-AG 1B-H25 | C14: =LEFT(B14, FIND("""", B14)) -> 8" | D14: Boiler Feed Water | E14: Water | F14: CS | G14: Hot | H14: =HYPERLINK("\\CAD-PC\1Data\3.Documentation\Isometric DWG MHI\" & I14 & ".pdf", "Drawing") -> Drawing | I14: G026
A15: 8 | B15: 8"-BFW-9201 -AG 1B-H25 | C15: =LEFT(B15, FIND("""", B15)) -> 8" | D15: Boiler Feed Water | E15: Water | F15: CS | G15: Hot | H15: =HYPERLINK("\\CAD-PC\1Data\3.Documentation\Isometric DWG MHI\" & I15 & ".pdf", "Drawing") -> Drawing | I15: G027
A16: 9 | B16: 4"-BFW-9202-BG4A- H25 | C16: =LEFT(B16, FIND("""", B16)) -> 4" | D16: Boiler Feed Water | E16: Water | F16: CS | G16: Hot | H16: =HYPERLINK("\\CAD-PC\1Data\3.Documentation\Isometric DWG MHI\" & I16 & ".pdf", "Drawing") -> Drawing | I16: G028
A17: 10 | B17: 6"-BFW-9202-BG4A-H25 (1/2) | C17: =LEFT(B17, FIND("""", B17)) -> 6" | D17: Boiler Feed Water | E17: Water | F17: CS | G17: Hot | H17: =HYPERLINK("\\CAD-PC\1Data\3.Documentation\Isometric DWG MHI\" & I17 & ".pdf", "Drawing") -> Drawing | I17: G029
A18: 11 | B18: 6"-BFW-9202-BG4A-H25 (2/2) | C18: =LEFT(B18, FIND("""", B18)) -> 6" | D18: Boiler Feed Water | E18: Water | F18: CS | G18: Hot | H18: =HYPERLINK("\\CAD-PC\1Data\3.Documentation\Isometric DWG MHI\" & I18 & ".pdf", "Drawing") -> Drawing | I18: G030
A19: 12 | B19: 3"-BFW-9205-AG1 B-H25 | C19: =LEFT(B19, FIND("""", B19)) -> 3" | D19: Boiler Feed Water | E19: Water | F19: CS | G19: Hot | H19: =HYPERLINK("\\CAD-PC\1Data\3.Documentation\Isometric DWG MHI\" & I19 & ".pdf", "Drawing") -> Drawing | I19: G031
A20: 13 | B20: 3"-BFW-9205-AG 1B-H25 | C20: =LEFT(B20, FIND("""", B20)) -> 3" | D20: Boiler Feed Water | E20: Water | F20: CS | G20: Hot | H20: =HYPERLINK("\\CAD-PC\1Data\3.Documentation\Isometric DWG MHI\" & I20 & ".pdf", "Drawing") -> Drawing | I20: G032
A21: 14 | B21: 3"-BFW-9205-AG 1B-H25 | C21: =LEFT(B21, FIND("""", B21)) -> 3" | D21: Boiler Feed Water | E21: Water | F21: CS | G21: Hot | H21: =HYPERLINK("\\CAD-PC\1Data\3.Documentation\Isometric DWG MHI\" & I21 & ".pdf", "Drawing") -> Drawing | I21: G033
A22: 15 | B22: 2"-CWR-9421 -AG 1A | C22: =LEFT(B22, FIND("""", B22)) -> 2" | D22: Cooling Water | E22: Water | F22: CS | H22: =HYPERLINK("\\CAD-PC\1Data\3.Documentation\Isometric DWG MHI\" & I22 & ".pdf", "Drawing") -> Drawing | I22: G051
A23: 16 | B23: 2"-CWR-8000-AG1A | C23: =LEFT(B23, FIND("""", B23)) -> 2" | D23: Cooling Water | E23: Water | F23: CS | H23: =HYPERLINK("\\CAD-PC\1Data\3.Documentation\Isometric DWG MHI\" & I23 & ".pdf", "Drawing") -> Drawing | I23: G052
A24: 17 | B24: 2"-CWR-9406-AG 1A | C24: =LEFT(B24, FIND("""", B24)) -> 2" | D24: Cooling Water | E24: Water | F24: CS | H24: =HYPERLINK("\\CAD-PC\1Data\3.Documentation\Isometric DWG MHI\" & I24 & ".pdf", "Drawing") -> Drawing | I24: G061
A25: 18 | B25: 20"-CWR-9451-AG1A | C25: =LEFT(B25, FIND("""", B25)) -> 20" | D25: Cooling Water | E25: Water | F25: CS | H25: =HYPERLINK("\\CAD-PC\1Data\3.Documentation\Isometric DWG MHI\" & I25 & ".pdf", "Drawing") -> Drawing | I25: G062
A26: 19 | B26: 4"-CWR-8501-AG1A | C26: =LEFT(B26, FIND("""", B26)) -> 4" | D26: Cooling Water | E26: Water | F26: CS | H26: =HYPERLINK("\\CAD-PC\1Data\3.Documentation\Isometric DWG MHI\" & I26 & ".pdf", "Drawing") -> Drawing | I26: G063
A27: 20 | B27: 2"-CWR-8000-AG 1A | C27: =LEFT(B27, FIND("""", B27)) -> 2" | D27: Cooling Water | E27: Water | F27: CS | H27: =HYPERLINK("\\CAD-PC\1Data\3.Documentation\Isometric DWG MHI\" & I27 & ".pdf", "Drawing") -> Drawing | I27: G064
A28: 21 | B28: 8"-CWR-9401 -AG 1A | C28: =LEFT(B28, FIND("""", B28)) -> 8" | D28: Cooling Water | E28: Water | F28: CS | H28: =HYPERLINK("\\CAD-PC\1Data\3.Documentation\Isometric DWG MHI\" & I28 & ".pdf", "Drawing") -> Drawing | I28: G065
A29: 22 | B29: 4"-CWR-9410-AG1A | C29: =LEFT(B29, FIND("""", B29)) -> 4" | D29: Cooling Water | E29: Water | F29: CS | H29: =HYPERLINK("\\CAD-PC\1Data\3.Documentation\Isometric DWG MHI\" & I29 & ".pdf", "Drawing") -> Drawing | I29: G067
A30: 23 | B30: 2"-WCR-9403-AG 1A | C30: =LEFT(B30, FIND("""", B30)) -> 2" | D30: Cooling Water | E30: Water | F30: CS | H30: =HYPERLINK("\\CAD-PC\1Data\3.Documentation\Isometric DWG MHI\" & I30 & ".pdf", "Drawing") -> Drawing | I30: G068
A31: 24 | B31: 28"-CWS-9400-AG 1A | C31: =LEFT(B31, FIND("""", B31)) -> 28" | D31: Cooling Water | E31: Water | F31: CS | H31: =HYPERLINK("\\CAD-PC\1Data\3.Documentation\Isometric DWG MHI\" & I31 & ".pdf", "Drawing") -> Drawing | I31: G091
A32: 25 | B32: 28"-CWS-9400-AG 1A | C32: =LEFT(B32, FIND("""", B32)) -> 28" | D32: Cooling Water | E32: Water | F32: CS | H32: =HYPERLINK("\\CAD-PC\1Data\3.Documentation\Isometric DWG MHI\" & I32 & ".pdf", "Drawing") -> Drawing | I32: G092
A33: 26 | B33: 2"-CWS-9406-AG 1A | C33: =LEFT(B33, FIND("""", B33)) -> 2" | D33: Cooling Water | E33: Water | F33: CS | H33: =HYPERLINK("\\CAD-PC\1Data\3.Documentation\Isometric DWG MHI\" & I33 & ".pdf", "Drawing") -> Drawing | I33: G093
... A82: 75 | B82: 3"-G PI -9901 -AG 1A | C82: =LEFT(B82, FIND("""", B82)) -> 3" | D82: Instrument Air | E82: Air | F82: CS | H82: =HYPERLINK("\\CAD-PC\1Data\3.Documentation\Isometric DWG MHI\" & I82 & ".pdf", "Drawing") -> Drawing | I82: G245
A83: 76 | B83: 6"-LPC-9202-AS 1A-H30 | C83: =LEFT(B83, FIND("""", B83)) -> 6" | D83: Condensate | E83: Water | F83: SS304 | G83: Hot | H83: =HYPERLINK("\\CAD-PC\1Data\3.Documentation\Isometric DWG MHI\" & I83 & ".pdf", "Drawing") -> Drawing | I83: G271
A84: 77 | B84: 6"-LPC-9202-AG 1B-H30 | C84: =LEFT(B84, FIND("""", B84)) -> 6" | D84: Condensate | E84: Water | F84: CS | G84: Hot | H84: =HYPERLINK("\\CAD-PC\1Data\3.Documentation\Isometric DWG MHI\" & I84 & ".pdf", "Drawing") -> Drawing | I84: G272
A85: 78 | B85: 2"-LPS-8504-AG 1A | C85: =LEFT(B85, FIND("""", B85)) -> 2" | D85: Low Pressure Steam | E85: Steam | F85: CS | H85: =HYPERLINK("\\CAD-PC\1Data\3.Documentation\Isometric DWG MHI\" & I85 & ".pdf", "Drawing") -> Drawing | I85: G281
A86: 79 | B86: 6"-LPS-9201 -AG1B-H30 (1/2) (2/2) | C86: =LEFT(B86, FIND("""", B86)) -> 6" | D86: Low Pressure Steam | E86: Steam | F86: CS | G86: Hot | H86: =HYPERLINK("\\CAD-PC\1Data\3.Documentation\Isometric DWG MHI\" & I86 & ".pdf", "Drawing") -> Drawing | I86: G282
A87: 80 | B87: 10"-MPS-9210-BG4A-H40 | C87: =LEFT(B87, FIND("""", B87)) -> 10" | D87: Medium Pressure Steam | E87: Steam | F87: CS | G87: Hot | H87: =HYPERLINK("\\CAD-PC\1Data\3.Documentation\Isometric DWG MHI\" & I87 & ".pdf", "Drawing") -> Drawing | I87: G311
A88: 81 | B88: 8"-M PS-9210-BG4A-H40 | C88: =LEFT(B88, FIND("""", B88)) -> 8" | D88: Medium Pressure Steam | E88: Steam | F88: CS | G88: Hot | H88: =HYPERLINK("\\CAD-PC\1Data\3.Documentation\Isometric DWG MHI\" & I88 & ".pdf", "Drawing") -> Drawing | I88: G312
A89: 82 | B89: 3"-NGS-9902-AG 1A | C89: =LEFT(B89, FIND("""", B89)) -> 3" | D89: Nitrogen Gas | E89: Gas | F89: CS | H89: =HYPERLINK("\\CAD-PC\1Data\3.Documentation\Isometric DWG MHI\" & I89 & ".pdf", "Drawing") -> Drawing | I89: G331
A90: 83 | B90: 3"-NGS-9904-AG 1A | C90: =LEFT(B90, FIND("""", B90)) -> 3" | D90: Nitrogen Gas | E90: Gas | F90: CS | H90: =HYPERLINK("\\CAD-PC\1Data\3.Documentation\Isometric DWG MHI\" & I90 & ".pdf", "Drawing") -> Drawing | I90: G332
A91: 84 | B91: 3"-NGS-9901 -AG 1A | C91: =LEFT(B91, FIND("""", B91)) -> 3" | D91: Nitrogen Gas | E91: Gas | F91: CS | H91: =HYPERLINK("\\CAD-PC\1Data\3.Documentation\Isometric DWG MHI\" & I91 & ".pdf", "Drawing") -> Drawing | I91: G333
A92: 85 | B92: 3"-NGS-9901 -AG 1A | C92: =LEFT(B92, FIND("""", B92)) -> 3" | D92: Nitrogen Gas | E92: Gas | F92: CS | H92: =HYPERLINK("\\CAD-PC\1Data\3.Documentation\Isometric DWG MHI\" & I92 & ".pdf", "Drawing") -> Drawing | I92: G334
A93: 86 | B93: 4"-P-8502-AG1A | C93: =LEFT(B93, FIND("""", B93)) -> 4" | D93: Process | E93: Chemical Solution | F93: CS | H93: =HYPERLINK("\\CAD-PC\1Data\3.Documentation\Isometric DWG MHI\" & I93 & ".pdf", "Drawing") -> Drawing | I93: G351
A94: 87 | B94: 4"-P-8501-AG1A | C94: =LEFT(B94, FIND("""", B94)) -> 4" | D94: Process | E94: Chemical Solution | F94: CS | H94: =HYPERLINK("\\CAD-PC\1Data\3.Documentation\Isometric DWG MHI\" & I94 & ".pdf", "Drawing") -> Drawing | I94: G352
A95: 88 | B95: 16"-P-8503-AS1 A-P | C95: =LEFT(B95, FIND("""", B95)) -> 16" | D95: Process | E95: Chemical Solution | F95: SS304 | H95: =HYPERLINK("\\CAD-PC\1Data\3.Documentation\Isometric DWG MHI\" & I95 & ".pdf", "Drawing") -> Drawing | I95: G353
A96: 89 | B96: 16"-P-8504-AS1 A-P | C96: =LEFT(B96, FIND("""", B96)) -> 16" | D96: Process | E96: Chemical Solution | F96: SS304 | H96: =HYPERLINK("\\CAD-PC\1Data\3.Documentation\Isometric DWG MHI\" & I96 & ".pdf", "Drawing") -> Drawing | I96: G354
A97: 90 | B97: 16"-P-8505-AS1 A-P | C97: =LEFT(B97, FIND("""", B97)) -> 16" | D97: Process | E97: Chemical Solution | F97: SS304 | H97: =HYPERLINK("\\CAD-PC\1Data\3.Documentation\Isometric DWG MHI\" & I97 & ".pdf", "Drawing") -> Drawing | I97: G355
A98: 91 | B98: 3"-P-8506-AG1C | C98: =LEFT(B98, FIND("""", B98)) -> 3" | D98: Process | E98: Chemical Solution | F98: CS | H98: =HYPERLINK("\\CAD-PC\1Data\3.Documentation\Isometric DWG MHI\" & I98 & ".pdf", "Drawing") -> Drawing | I98: G356
A99: 92 | B99: 4"-PC-9204-AG 1B | C99: =LEFT(B99, FIND("""", B99)) -> 4" | D99: Process Condensate | E99: Process | F99: CS | H99: =HYPERLINK("\\CAD-PC\1Data\3.Documentation\Isometric DWG MHI\" & I99 & ".pdf", "Drawing") -> Drawing | I99: G371
A100: 93 | B100: 2"-PWS-9301-AG2A | C100: =LEFT(B100, FIND("""", B100)) -> 2" | D100: Potable Water | E100: Water | F100: CS | H100: =HYPERLINK("\\CAD-PC\1Data\3.Documentation\Isometric DWG MHI\" & I100 & ".pdf", "Drawing") -> Drawing | I100: G401
... A109: 102 | B109: 3"-SHY-8001 -AG 1C | C109: =LEFT(B109, FIND("""", B109)) -> 3" | D109: Caustic Soda | E109: Chemical Solution | F109: CS | H109: =HYPERLINK("\\CAD-PC\1Data\3.Documentation\Isometric DWG MHI\" & I109 & ".pdf", "Drawing") -> Drawing | I109: G481
A110: 103 | B110: 6"-WAR-8001-AG1A | C110: =LEFT(B110, FIND("""", B110)) -> 6" | F110: CS | H110: =HYPERLINK("\\CAD-PC\1Data\3.Documentation\Isometric DWG MHI\" & I110 & ".pdf", "Drawing") -> Drawing | I110: G511
A111: 104 | B111: 2"-WAR-8005-AG 1A | C111: =LEFT(B111, FIND("""", B111)) -> 2" | F111: CS | H111: =HYPERLINK("\\CAD-PC\1Data\3.Documentation\Isometric DWG MHI\" & I111 & ".pdf", "Drawing") -> Drawing | I111: G512
A112: 105 | B112: 2"-WAR-8006-AG 1A | C112: =LEFT(B112, FIND("""", B112)) -> 2" | F112: CS | H112: =HYPERLINK("\\CAD-PC\1Data\3.Documentation\Isometric DWG MHI\" & I112 & ".pdf", "Drawing") -> Drawing | I112: G513
A113: 106 | B113: 6"-WAR-8000-AG 1A | C113: =LEFT(B113, FIND("""", B113)) -> 6" | F113: CS | H113: =HYPERLINK("\\CAD-PC\1Data\3.Documentation\Isometric DWG MHI\" & I113 & ".pdf", "Drawing") -> Drawing | I113: G514
A114: 107 | B114: 6"-WAR-8001 -AG 1A | C114: =LEFT(B114, FIND("""", B114)) -> 6" | F114: CS | H114: =HYPERLINK("\\CAD-PC\1Data\3.Documentation\Isometric DWG MHI\" & I114 & ".pdf", "Drawing") -> Drawing | I114: G515
A115: 108 | B115: 6"-WAR-8004-AG 1A | C115: =LEFT(B115, FIND("""", B115)) -> 6" | F115: CS | H115: =HYPERLINK("\\CAD-PC\1Data\3.Documentation\Isometric DWG MHI\" & I115 & ".pdf", "Drawing") -> Drawing | I115: G516
A116: 109 | B116: 2"-WAR-8004-AG 1A | C116: =LEFT(B116, FIND("""", B116)) -> 2" | F116: CS | H116: =HYPERLINK("\\CAD-PC\1Data\3.Documentation\Isometric DWG MHI\" & I116 & ".pdf", "Drawing") -> Drawing | I116: G517
A117: 110 | B117: 2"-WAR-8004-AG 1A | C117: =LEFT(B117, FIND("""", B117)) -> 2" | F117: CS | H117: =HYPERLINK("\\CAD-PC\1Data\3.Documentation\Isometric DWG MHI\" & I117 & ".pdf", "Drawing") -> Drawing | I117: G518
A118: 111 | B118: 2"-WAR-8004-AG 1A | C118: =LEFT(B118, FIND("""", B118)) -> 2" | F118: CS | H118: =HYPERLINK("\\CAD-PC\1Data\3.Documentation\Isometric DWG MHI\" & I118 & ".pdf", "Drawing") -> Drawing | I118: G519
A119: 112 | B119: 2"-WAR-8004-AG 1A | C119: =LEFT(B119, FIND("""", B119)) -> 2" | F119: CS | H119: =HYPERLINK("\\CAD-PC\1Data\3.Documentation\Isometric DWG MHI\" & I119 & ".pdf", "Drawing") -> Drawing | I119: G520
A120: 113 | B120: 2"-WAR-8004-AS 1A | C120: =LEFT(B120, FIND("""", B120)) -> 2" | F120: SS304 | H120: =HYPERLINK("\\CAD-PC\1Data\3.Documentation\Isometric DWG MHI\" & I120 & ".pdf", "Drawing") -> Drawing | I120: G521
A121: 114 | B121: 2"-WAR-8004-AS 1A | C121: =LEFT(B121, FIND("""", B121)) -> 2" | F121: SS304 | H121: =HYPERLINK("\\CAD-PC\1Data\3.Documentation\Isometric DWG MHI\" & I121 & ".pdf", "Drawing") -> Drawing | I121: G522
... A142: 135 | B142: 2"-WW I-8004-AS1A | C142: =LEFT(B142, FIND("""", B142)) -> 2" | F142: SS304 | H142: =HYPERLINK("\\CAD-PC\1Data\3.Documentation\Isometric DWG MHI\" & I142 & ".pdf", "Drawing") -> Drawing | I142: G625
A143: 136 | B143: 4"-WWT-8503-AS1A-P (1/2) (2/2) | C143: =LEFT(B143, FIND("""", B143)) -> 4" | D143: Waste Water | E143: Water | F143: SS304 | H143: =HYPERLINK("\\CAD-PC\1Data\3.Documentation\Isometric DWG MHI\" & I143 & ".pdf", "Drawing") -> Drawing | I143: G641
A144: 137 | B144: 2-1 /2"-WWT-8505-AS1A-P (1/2) (2/2) | C144: =LEFT(B144, FIND("""", B144)) -> 2-1 /2" | D144: Waste Water | E144: Water | F144: SS304 | H144: =HYPERLINK("\\CAD-PC\1Data\3.Documentation\Isometric DWG MHI\" & I144 & ".pdf", "Drawing") -> Drawing | I144: G642
A145: 138 | B145: 4"-WWT-8508-AS1 A-P | C145: =LEFT(B145, FIND("""", B145)) -> 4" | D145: Waste Water | E145: Water | F145: SS304 | H145: =HYPERLINK("\\CAD-PC\1Data\3.Documentation\Isometric DWG MHI\" & I145 & ".pdf", "Drawing") -> Drawing | I145: G643
A146: 139 | B146: 4"-WWT-8509-AS1 A-P | C146: =LEFT(B146, FIND("""", B146)) -> 4" | D146: Waste Water | E146: Water | F146: SS304 | H146: =HYPERLINK("\\CAD-PC\1Data\3.Documentation\Isometric DWG MHI\" & I146 & ".pdf", "Drawing") -> Drawing | I146: G644
A147: 140 | B147: 3"-WWT-8510-AS 1 A-P | C147: =LEFT(B147, FIND("""", B147)) -> 3" | D147: Waste Water | E147: Water | F147: SS304 | H147: =HYPERLINK("\\CAD-PC\1Data\3.Documentation\Isometric DWG MHI\" & I147 & ".pdf", "Drawing") -> Drawing | I147: G645
A148: 141 | B148: 3"-WWT-8510-AS1 A-P | C148: =LEFT(B148, FIND("""", B148)) -> 3" | D148: Waste Water | E148: Water | F148: SS304 | H148: =HYPERLINK("\\CAD-PC\1Data\3.Documentation\Isometric DWG MHI\" & I148 & ".pdf", "Drawing") -> Drawing | I148: G646
A149: 142 | B149: 4"-WWT-8513-AS1 A-P | C149: =LEFT(B149, FIND("""", B149)) -> 4" | D149: Waste Water | E149: Water | F149: SS304 | H149: =HYPERLINK("\\CAD-PC\1Data\3.Documentation\Isometric DWG MHI\" & I149 & ".pdf", "Drawing") -> Drawing | I149: G647
A150: 143 | B150: 6"-TK-931-AG1A | C150: =LEFT(B150, FIND("""", B150)) -> 6" | F150: CS | H150: =HYPERLINK("\\CAD-PC\1Data\3.Documentation\Isometric DWG MHI\" & I150 & ".pdf", "Drawing") -> Drawing | I150: G701
A151: 144 | B151: 2"-TK-811-AS1A | C151: =LEFT(B151, FIND("""", B151)) -> 2" | F151: SS304 | H151: =HYPERLINK("\\CAD-PC\1Data\3.Documentation\Isometric DWG MHI\" & I151 & ".pdf", "Drawing") -> Drawing | I151: G702
A152: 145 | B152: 2"-TK-831-AG1C | C152: =LEFT(B152, FIND("""", B152)) -> 2" | F152: CS | H152: =HYPERLINK("\\CAD-PC\1Data\3.Documentation\Isometric DWG MHI\" & I152 & ".pdf", "Drawing") -> Drawing | I152: G703
A153: 146 | B153: 2"-TK-832-AG1C | C153: =LEFT(B153, FIND("""", B153)) -> 2" | F153: CS | H153: =HYPERLINK("\\CAD-PC\1Data\3.Documentation\Isometric DWG MHI\" & I153 & ".pdf", "Drawing") -> Drawing | I153: G704
A154: 147 | B154: 2"-TK-833-AG1A | C154: =LEFT(B154, FIND("""", B154)) -> 2" | F154: CS | H154: =HYPERLINK("\\CAD-PC\1Data\3.Documentation\Isometric DWG MHI\" & I154 & ".pdf", "Drawing") -> Drawing | I154: G705
A155: 148 | B155: 4"-D-921-AG1B | C155: =LEFT(B155, FIND("""", B155)) -> 4" | F155: CS | H155: =HYPERLINK("\\CAD-PC\1Data\3.Documentation\Isometric DWG MHI\" & I155 & ".pdf", "Drawing") -> Drawing | I155: G706
A156: 149 | B156: 2"-D-921-AG1B | C156: =LEFT(B156, FIND("""", B156)) -> 2" | F156: CS | H156: =HYPERLINK("\\CAD-PC\1Data\3.Documentation\Isometric DWG MHI\" & I156 & ".pdf", "Drawing") -> Drawing | I156: G707
A157: 150 | B157: 2"-D-921-AG1B (1/2) (2/2) | C157: =LEFT(B157, FIND("""", B157)) -> 2" | F157: CS | H157: =HYPERLINK("\\CAD-PC\1Data\3.Documentation\Isometric DWG MHI\" & I157 & ".pdf", "Drawing") -> Drawing | I157: G708
A158: 151 | B158: 2"-TK-932-AS1A | C158: =LEFT(B158, FIND("""", B158)) -> 2" | F158: SS304 | H158: =HYPERLINK("\\CAD-PC\1Data\3.Documentation\Isometric DWG MHI\" & I158 & ".pdf", "Drawing") -> Drawing | I158: G709
A159: 152 | B159: 4"-TK-820-AS1A | C159: =LEFT(B159, FIND("""", B159)) -> 4" | F159: SS304 | H159: =HYPERLINK("\\CAD-PC\1Data\3.Documentation\Isometric DWG MHI\" & I159 & ".pdf", "Drawing") -> Drawing | I159: G710
A160: 153 | B160: 4"-TK-822-AS1A | C160: =LEFT(B160, FIND("""", B160)) -> 4" | F160: SS304 | H160: =HYPERLINK("\\CAD-PC\1Data\3.Documentation\Isometric DWG MHI\" & I160 & ".pdf", "Drawing") -> Drawing | I160: G711
A161: 154 | B161: 1 /2"-BFW-8501-BG4A-P | C161: =LEFT(B161, FIND("""", B161)) -> 1 /2" | D161: Boiler Feed Water | E161: Water | F161: CS | H161: =HYPERLINK("\\CAD-PC\1Data\3.Documentation\Isometric DWG MHI\" & I161 & ".pdf", "Drawing") -> Drawing | I161: H021
A162: 155 | B162: 3/4"-BFW-8502-BG4A- P | C162: =LEFT(B162, FIND("""", B162)) -> 3/4" | D162: Boiler Feed Water | E162: Water | F162: CS | H162: =HYPERLINK("\\CAD-PC\1Data\3.Documentation\Isometric DWG MHI\" & I162 & ".pdf", "Drawing") -> Drawing | I162: H022
A163: 156 | B163: 1 /2"-BFW-9201 -AG 1B-H25 | C163: =LEFT(B163, FIND("""", B163)) -> 1 /2" | D163: Boiler Feed Water | E163: Water | F163: CS | G163: Hot | H163: =HYPERLINK("\\CAD-PC\1Data\3.Documentation\Isometric DWG MHI\" & I163 & ".pdf", "Drawing") -> Drawing | I163: H023
A164: 157 | B164: 3/4"-BFW-9201 -AG1B-H25 | C164: =LEFT(B164, FIND("""", B164)) -> 3/4" | D164: Boiler Feed Water | E164: Water | F164: CS | G164: Hot | H164: =HYPERLINK("\\CAD-PC\1Data\3.Documentation\Isometric DWG MHI\" & I164 & ".pdf", "Drawing") -> Drawing | I164: H024
A165: 158 | B165: 3/4"-CF-9203-AS1A | C165: =LEFT(B165, FIND("""", B165)) -> 3/4" | F165: SS304 | H165: =HYPERLINK("\\CAD-PC\1Data\3.Documentation\Isometric DWG MHI\" & I165 & ".pdf", "Drawing") -> Drawing | I165: H041
A166: 159 | B166: 3/4"-CF-9402-AS 1A | C166: =LEFT(B166, FIND("""", B166)) -> 3/4" | F166: SS304 | H166: =HYPERLINK("\\CAD-PC\1Data\3.Documentation\Isometric DWG MHI\" & I166 & ".pdf", "Drawing") -> Drawing | I166: H042
A167: 160 | B167: 3/4"-CF-9201 -AS1A | C167: =LEFT(B167, FIND("""", B167)) -> 3/4" | F167: SS304 | H167: =HYPERLINK("\\CAD-PC\1Data\3.Documentation\Isometric DWG MHI\" & I167 & ".pdf", "Drawing") -> Drawing | I167: H043
A168: 161 | B168: 3/4"-CF-9201 -AS 1A | C168: =LEFT(B168, FIND("""", B168)) -> 3/4" | F168: SS304 | H168: =HYPERLINK("\\CAD-PC\1Data\3.Documentation\Isometric DWG MHI\" & I168 & ".pdf", "Drawing") -> Drawing | I168: H044
A169: 162 | B169: 3/4"-CF-9202-AS 1A | C169: =LEFT(B169, FIND("""", B169)) -> 3/4" | F169: SS304 | H169: =HYPERLINK("\\CAD-PC\1Data\3.Documentation\Isometric DWG MHI\" & I169 & ".pdf", "Drawing") -> Drawing | I169: H045
A170: 163 | B170: 3/4"-CWR-9204-AG 1A | C170: =LEFT(B170, FIND("""", B170)) -> 3/4" | D170: Cooling Water | E170: Water | F170: CS | H170: =HYPERLINK("\\CAD-PC\1Data\3.Documentation\Isometric DWG MHI\" & I170 & ".pdf", "Drawing") -> Drawing | I170: H061
A171: 164 | B171: 3/4"-CWR-9413-AG1A | C171: =LEFT(B171, FIND("""", B171)) -> 3/4" | D171: Cooling Water | E171: Water | F171: CS | H171: =HYPERLINK("\\CAD-PC\1Data\3.Documentation\Isometric DWG MHI\" & I171 & ".pdf", "Drawing") -> Drawing | I171: H062
A172: 165 | B172: 3/4"-CWS-9203-AG 1A | C172: =LEFT(B172, FIND("""", B172)) -> 3/4" | D172: Cooling Water | E172: Water | F172: CS | H172: =HYPERLINK("\\CAD-PC\1Data\3.Documentation\Isometric DWG MHI\" & I172 & ".pdf", "Drawing") -> Drawing | I172: H091
A173: 166 | B173: 3/4"-CWS-9413-AG1A | C173: =LEFT(B173, FIND("""", B173)) -> 3/4" | D173: Cooling Water | E173: Water | F173: CS | H173: =HYPERLINK("\\CAD-PC\1Data\3.Documentation\Isometric DWG MHI\" & I173 & ".pdf", "Drawing") -> Drawing | I173: H092
A174: 167 | B174: 1-1/2"-DMW-9309- AS1A | C174: =LEFT(B174, FIND("""", B174)) -> 1-1/2" | D174: Demin Water | E174: Water | F174: SS304 | H174: =HYPERLINK("\\CAD-PC\1Data\3.Documentation\Isometric DWG MHI\" & I174 & ".pdf", "Drawing") -> Drawing | I174: H121
A175: 168 | B175: 1-1/2"-DMW-9310- AS1A | C175: =LEFT(B175, FIND("""", B175)) -> 1-1/2" | D175: Demin Water | E175: Water | F175: SS304 | H175: =HYPERLINK("\\CAD-PC\1Data\3.Documentation\Isometric DWG MHI\" & I175 & ".pdf", "Drawing") -> Drawing | I175: H122
A176: 169 | B176: 3/4"-DMW-9210-AS1A | C176: =LEFT(B176, FIND("""", B176)) -> 3/4" | D176: Demin Water | E176: Water | F176: SS304 | H176: =HYPERLINK("\\CAD-PC\1Data\3.Documentation\Isometric DWG MHI\" & I176 & ".pdf", "Drawing") -> Drawing | I176: H123
A177: 170 | B177: 1-1/2"-DMW-93D7- AS1A | C177: =LEFT(B177, FIND("""", B177)) -> 1-1/2" | D177: Demin Water | E177: Water | F177: SS304 | H177: =HYPERLINK("\\CAD-PC\1Data\3.Documentation\Isometric DWG MHI\" & I177 & ".pdf", "Drawing") -> Drawing | I177: H124
...

Sheet 48-1
C1: EQUIPMENT LIST | F1: Document No. | G1: : MNTC-ME
F2: Revision | G2: : 0
F3: Date of issue | G3: : 2025
A4: PT. PETRO OXO NUSANTARA | F4: Page | G4: :
A5: VALVE LIST OCTANOL
A7: No | B7: Line No. | C7: PAGE NO. | D7: Dia. | E7: Valve ID | F7: Material | G7: Remark
A8: 1 | B8: 3/4" - DMW-HS124 - AS1A | C8: E065 | D8: 3/4" | F8: A312-TP304 | H8: 1
A9: 2 | B9: 3/4" - DMW-HS142 - AS1A | C9: E066 | D9: 3/4" | E9: GV 1 | F9: A312-TP304 | H9: 1
A10: 3 | B10: 3/4" - DMW-HS152 - AS1A | C10: E067 | D10: 3/4" | F10: A312-TP304
A11: 4 | B11: 3/4" - DMW-HS162 - AS1A | C11: E068 | D11: 3/4" | E11: GV 1 | F11: A312-TP304 | H11: 1
A12: 5 | B12: 1 1/2" - FGS-6105-1 - AG1C | C12: E089 | D12: 1 1/2" | F12: CS
A13: 6 | B13: 3/4" - FGS-9621 - AG1C | C13: E090 | D13: 3/4" | F13: CS
A14: 7 | B14: 1 1/2" - FGS-5105 - AG1C | C14: E091 | D14: 1 1/2" | F14: CS
A15: 8 | B15: 1 1/2" - FGS-5105-2 - AG1A | C15: E092 | D15: 1 1/2" | F15: CS
A16: 9 | B16: 1 1/2" - FGS-6105-2 - AG1C | C16: E093 | D16: 1 1/2" | F16: CS
A17: 10 | B17: 1 1/2" - FWS-9383 - AG1A | C17: E104 | D17: 1 1/2" | E17: GV 2 | F17: CS | H17: 1
A18: 11 | B18: 1" - FWS-9384 - AG1A | C18: E106 | D18: 1" | F18: CS
A19: 12 | B19: 1" - FWS-HS144-1 - AG1A | C19: E109 | D19: 1" | F19: CS
A20: 13 | B20: 1" - FWS-HS155-1 - AG1A | C20: E110 | D20: 1" | F20: CS
A21: 14 | B21: 3/4" - FWS-HS101 - AG1A | C21: E127 | D21: 3/4" | E21: GV 1 | F21: CS | H21: 1
A22: 15 | B22: 3/4" - FWS-HS102 - AG1A | C22: E128 | D22: 3/4" | E22: GV 1 | F22: CS | H22: 1
A23: 16 | B23: 3/4" - FWS-HS103 - AG1A | C23: E129 | D23: 3/4" | E23: GV 1 | F23: CS | H23: 1
A24: 17 | B24: 3/4" - FWS-HS104 - AG1A | C24: E130 | D24: 3/4" | F24: CS
A25: 18 | B25: 3/4" - FWS-HS105 - AG1A | C25: E131 | D25: 3/4" | E25: GV 1 | F25: CS | H25: 1
A26: 19 | B26: 3/4" - FWS-HS106 - AG1A | C26: E132 | D26: 3/4" | F26: CS
A27: 20 | B27: 3/4" - FWS-HS107 - AG1A | C27: E133 | D27: 3/4" | F27: CS
A28: 21 | B28: 3/4" - FWS-HS108 - AG1A | C28: E134 | D28: 3/4" | F28: CS
A29: 22 | B29: 3/4" - FWS-HS109 - AG1A | C29: E135 | D29: 3/4" | F29: CS
A30: 23 | B30: 3/4" - FWS-HS110 - AG1A | C30: E136 | D30: 3/4" | E30: GV 1 | F30: CS | H30: 1
A31: 24 | B31: 3/4" - FWS-HS111 - AG1A | C31: E137 | D31: 3/4" | F31: CS
A32: 25 | B32: 3/4" - FWS-HS121 - AG1A | C32: E138 | D32: 3/4" | E32: GV 1 | F32: CS | H32: 1
A33: 26 | B33: 3/4" - FWS-HS122 - AG1A | C33: E139 | D33: 3/4" | F33: CS
A34: 27 | B34: 3/4" - FWS-HS123 - AG1A | C34: E140 | D34: 3/4" | F34: CS
A35: 28 | B35: 3/4" - FWS-HS124 - AG1A | C35: E141 | D35: 3/4" | F35: CS
A36: 29 | B36: 3/4" - FWS-HS141 - AG1A | C36: E142 | D36: 3/4" | E36: GV 1 | F36: CS | H36: 1
A37: 30 | B37: 3/4" - FWS-HS142 - AG1A | C37: E143 | D37: 3/4" | E37: GV 1 | F37: CS | H37: 1
A38: 31 | B38: 3/4" - FWS-HS143 - AG1A | C38: E144 | D38: 3/4" | F38: CS
A39: 32 | B39: 3/4" - FWS-HS144-2 - AG1A | C39: E145 | D39: 3/4" | F39: CS
A40: 33 | B40: 3/4" - FWS-HS145 - AG1A | C40: E146 | D40: 3/4" | F40: CS
A41: 34 | B41: 3/4" - FWS-HS151 - AG1A | C41: E147 | D41: 3/4" | E41: GV 1 | F41: CS | H41: 1
A42: 35 | B42: 3/4" - FWS-HS152 - AG1A | C42: E148 | D42: 3/4" | F42: CS
A43: 36 | B43: 3/4" - FWS-HS153 - AG1A | C43: E149 | D43: 3/4" | F43: CS
A44: 37 | B44: 3/4" - FWS-HS154-2 - AG1A | C44: E150 | D44: 3/4" | F44: CS
A45: 38 | B45: 3/4" - FWS-HS155-2 - AG1A | C45: E151 | D45: 3/4" | F45: CS
A46: 39 | B46: 3/4" - FWS-HS162 - AG1A | C46: E152 | D46: 3/4" | E46: GV 1 | F46: CS | H46: 1
A47: 40 | B47: 3/4" - GHY-1010 - DG3A | C47: E176 | D47: 3/4" | E47: GV 8,CV 1 | F47: CS | H47: 1
A48: 41 | B48: 1" - GHY-1210 - BG3A | C48: E178 | D48: 1" | F48: CS
A49: 42 | B49: 3/4" - GHY-2311 - DG3A | C49: E179 | D49: 3/4" | E49: GV 3,CV 1 | F49: CS | H49: 1
A50: 43 | B50: 1 1/2" - GHY-6109-1 - DG3A | C50: E181 | D50: 1 1/2" | F50: CS
A51: 44 | B51: 1 1/2" - GHY-6109-2 - DG3A | C51: E182 | D51: 1 1/2" | F51: CS
A52: 45 | B52: 1 1/2" - GHY-6109-3 - DG3A | C52: E183 | D52: 1 1/2" | F52: CS
A53: 46 | B53: 1 1/2" - GHY-5109-1 - DG3A | C53: E184 | D53: 1 1/2" | F53: CS
A54: 47 | B54: 1 1/2" - GHY-5109 - DG3A | C54: E185 | D54: 1 1/2" | F54: CS
A55: 48 | B55: 1 1/2" - GHY-5109-2 - DG3A | C55: E186 | D55: 1 1/2" | F55: CS
A56: 49 | B56: 1" - GHY-1210 - DG3A | C56: E188 | D56: 1" | E56: GV 5, CV 1 | F56: CS | H56: 1
A57: 50 | B57: 3/4" - GHY-2311 - BS1A | C57: E189 | D57: 3/4" | F57: A312-TP304
A58: 51 | B58: 1 1/2" - GOX-1309 - BS1A | C58: E202 | D58: 1 1/2" | E58: CV 1 | F58: A312-TP304 | H58: 1
A59: 52 | B59: 1 1/2" - GOX-1309 - BG3A | C59: E203 | D59: 1 1/2" | F59: CS
A60: 53 | B60: 1" - GPA-9984 - AG1A | C60: E213 | D60: 1" | F60: CS
A61: 54 | B61: 3/4" - GPA-HS144-1 - AG1A | C61: E217 | D61: 3/4" | F61: CS
A62: 55 | B62: 1" - GPA-HS155-1 - AG1A | C62: E218 | D62: 1" | F62: CS
A63: 56 | B63: 1" - GPI-9917 - AG2A | C63: E220 | D63: 1" | E63: GV 4 | F63: CS | H63: 1
A64: 57 | B64: 1" - GPI-9917 - AG2A | C64: E221 | D64: 1" | E64: GV 4 | F64: CS | H64: 1
A65: 58 | B65: 3/4" - GPA-HS101 - AG1A | C65: E227 | D65: 3/4" | E65: GV 1 | F65: CS | H65: 1
A66: 59 | B66: 3/4" - GPA-HS102 - AG1A | C66: E228 | D66: 3/4" | E66: GV 1 | F66: CS | H66: 1
A67: 60 | B67: 3/4" - GPA-HS103 - AG1A | C67: E229 | D67: 3/4" | E67: GV 1 | F67: CS | H67: 1
A68: 61 | B68: 3/4" - GPA-HS104 - AG1A | C68: E230 | D68: 3/4" | F68: CS
A69: 62 | B69: 3/4" - GPA-HS105 - AG1A | C69: E231 | D69: 3/4" | E69: GV 1 | F69: CS | H69: 1
A70: 63 | B70: 3/4" - GPA-HS106 - AG1A | C70: E232 | D70: 3/4" | F70: CS
A71: 64 | B71: 3/4" - GPA-HS107 - AG1A | C71: E233 | D71: 3/4" | F71: CS
A72: 65 | B72: 3/4" - GPA-HS108 - AG1A | C72: E234 | D72: 3/4" | F72: CS
A73: 66 | B73: 3/4" - GPA-HS109 - AG1A | C73: E235 | D73: 3/4" | F73: CS
A74: 67 | B74: 3/4" - GPA-HS110 - AG1A | C74: E236 | D74: 3/4" | E74: GV 1 | F74: CS | H74: 1
A75: 68 | B75: 3/4" - GPA-HS111 - AG1A | C75: E237 | D75: 3/4" | F75: CS
A76: 69 | B76: 3/4" - GPA-HS121 - AG1A | C76: E238 | D76: 3/4" | E76: GV 1 | F76: CS | H76: 1
A77: 70 | B77: 3/4" - GPA-HS122 - AG1A | C77: E239 | D77: 3/4" | F77: CS
A78: 71 | B78: 3/4" - GPA-HS123 - AG1A | C78: E240 | D78: 3/4" | F78: CS
A79: 72 | B79: 3/4" - GPA-HS124 - AG1A | C79: E241 | D79: 3/4" | F79: CS
A80: 73 | B80: 3/4" - GPA-HS131 - AG1A | C80: E242 | D80: 3/4" | E80: GV 1 | F80: CS | H80: 1
A81: 74 | B81: 3/4" - GPA-HS132 - AG1A | C81: E243 | D81: 3/4" | F81: CS
A82: 75 | B82: 3/4" - GPA-HS133 - AG1A | C82: E244 | D82: 3/4" | F82: CS
A83: 76 | B83: 3/4" - GPA-HS134 - AG1A | C83: E245 | D83: 3/4" | F83: CS
A84: 77 | B84: 3/4" - GPA-HS135-1 - AG1A | C84: E246 | D84: 3/4" | F84: CS
A85: 78 | B85: 3/4" - GPA-HS136 - AG1A | C85: E247 | D85: 3/4" | F85: CS
A86: 79 | B86: 3/4" - GPA-HS137 - AG1A | C86: E248 | D86: 3/4" | F86: CS
A87: 80 | B87: 3/4" - GPA-HS138 - AG1A | C87: E249 | D87: 3/4" | F87: CS
A88: 81 | B88: 3/4" - GPA-HS139-2 - AG1A | C88: E250 | D88: 3/4" | F88: CS
A89: 82 | B89: 3/4" - GPA-HS142 - AG1A | C89: E252 | D89: 3/4" | E89: GV 1 | F89: CS | H89: 1
A90: 83 | B90: 3/4" - GPA-HS143 - AG1A | C90: E253 | D90: 3/4" | F90: CS
A91: 84 | B91: 3/4" - GPA-HS144-2 - AG1A | C91: E254 | D91: 3/4" | F91: CS
A92: 85 | B92: 3/4" - GPA-HS145 - AG1A | C92: E255 | D92: 3/4" | F92: CS
A93: 86 | B93: 3/4" - GPA-HS151 - AG1A | C93: E256 | D93: 3/4" | E93: GV 1 | F93: CS | H93: 1
A94: 87 | B94: 3/4" - GPA-HS152 - AG1A | C94: E257 | D94: 3/4" | F94: CS
A95: 88 | B95: 3/4" - GPA-HS153 - AG1A | C95: E258 | D95: 3/4" | F95: CS
A96: 89 | B96: 3/4" - GPA-HS154-2 - AG1A | C96: E259 | D96: 3/4" | F96: CS
A97: 90 | B97: 3/4" - GPA-HS155-2 - AG1A | C97: E260 | D97: 3/4" | F97: CS
A98: 91 | B98: 3/4" - GPA-HS162 - AG1A | C98: E261 | D98: 3/4" | E98: GV 1 | F98: CS | H98: 1
A99: 92 | B99: 1" - IBA-6316 - AG1E | C99: E267 | D99: 1" | F99: CS
A100: 93 | B100: 1 1/2" - IPA-2302 - AS1A | C100: E273 | D100: 1 1/2" | F100: A312-TP304
A101: 94 | B101: 3/4" - IPA-2304 - AS1A | C101: E275 | D101: 3/4" | E101: GV 2 | F101: A312-TP304 | H101: 1
...

Sheet 48
C1: EQUIPMENT LIST | G1: Document No. | J1: : MNTC-ME
G2: Revision | J2: : 0
G3: Date of issue | J3: : 2025
A4: PT. PETRO OXO NUSANTARA | G4: Page | J4: :
A5: PIPING LIST OCTANOL
A7: No | B7: Line No. | C7: Size | D7: Service | E7: Fluid | F7: Material | G7: Insulation | H7: Drawing | I7: PAGE NO. | J7: Pipe length ( mm )
A8: 1 | B8: 3/4" - DMW-HS124 - AS1A | C8: 3/4" | D8: DEMINERALIZED WATER | E8: WATER | F8: A312-TP304 | H8: =HYPERLINK("\\CAD-PC\1Data\3.Documentation\Isometric DWG MHI\" & I8 & ".pdf", "Drawing") -> Drawing | I8: E065
A9: 2 | B9: 3/4" - DMW-HS142 - AS1A | C9: 3/4" | D9: DEMINERALIZED WATER | E9: WATER | F9: A312-TP304 | H9: =HYPERLINK("\\CAD-PC\1Data\3.Documentation\Isometric DWG MHI\" & I9 & ".pdf", "Drawing") -> Drawing | I9: E066
A10: 3 | B10: 3/4" - DMW-HS152 - AS1A | C10: 3/4" | D10: DEMINERALIZED WATER | E10: WATER | F10: A312-TP304 | H10: =HYPERLINK("\\CAD-PC\1Data\3.Documentation\Isometric DWG MHI\" & I10 & ".pdf", "Drawing") -> Drawing | I10: E067
A11: 4 | B11: 3/4" - DMW-HS162 - AS1A | C11: 3/4" | D11: DEMINERALIZED WATER | E11: WATER | F11: A312-TP304 | H11: =HYPERLINK("\\CAD-PC\1Data\3.Documentation\Isometric DWG MHI\" & I11 & ".pdf", "Drawing") -> Drawing | I11: E068
A12: 5 | B12: 1 1/2" - FGS-6105-1 - AG1C | C12: 1 1/2" | D12: FUEL GAS | E12: GAS | F12: CS | H12: =HYPERLINK("\\CAD-PC\1Data\3.Documentation\Isometric DWG MHI\" & I12 & ".pdf", "Drawing") -> Drawing | I12: E089
A13: 6 | B13: 3/4" - FGS-9621 - AG1C | C13: 3/4" | D13: FUEL GAS | E13: GAS | F13: CS | H13: =HYPERLINK("\\CAD-PC\1Data\3.Documentation\Isometric DWG MHI\" & I13 & ".pdf", "Drawing") -> Drawing | I13: E090
A14: 7 | B14: 1 1/2" - FGS-5105 - AG1C | C14: 1 1/2" | D14: FUEL GAS | E14: GAS | F14: CS | H14: =HYPERLINK("\\CAD-PC\1Data\3.Documentation\Isometric DWG MHI\" & I14 & ".pdf", "Drawing") -> Drawing | I14: E091
A15: 8 | B15: 1 1/2" - FGS-5105-2 - AG1A | C15: 1 1/2" | D15: FUEL GAS | E15: GAS | F15: CS | H15: =HYPERLINK("\\CAD-PC\1Data\3.Documentation\Isometric DWG MHI\" & I15 & ".pdf", "Drawing") -> Drawing | I15: E092
A16: 9 | B16: 1 1/2" - FGS-6105-2 - AG1C | C16: 1 1/2" | D16: FUEL GAS | E16: GAS | F16: CS | H16: =HYPERLINK("\\CAD-PC\1Data\3.Documentation\Isometric DWG MHI\" & I16 & ".pdf", "Drawing") -> Drawing | I16: E093
A17: 10 | B17: 1 1/2" - FWS-9383 - AG1A | C17: 1 1/2" | D17: FILTERED WATER | E17: WATER | F17: CS | H17: =HYPERLINK("\\CAD-PC\1Data\3.Documentation\Isometric DWG MHI\" & I17 & ".pdf", "Drawing") -> Drawing | I17: E104
A18: 11 | B18: 1" - FWS-9384 - AG1A | C18: 1" | D18: FILTERED WATER | E18: WATER | F18: CS | H18: =HYPERLINK("\\CAD-PC\1Data\3.Documentation\Isometric DWG MHI\" & I18 & ".pdf", "Drawing") -> Drawing | I18: E106
A19: 12 | B19: 1" - FWS-HS144-1 - AG1A | C19: 1" | D19: FILTERED WATER | E19: WATER | F19: CS | H19: =HYPERLINK("\\CAD-PC\1Data\3.Documentation\Isometric DWG MHI\" & I19 & ".pdf", "Drawing") -> Drawing | I19: E109
... A102: 95 | B102: 3/4" - IPA-2303 - AS1A | C102: 3/4" | D102: ISO PROPANOL | E102: LIQUID | F102: A312-TP304 | H102: =HYPERLINK("\\CAD-PC\1Data\3.Documentation\Isometric DWG MHI\" & I102 & ".pdf", "Drawing") -> Drawing | I102: E276
A103: 96 | B103: 3/4" - LPC-3159 - AG1B | C103: 3/4" | D103: STEAM CONDENSATE | E103: WATER | F103: CS | G103: H25 | H103: =HYPERLINK("\\CAD-PC\1Data\3.Documentation\Isometric DWG MHI\" & I103 & ".pdf", "Drawing") -> Drawing | I103: E286
A104: 97 | B104: 1 1/2" - LPC-5552-1 - AG1B | C104: 1 1/2" | D104: STEAM CONDENSATE | E104: WATER | F104: CS | G104: H25 | H104: =HYPERLINK("\\CAD-PC\1Data\3.Documentation\Isometric DWG MHI\" & I104 & ".pdf", "Drawing") -> Drawing | I104: E287
A105: 98 | B105: 1 1/2" - LPC-9203 - AG1B | C105: 1 1/2" | D105: STEAM CONDENSATE | E105: WATER | F105: CS | G105: H25 | H105: =HYPERLINK("\\CAD-PC\1Data\3.Documentation\Isometric DWG MHI\" & I105 & ".pdf", "Drawing") -> Drawing | I105: E288
A106: 99 | B106: 3/4" - LPC-2556 - AG1B | C106: 3/4" | D106: STEAM CONDENSATE | E106: WATER | F106: CS | H106: =HYPERLINK("\\CAD-PC\1Data\3.Documentation\Isometric DWG MHI\" & I106 & ".pdf", "Drawing") -> Drawing | I106: E290
A107: 100 | B107: 1 1/2" - LPC-3159 - AG1B | C107: 1 1/2" | D107: STEAM CONDENSATE | E107: WATER | F107: CS | G107: H25 | H107: =HYPERLINK("\\CAD-PC\1Data\3.Documentation\Isometric DWG MHI\" & I107 & ".pdf", "Drawing") -> Drawing | I107: E291
A108: 101 | B108: 3/4" - LPC-HOLD - AG1B | C108: 3/4" | D108: STEAM CONDENSATE | E108: WATER | F108: CS | G108: H25 | H108: =HYPERLINK("\\CAD-PC\1Data\3.Documentation\Isometric DWG MHI\" & I108 & ".pdf", "Drawing") -> Drawing | I108: E292
A109: 102 | B109: 1" - LPS-9283 - AG1B | C109: 1" | D109: LOW PRESSURE STEAM | E109: STEAM | F109: CS | G109: H25 | H109: =HYPERLINK("\\CAD-PC\1Data\3.Documentation\Isometric DWG MHI\" & I109 & ".pdf", "Drawing") -> Drawing | I109: E312
A110: 103 | B110: 1" - LPS-HS144-1 - AG1B | C110: 1" | D110: LOW PRESSURE STEAM | E110: STEAM | F110: CS | G110: H25 | H110: =HYPERLINK("\\CAD-PC\1Data\3.Documentation\Isometric DWG MHI\" & I110 & ".pdf", "Drawing") -> Drawing | I110: E315
A111: 104 | B111: 1" - LPS-HS155-1 - AG1B | C111: 1" | D111: LOW PRESSURE STEAM | E111: STEAM | F111: CS | G111: H25 | H111: =HYPERLINK("\\CAD-PC\1Data\3.Documentation\Isometric DWG MHI\" & I111 & ".pdf", "Drawing") -> Drawing | I111: E316
A112: 105 | B112: 3/4" - LPS-HS101 - AG1B | C112: 3/4" | D112: LOW PRESSURE STEAM | E112: STEAM | F112: CS | G112: H25 | H112: =HYPERLINK("\\CAD-PC\1Data\3.Documentation\Isometric DWG MHI\" & I112 & ".pdf", "Drawing") -> Drawing | I112: E346
A113: 106 | B113: 3/4" - LPS-HS102 - AG1B | C113: 3/4" | D113: LOW PRESSURE STEAM | E113: STEAM | F113: CS | G113: H25 | H113: =HYPERLINK("\\CAD-PC\1Data\3.Documentation\Isometric DWG MHI\" & I113 & ".pdf", "Drawing") -> Drawing | I113: E347
A114: 107 | B114: 3/4" - LPS-HS103 - AG1A | C114: 3/4" | D114: LOW PRESSURE STEAM | E114: STEAM | F114: CS | G114: H25 | H114: =HYPERLINK("\\CAD-PC\1Data\3.Documentation\Isometric DWG MHI\" & I114 & ".pdf", "Drawing") -> Drawing | I114: E348
A115: 108 | B115: 3/4" - LPS-HS104 - AG1B | C115: 3/4" | D115: LOW PRESSURE STEAM | E115: STEAM | F115: CS | G115: H25 | H115: =HYPERLINK("\\CAD-PC\1Data\3.Documentation\Isometric DWG MHI\" & I115 & ".pdf", "Drawing") -> Drawing | I115: E349
A116: 109 | B116: 3/4" - LPS-HS105 - AG1B | C116: 3/4" | D116: LOW PRESSURE STEAM | E116: STEAM | F116: CS | G116: H25 | H116: =HYPERLINK("\\CAD-PC\1Data\3.Documentation\Isometric DWG MHI\" & I116 & ".pdf", "Drawing") -> Drawing | I116: E350
A117: 110 | B117: 3/4" - LPS-HS106 - AG1B | C117: 3/4" | D117: LOW PRESSURE STEAM | E117: STEAM | F117: CS | G117: H25 | H117: =HYPERLINK("\\CAD-PC\1Data\3.Documentation\Isometric DWG MHI\" & I117 & ".pdf", "Drawing") -> Drawing | I117: E351
A118: 111 | B118: 3/4" - LPS-HS107 - AG1B | C118: 3/4" | D118: LOW PRESSURE STEAM | E118: STEAM | F118: CS | G118: H25 | H118: =HYPERLINK("\\CAD-PC\1Data\3.Documentation\Isometric DWG MHI\" & I118 & ".pdf", "Drawing") -> Drawing | I118: E352
... A156: 149 | B156: 1 1/2" - MPS-2254 - AG4A | C156: 1 1/2" | D156: MEDIUM PRESSURE STEAM | E156: STEAM | F156: CS | G156: H25 | H156: =HYPERLINK("\\CAD-PC\1Data\3.Documentation\Isometric DWG MHI\" & I156 & ".pdf", "Drawing") -> Drawing | I156: E417
A157: 150 | B157: 3/4" - P-4555 - BG4A | C157: 3/4" | D157: PROCESS | F157: CS | G157: H25 | H157: =HYPERLINK("\\CAD-PC\1Data\3.Documentation\Isometric DWG MHI\" & I157 & ".pdf", "Drawing") -> Drawing | I157: E418
A158: 151 | B158: 1" - MPS-4556 - BG4A | C158: 1" | D158: MEDIUM PRESSURE STEAM | E158: STEAM | F158: CS | G158: H25 | H158: =HYPERLINK("\\CAD-PC\1Data\3.Documentation\Isometric DWG MHI\" & I158 & ".pdf", "Drawing") -> Drawing | I158: E419
A159: 152 | B159: 1 1/2" - MPS-5451 - BG4A | C159: 1 1/2" | D159: MEDIUM PRESSURE STEAM | E159: STEAM | F159: CS | G159: H25 | H159: =HYPERLINK("\\CAD-PC\1Data\3.Documentation\Isometric DWG MHI\" & I159 & ".pdf", "Drawing") -> Drawing | I159: E421
A160: 153 | B160: 1 1/2" - MPS-6451-1 - BG4A | C160: 1 1/2" | D160: MEDIUM PRESSURE STEAM | E160: STEAM | F160: CS | G160: H25 | H160: =HYPERLINK("\\CAD-PC\1Data\3.Documentation\Isometric DWG MHI\" & I160 & ".pdf", "Drawing") -> Drawing | I160: E422
A161: 154 | B161: 1 1/2" - MPS-5451-2 - BG4A | C161: 1 1/2" | D161: MEDIUM PRESSURE STEAM | E161: STEAM | F161: CS | G161: H25 | H161: =HYPERLINK("\\CAD-PC\1Data\3.Documentation\Isometric DWG MHI\" & I161 & ".pdf", "Drawing") -> Drawing | I161: E423
A162: 155 | B162: 1 1/2" - MPS-6451-2 - BG4A | C162: 1 1/2" | D162: MEDIUM PRESSURE STEAM | E162: STEAM | F162: CS | G162: H25 | H162: =HYPERLINK("\\CAD-PC\1Data\3.Documentation\Isometric DWG MHI\" & I162 & ".pdf", "Drawing") -> Drawing | I162: E424
A163: 156 | B163: 3/4" - MPS-* - BG4A | C163: 3/4" | D163: MEDIUM PRESSURE STEAM | E163: STEAM | F163: CS | G163: H25 | H163: =HYPERLINK("\\CAD-PC\1Data\3.Documentation\Isometric DWG MHI\" & I163 & ".pdf", "Drawing") -> Drawing | I163: E425
A164: 157 | B164: 1 1/2" - NBA-5316-1 - AS1A | C164: 1 1/2" | D164: NORMAL BUTANOL | E164: LIQUID | F164: A312-TP304 | H164: =HYPERLINK("\\CAD-PC\1Data\3.Documentation\Isometric DWG MHI\" & I164 & ".pdf", "Drawing") -> Drawing | I164: E443
A165: 158 | B165: 1 1/2" - NBA-5316-2 - AS1A | C165: 1 1/2" | D165: NORMAL BUTANOL | E165: LIQUID | F165: A312-TP304 | H165: =HYPERLINK("\\CAD-PC\1Data\3.Documentation\Isometric DWG MHI\" & I165 & ".pdf", "Drawing") -> Drawing | I165: E444
A166: 159 | B166: 1 1/2" - NBA-5316-3 - AS1A | C166: 1 1/2" | D166: NORMAL BUTANOL | E166: LIQUID | F166: A312-TP304 | H166: =HYPERLINK("\\CAD-PC\1Data\3.Documentation\Isometric DWG MHI\" & I166 & ".pdf", "Drawing") -> Drawing | I166: E445
A167: 160 | B167: 1 1/2" - NBA-5316-4 - AS1A | C167: 1 1/2" | D167: NORMAL BUTANOL | E167: LIQUID | F167: A312-TP304 | H167: =HYPERLINK("\\CAD-PC\1Data\3.Documentation\Isometric DWG MHI\" & I167 & ".pdf", "Drawing") -> Drawing | I167: E446
A168: 161 | B168: 3/4" - NGB-1151 - AG1A | C168: 3/4" | D168: NITROGEN GAS | E168: GAS | F168: CS | H168: =HYPERLINK("\\CAD-PC\1Data\3.Documentation\Isometric DWG MHI\" & I168 & ".pdf", "Drawing") -> Drawing | I168: E456
A169: 162 | B169: 3/4" - NGB-1437 - AG1A | C169: 3/4" | D169: NITROGEN GAS | E169: GAS | F169: CS | H169: =HYPERLINK("\\CAD-PC\1Data\3.Documentation\Isometric DWG MHI\" & I169 & ".pdf", "Drawing") -> Drawing | I169: E457
A170: 163 | B170: 3/4" - NGB-1655 - AG1A | C170: 3/4" | D170: NITROGEN GAS | E170: GAS | F170: CS | H170: =HYPERLINK("\\CAD-PC\1Data\3.Documentation\Isometric DWG MHI\" & I170 & ".pdf", "Drawing") -> Drawing | I170: E458
A171: 164 | B171: 1 1/2" - NGB-1658 - AS1A | C171: 1 1/2" | D171: NITROGEN GAS | E171: GAS | F171: A312-TP304 | H171: =HYPERLINK("\\CAD-PC\1Data\3.Documentation\Isometric DWG MHI\" & I171 & ".pdf", "Drawing") -> Drawing | I171: E459
A172: 165 | B172: 1 1/2" - NGB-1663 - AS2A | C172: 1 1/2" | D172: NITROGEN GAS | E172: GAS | F172: A312-TP304 | H172: =HYPERLINK("\\CAD-PC\1Data\3.Documentation\Isometric DWG MHI\" & I172 & ".pdf", "Drawing") -> Drawing | I172: E460
A173: 166 | B173: 3/4" - NGB-2130-1 - AG1A | C173: 3/4" | D173: NITROGEN GAS | E173: GAS | F173: CS | H173: =HYPERLINK("\\CAD-PC\1Data\3.Documentation\Isometric DWG MHI\" & I173 & ".pdf", "Drawing") -> Drawing | I173: E461
A174: 167 | B174: 1 1/2" - NGB-2140 - AS1A | C174: 1 1/2" | D174: NITROGEN GAS | E174: GAS | F174: A312-TP304 | H174: =HYPERLINK("\\CAD-PC\1Data\3.Documentation\Isometric DWG MHI\" & I174 & ".pdf", "Drawing") -> Drawing | I174: E462
A175: 168 | B175: 3/4" - NGB-2360 - AG1A | C175: 3/4" | D175: NITROGEN GAS | E175: GAS | F175: CS | H175: =HYPERLINK("\\CAD-PC\1Data\3.Documentation\Isometric DWG MHI\" & I175 & ".pdf", "Drawing") -> Drawing | I175: E463
... A181: 174 | B181: 3/4" - NGB-4357-1 - AG1A | C181: 3/4" | D181: NITROGEN GAS | E181: GAS | F181: CS | H181: =HYPERLINK("\\CAD-PC\1Data\3.Documentation\Isometric DWG MHI\" & I181 & ".pdf", "Drawing") -> Drawing | I181: E470
A182: 175 | B182: 3/4" - P-4361-1 - AG1A | C182: 3/4" | D182: PROCESS | F182: CS | H182: =HYPERLINK("\\CAD-PC\1Data\3.Documentation\Isometric DWG MHI\" & I182 & ".pdf", "Drawing") -> Drawing | I182: E471
A183: 176 | B183: 3/4" - NGB-5166 - AG1A | C183: 3/4" | D183: NITROGEN GAS | E183: GAS | F183: CS | H183: =HYPERLINK("\\CAD-PC\1Data\3.Documentation\Isometric DWG MHI\" & I183 & ".pdf", "Drawing") -> Drawing | I183: E472
A184: 177 | B184: 3/4" - NGB-5357 - AG1C | C184: 3/4" | D184: NITROGEN GAS | E184: GAS | F184: CS | H184: =HYPERLINK("\\CAD-PC\1Data\3.Documentation\Isometric DWG MHI\" & I184 & ".pdf", "Drawing") -> Drawing | I184: E474
A185: 178 | B185: 1" - NGB-6160 - AG1A | C185: 1" | D185: NITROGEN GAS | E185: GAS | F185: CS | H185: =HYPERLINK("\\CAD-PC\1Data\3.Documentation\Isometric DWG MHI\" & I185 & ".pdf", "Drawing") -> Drawing | I185: E475
A186: 179 | B186: 3/4" - NGB-6357 - AG1A | C186: 3/4" | D186: NITROGEN GAS | E186: GAS | F186: CS | H186: =HYPERLINK("\\CAD-PC\1Data\3.Documentation\Isometric DWG MHI\" & I186 & ".pdf", "Drawing") -> Drawing | I186: E476
A187: 180 | B187: 1 1/2" - NGB-9653 - AG1C | C187: 1 1/2" | D187: NITROGEN GAS | E187: GAS | F187: CS | H187: =HYPERLINK("\\CAD-PC\1Data\3.Documentation\Isometric DWG MHI\" & I187 & ".pdf", "Drawing") -> Drawing | I187: E477
A188: 181 | B188: 1 1/2" - NGB-9654 - AG1C | C188: 1 1/2" | D188: NITROGEN GAS | E188: GAS | F188: CS | H188: =HYPERLINK("\\CAD-PC\1Data\3.Documentation\Isometric DWG MHI\" & I188 & ".pdf", "Drawing") -> Drawing | I188: E478
A189: 182 | B189: 3/4" - NGB-9855 - AG1A | C189: 3/4" | D189: NITROGEN GAS | E189: GAS | F189: CS | G189: H25 | H189: =HYPERLINK("\\CAD-PC\1Data\3.Documentation\Isometric DWG MHI\" & I189 & ".pdf", "Drawing") -> Drawing | I189: E480
A190: 183 | B190: 1 1/2" - NGB-9975 - AG1A | C190: 1 1/2" | D190: NITROGEN GAS | E190: GAS | F190: CS | H190: =HYPERLINK("\\CAD-PC\1Data\3.Documentation\Isometric DWG MHI\" & I190 & ".pdf", "Drawing") -> Drawing | I190: E483
A191: 184 | B191: 1 1/2" - NGB-1156 - AG1A | C191: 1 1/2" | D191: NITROGEN GAS | E191: GAS | F191: CS | H191: =HYPERLINK("\\CAD-PC\1Data\3.Documentation\Isometric DWG MHI\" & I191 & ".pdf", "Drawing") -> Drawing | I191: E484
A192: 185 | B192: 1 1/2" - NGB-4162 - AG1C | C192: 1 1/2" | D192: NITROGEN GAS | E192: GAS | F192: CS | H192: =HYPERLINK("\\CAD-PC\1Data\3.Documentation\Isometric DWG MHI\" & I192 & ".pdf", "Drawing") -> Drawing | I192: E486
A193: 186 | B193: 1 1/2" - NGB-4162 - AG1A | C193: 1 1/2" | D193: NITROGEN GAS | E193: GAS | F193: CS | H193: =HYPERLINK("\\CAD-PC\1Data\3.Documentation\Isometric DWG MHI\" & I193 & ".pdf", "Drawing") -> Drawing | I193: E487
A194: 187 | B194: 1 1/2" - NGB-9653 - AG1C | C194: 1 1/2" | D194: NITROGEN GAS | E194: GAS | F194: CS | H194: =HYPERLINK("\\CAD-PC\1Data\3.Documentation\Isometric DWG MHI\" & I194 & ".pdf", "Drawing") -> Drawing | I194: E488
A195: 188 | B195: 1 1/2" - NGB-9654 - AG1C | C195: 1 1/2" | D195: NITROGEN GAS | E195: GAS | F195: CS | H195: =HYPERLINK("\\CAD-PC\1Data\3.Documentation\Isometric DWG MHI\" & I195 & ".pdf", "Drawing") -> Drawing | I195: E489
A196: 189 | B196: 3/4" - NGB-3156-2 - AG1A | C196: 3/4" | D196: NITROGEN GAS | E196: GAS | F196: CS | H196: =HYPERLINK("\\CAD-PC\1Data\3.Documentation\Isometric DWG MHI\" & I196 & ".pdf", "Drawing") -> Drawing | I196: E491
A197: 190 | B197: 3/4" - NGB-4357-2 - AG1D | C197: 3/4" | D197: NITROGEN GAS | E197: GAS | F197: CS | H197: =HYPERLINK("\\CAD-PC\1Data\3.Documentation\Isometric DWG MHI\" & I197 & ".pdf", "Drawing") -> Drawing | I197: E492
A198: 191 | B198: 3/4" - NGB-4361-2 - AG1D | C198: 3/4" | D198: NITROGEN GAS | E198: GAS | F198: CS | H198: =HYPERLINK("\\CAD-PC\1Data\3.Documentation\Isometric DWG MHI\" & I198 & ".pdf", "Drawing") -> Drawing | I198: E493
A199: 192 | B199: 1 1/2" - NGS-1040 - AG1A | C199: 1 1/2" | D199: NITROGEN GAS | E199: GAS | F199: CS | H199: =HYPERLINK("\\CAD-PC\1Data\3.Documentation\Isometric DWG MHI\" & I199 & ".pdf", "Drawing") -> Drawing | I199: E509
A200: 193 | B200: 3/4" - NGS-1149 - AG1A | C200: 3/4" | D200: NITROGEN GAS | E200: GAS | F200: CS | H200: =HYPERLINK("\\CAD-PC\1Data\3.Documentation\Isometric DWG MHI\" & I200 & ".pdf", "Drawing") -> Drawing | I200: E511
A201: 194 | B201: 1" - NGS-1150 - AG1B | C201: 1" | D201: NITROGEN GAS | E201: GAS | F201: CS | H201: =HYPERLINK("\\CAD-PC\1Data\3.Documentation\Isometric DWG MHI\" & I201 & ".pdf", "Drawing") -> Drawing | I201: E512
... A266: 259 | B266: 3/4" - NGS-HS162 - AG1A | C266: 3/4" | D266: NITROGEN GAS | E266: GAS | F266: CS | H266: =HYPERLINK("\\CAD-PC\1Data\3.Documentation\Isometric DWG MHI\" & I266 & ".pdf", "Drawing") -> Drawing | I266: E596
A267: 260 | B267: 1 1/2" - P-1206 - AS1A | C267: 1 1/2" | D267: PROCESS | F267: A312-TP304 | H267: =HYPERLINK("\\CAD-PC\1Data\3.Documentation\Isometric DWG MHI\" & I267 & ".pdf", "Drawing") -> Drawing | I267: E601
A268: 261 | B268: 3/4" - P-1207 - AS1A | C268: 3/4" | D268: PROCESS | F268: A312-TP304 | H268: =HYPERLINK("\\CAD-PC\1Data\3.Documentation\Isometric DWG MHI\" & I268 & ".pdf", "Drawing") -> Drawing | I268: E602
A269: 262 | B269: 3/4" - P-1208 - AS1A | C269: 3/4" | D269: PROCESS | F269: A312-TP304 | H269: =HYPERLINK("\\CAD-PC\1Data\3.Documentation\Isometric DWG MHI\" & I269 & ".pdf", "Drawing") -> Drawing | I269: E603
A270: 263 | B270: 1 1/2" - P-1211 - AG1C | C270: 1 1/2" | D270: PROCESS | F270: CS | H270: =HYPERLINK("\\CAD-PC\1Data\3.Documentation\Isometric DWG MHI\" & I270 & ".pdf", "Drawing") -> Drawing | I270: E604
A271: 264 | B271: 1 1/2" - P-1304 - BS1A | C271: 1 1/2" | D271: PROCESS | F271: A312-TP304 | H271: =HYPERLINK("\\CAD-PC\1Data\3.Documentation\Isometric DWG MHI\" & I271 & ".pdf", "Drawing") -> Drawing | I271: E607
A272: 265 | B272: 1 1/2" - P-1305 - BS1A | C272: 1 1/2" | D272: PROCESS | F272: A312-TP304 | H272: =HYPERLINK("\\CAD-PC\1Data\3.Documentation\Isometric DWG MHI\" & I272 & ".pdf", "Drawing") -> Drawing | I272: E608
A273: 266 | B273: 1" - P-1306 - BS1A | C273: 1" | D273: PROCESS | F273: A312-TP304 | H273: =HYPERLINK("\\CAD-PC\1Data\3.Documentation\Isometric DWG MHI\" & I273 & ".pdf", "Drawing") -> Drawing | I273: E609
A274: 267 | B274: 3/4" - P-1307 - BS1A | C274: 3/4" | D274: PROCESS | F274: A312-TP304 | H274: =HYPERLINK("\\CAD-PC\1Data\3.Documentation\Isometric DWG MHI\" & I274 & ".pdf", "Drawing") -> Drawing | I274: E610
A275: 268 | B275: 1 1/2" - P-1413 - AS1A | C275: 1 1/2" | D275: PROCESS | F275: A312-TP304 | H275: =HYPERLINK("\\CAD-PC\1Data\3.Documentation\Isometric DWG MHI\" & I275 & ".pdf", "Drawing") -> Drawing | I275: E612
A276: 269 | B276: 3/4" - P-1416 - AS1A | C276: 3/4" | D276: PROCESS | F276: A312-TP304 | H276: =HYPERLINK("\\CAD-PC\1Data\3.Documentation\Isometric DWG MHI\" & I276 & ".pdf", "Drawing") -> Drawing | I276: E613
A277: 270 | B277: 1 1/2" - P-1422 - BS1A | C277: 1 1/2" | D277: PROCESS | F277: A312-TP304 | G277: H25 | H277: =HYPERLINK("\\CAD-PC\1Data\3.Documentation\Isometric DWG MHI\" & I277 & ".pdf", "Drawing") -> Drawing | I277: E615
A278: 271 | B278: 3/4" - P-1429 - AS1A | C278: 3/4" | D278: PROCESS | F278: A312-TP304 | H278: =HYPERLINK("\\CAD-PC\1Data\3.Documentation\Isometric DWG MHI\" & I278 & ".pdf", "Drawing") -> Drawing | I278: E616
A279: 272 | B279: 1" - P-1506 - AS1A | C279: 1" | D279: PROCESS | F279: A312-TP304 | H279: =HYPERLINK("\\CAD-PC\1Data\3.Documentation\Isometric DWG MHI\" & I279 & ".pdf", "Drawing") -> Drawing | I279: E617
A280: 273 | B280: 1" - P-1514 - AS1A | C280: 1" | D280: PROCESS | F280: A312-TP304 | H280: =HYPERLINK("\\CAD-PC\1Data\3.Documentation\Isometric DWG MHI\" & I280 & ".pdf", "Drawing") -> Drawing | I280: E618
A281: 274 | B281: 1" - P-1623 - AS1A | C281: 1" | D281: PROCESS | F281: A312-TP304 | H281: =HYPERLINK("\\CAD-PC\1Data\3.Documentation\Isometric DWG MHI\" & I281 & ".pdf", "Drawing") -> Drawing | I281: E619
A282: 275 | B282: 1 1/2" - P-1624 - AS1A | C282: 1 1/2" | D282: PROCESS | F282: A312-TP304 | H282: =HYPERLINK("\\CAD-PC\1Data\3.Documentation\Isometric DWG MHI\" & I282 & ".pdf", "Drawing") -> Drawing | I282: E620
A283: 276 | B283: 1" - P-1627 - AS1A | C283: 1" | D283: PROCESS | F283: A312-TP304 | H283: =HYPERLINK("\\CAD-PC\1Data\3.Documentation\Isometric DWG MHI\" & I283 & ".pdf", "Drawing") -> Drawing | I283: E621
A284: 277 | B284: 1" - P-1628 - AS1A | C284: 1" | D284: PROCESS | F284: A312-TP304 | H284: =HYPERLINK("\\CAD-PC\1Data\3.Documentation\Isometric DWG MHI\" & I284 & ".pdf", "Drawing") -> Drawing | I284: E622
A285: 278 | B285: 3/4" - P-1630 - AS1A | C285: 3/4" | D285: PROCESS | F285: A312-TP304 | H285: =HYPERLINK("\\CAD-PC\1Data\3.Documentation\Isometric DWG MHI\" & I285 & ".pdf", "Drawing") -> Drawing | I285: E623
A286: 279 | B286: 3/4" - P-1635 - AS1A | C286: 3/4" | D286: PROCESS | F286: A312-TP304 | H286: =HYPERLINK("\\CAD-PC\1Data\3.Documentation\Isometric DWG MHI\" & I286 & ".pdf", "Drawing") -> Drawing | I286: E624
A287: 280 | B287: 1" - P-1637 - AS1A | C287: 1" | D287: PROCESS | F287: A312-TP304 | H287: =HYPERLINK("\\CAD-PC\1Data\3.Documentation\Isometric DWG MHI\" & I287 & ".pdf", "Drawing") -> Drawing | I287: E625
A288: 281 | B288: 3/4" - P-1642 - AS1A | C288: 3/4" | D288: PROCESS | F288: A312-TP304 | H288: =HYPERLINK("\\CAD-PC\1Data\3.Documentation\Isometric DWG MHI\" & I288 & ".pdf", "Drawing") -> Drawing | I288: E626
A289: 282 | B289: 1 1/2" - P-1644 - AS1A | C289: 1 1/2" | D289: PROCESS | F289: A312-TP304 | H289: =HYPERLINK("\\CAD-PC\1Data\3.Documentation\Isometric DWG MHI\" & I289 & ".pdf", "Drawing") -> Drawing | I289: E627
...

Sheet 47-1
C1: EQUIPMENT LIST | G1: Document No. | H1: : MNTC-ME
G2: Revision | H2: : 0
G3: Date of issue | H3: : 2025
A4: PT. PETRO OXO NUSANTARA | G4: Page | H4: :
A5: VALVE LIST SYN GAS
A7: NO | B7: Code | C7: Line Number piping + accecories | D7: Diameter | E7: SCH | F7: Valve | G7: Material | H7: Remark
A9: Syngas
A10: 1 | B10: A001 | C10: 2"-BBD-0155-BG4A-H25 | D10: =LEFT(C10, FIND("""", C10)) -> 2" | E10: 40 | F10: GV 1,2,3,4 | G10: Carbon steel | I10: 1
A11: 2 | B11: A002 | C11: 2"-BBD-0156-BG4A-H25 | D11: =LEFT(C11, FIND("""", C11)) -> 2" | E11: 40 | F11: GV1 | I11: 1
D12: 1/2" | F12: GV1 | I12: 1
D13: 1 1/2" | F13: GV1 | I13: 1
A14: 3 | B14: A003 | C14: 2"-BBD-0156-AG1B-H25 | D14: =LEFT(C14, FIND("""", C14)) -> 2" | E14: 40 | F14: GV1,2 | I14: 1
D15: 1 1/2" | F15: GV1,2 | I15: 1
A16: 4 | B16: A004 | C16: 2"-BBD-0157-BG4A-H25 | D16: =LEFT(C16, FIND("""", C16)) -> 2" | E16: 40 | F16: GV1,2,3,4 | I16: 1
A17: 5 | B17: A005 | C17: 2"-BBD-0157-BG4A | D17: =LEFT(C17, FIND("""", C17)) -> 2" | E17: 40 | F17: GV1 | I17: 1
A18: 6 | B18: A006 | C18: 10"-BBD-0157-BG4A | D18: =LEFT(C18, FIND("""", C18)) -> 10" | E18: 20 | I18: 1
A19: 7 | B19: A007 | C19: 2"-BBD-0156-AG1B-H25 | D19: =LEFT(C19, FIND("""", C19)) -> 2" | E19: 40
A20: 8 | B20: A008 | C20: 2"-BBD-0156-AG1B-H25 | D20: =LEFT(C20, FIND("""", C20)) -> 2" | E20: 40
A21: 9 | B21: A011 | C21: 4"-BFW-0173-BG4A-H25 | D21: =LEFT(C21, FIND("""", C21)) -> 4" | E21: 40 | F21: GV1 | I21: 1
D22: 3/4" | E22: 80 | F22: GV1 | I22: 1
D23: 1/2" | E23: 80 | F23: GV1,2 | I23: 1
A24: 10 | B24: A012 | C24: 4"-BFW-0182-BG4A-H30 | D24: =LEFT(C24, FIND("""", C24)) -> 4" | E24: 40 | F24: GV1,2 | I24: 1
A25: 11 | B25: A013 | C25: 4"-BFW-0182-BG4A-H30 | D25: =LEFT(C25, FIND("""", C25)) -> 4" | E25: 40 | F25: GV1 | I25: 1
D26: 4" | F26: CV1 | I26: 1
D27: 3/4" | F27: GV1 | I27: 1
A28: 12 | B28: A014 | C28: 4"-BFW-0182-BG4A-H30 | D28: =LEFT(C28, FIND("""", C28)) -> 4" | E28: 40 | I28: 1
A29: 13 | B29: A015 | C29: 4"-BFW-0173-BG4A-H25 | D29: =LEFT(C29, FIND("""", C29)) -> 4" | E29: 40 | I29: 1
A30: 14 | B30: A016 | C30: 4"-BFW-0173-BG4A-H25 | D30: =LEFT(C30, FIND("""", C30)) -> 4" | E30: 40 | I30: 1
A31: 15 | B31: A021 | C31: 6"-CWR-0274-AG1A | D31: =LEFT(C31, FIND("""", C31)) -> 6" | E31: 40 | I31: 1
A32: 16 | B32: A022 | C32: 6"-CWR-0175-AG1A | D32: =LEFT(C32, FIND("""", C32)) -> 6" | E32: 40 | F32: - | I32: 1
C33: Check valve | D33: 6" | F33: CV 1 | I33: 1
D34: 3/4" | F34: GV1 | I34: 1
A35: 17 | B35: A023 | C35: 6"-CWR-0276-AG1A | D35: =LEFT(C35, FIND("""", C35)) -> 6" | E35: 40 | F35: BV1 | I35: 1
A36: 18 | B36: A024 | C36: 2"-CWR-0278-AG1A | D36: =LEFT(C36, FIND("""", C36)) -> 2" | E36: 40 | I36: 1
A37: 19 | B37: A025 | C37: 3"-CWR-0372-AG1A | D37: =LEFT(C37, FIND("""", C37)) -> 3" | E37: 40 | I37: 1
A38: 20 | B38: A026 | C38: 14"-CWR-9465-AG1A | D38: =LEFT(C38, FIND("""", C38)) -> 14" | E38: 20 | I38: 1
D39: 2" | F39: GV1 | I39: 1
A40: 21 | B40: A027 | C40: 2"-CWR-0072-AG1A | D40: =LEFT(C40, FIND("""", C40)) -> 2" | I40: 1
A41: 22 | B41: A028 | C41: 2"-CWR-0072-AG1A | D41: =LEFT(C41, FIND("""", C41)) -> 2" | I41: 1
A42: 23 | B42: A029 | C42: 14"-CWR-9465-AG1A | D42: =LEFT(C42, FIND("""", C42)) -> 14" | E42: 20 | I42: 1
A43: 24 | B43: A030 | C43: 3"-CWR-0185-AG1A | D43: =LEFT(C43, FIND("""", C43)) -> 3" | I43: 1
A44: 25 | B44: A031 | C44: 3"-CWR-0078-AG1A | D44: =LEFT(C44, FIND("""", C44)) -> 3" | I44: 1
A45: 26 | B45: A032 | C45: 8"-CWR-9465-AG1A (1/2) (2/2) | D45: =LEFT(C45, FIND("""", C45)) -> 8" | E45: 20 | I45: 1
A46: 27 | B46: A033 | C46: 4"-CWR-0174-AG1A | D46: =LEFT(C46, FIND("""", C46)) -> 4" | E46: 40 | F46: - | I46: 1
D47: 3/4" | F47: GV1 | I47: 1
A48: 28 | B48: A034 | C48: 6"-CWR-0176-AG1A | D48: =LEFT(C48, FIND("""", C48)) -> 6" | E48: 40 | I48: 1
A49: 29 | B49: A035 | C49: 3"-CWR-0181-AG1A | D49: =LEFT(C49, FIND("""", C49)) -> 3" | E49: 40 | I49: 1
A50: 30 | B50: A036 | C50: 2"-CWR-0183-AG1A | D50: =LEFT(C50, FIND("""", C50)) -> 2" | E50: 40 | I50: 1
A51: 31 | B51: A037 | C51: 4"-CWR-0076-AG1A | D51: =LEFT(C51, FIND("""", C51)) -> 4" | E51: 40 | I51: 1
A52: 32 | B52: A061 | C52: 6"-CWS-0273-AG1A | D52: =LEFT(C52, FIND("""", C52)) -> 6" | E52: 40 | F52: - | I52: 1
C53: Check valve | D53: 6" | F53: CV 1 | I53: 1
A54: 33 | B54: A062 | C54: 6"-CWS-0275-AG1A | D54: =LEFT(C54, FIND("""", C54)) -> 6" | I54: 1
A55: 34 | B55: A063 | C55: 2"-CWS-0277-AG1A | D55: =LEFT(C55, FIND("""", C55)) -> 2" | F55: - | I55: 1
A56: 35 | B56: A064 | C56: 6"-CWS-0174-AG1A | D56: =LEFT(C56, FIND("""", C56)) -> 6" | E56: 40 | F56: - | I56: 1
C57: Check valve | D57: 6" | F57: CV 1 | I57: 1
A58: 36 | B58: A065 | C58: 3"-CWS-0371-AG1A | D58: =LEFT(C58, FIND("""", C58)) -> 3" | F58: - | I58: 1
A59: 37 | B59: A066 | C59: 14"-CWS-9455-AG1A | D59: =LEFT(C59, FIND("""", C59)) -> 14" | F59: - | I59: 1
D60: 2" | F60: GV1 | I60: 1
A61: 38 | B61: A067 | C61: 2"-CWS-0071-AG1A | D61: =LEFT(C61, FIND("""", C61)) -> 2" | F61: - | I61: 1
A62: 39 | B62: A068 | C62: 2"-CWS-0071-AG1A | D62: =LEFT(C62, FIND("""", C62)) -> 2" | F62: - | I62: 1
A63: 40 | B63: A069 | C63: 14"-CWS-9455-AG1A | D63: =LEFT(C63, FIND("""", C63)) -> 14" | I63: 1
A64: 41 | B64: A070 | C64: 3"-CWS-0077-AG1A | D64: =LEFT(C64, FIND("""", C64)) -> 3" | I64: 1
A65: 42 | B65: A071 | C65: 8"-CWS-9455-AG1A | D65: =LEFT(C65, FIND("""", C65)) -> 8" | I65: 1
A66: 43 | B66: A073 | C66: 4"-CWS-0075-AG1A | D66: =LEFT(C66, FIND("""", C66)) -> 4" | I66: 1
A67: 44 | B67: A074 | C67: 3"-CWS-0173-AG1A | D67: =LEFT(C67, FIND("""", C67)) -> 3" | I67: 1
A68: 45 | B68: A075 | C68: 6"-CWS-0175-AG1A | D68: =LEFT(C68, FIND("""", C68)) -> 6" | I68: 1
A69: 46 | B69: A076 | C69: 3"-CWS-0180-AG1A | D69: =LEFT(C69, FIND("""", C69)) -> 3" | I69: 1
A70: 47 | B70: A077 | C70: 2"-CWS-0182-AG1A | D70: =LEFT(C70, FIND("""", C70)) -> 2" | I70: 1
A71: 48 | B71: A078 | C71: 3"-CWS-0184-AG1A | D71: =LEFT(C71, FIND("""", C71)) -> 3" | I71: 1
A72: 49 | B72: A131 | C72: 6"-FGS-0360-AG1C | D72: =LEFT(C72, FIND("""", C72)) -> 6" | F72: - | I72: 1
A73: 50 | B73: A132 | C73: 6"-FGS-0362-AG1C | D73: =LEFT(C73, FIND("""", C73)) -> 6" | F73: - | I73: 1
A74: 51 | B74: A133 | C74: 6"-FGS-0361-AG1C | D74: =LEFT(C74, FIND("""", C74)) -> 6" | F74: GV1 | I74: 1
D75: 6" | F75: CV 1 | I75: 1
D76: 3/4" | F76: GV1 | I76: 1
A77: 52 | B77: A134 | C77: 10"-FGS-0360-AG1C | D77: =LEFT(C77, FIND("""", C77)) -> 10" | E77: 20 | F77: GV 1 | I77: 1
C78: Non return check valve | D78: 10" | E78: 20 | F78: NR CV 1 | I78: 1
D79: 1/2" | F79: GV 1,2,3,4,5,6 | I79: 1
A80: 53 | B80: A135 | C80: 12"-FGS-0182-AG1C | D80: =LEFT(C80, FIND("""", C80)) -> 12" | F80: - | I80: 1
D81: 1/2" | F81: GV1,2,3,4 | I81: 1
A82: 54 | B82: A136 | C82: 10"-FGS-0360-AG1C | D82: =LEFT(C82, FIND("""", C82)) -> 10" | I82: 1
A83: 55 | B83: A137 | C83: 6"-FGS-0361-AG1C | D83: =LEFT(C83, FIND("""", C83)) -> 6" | E83: 40 | F83: GV 1, 2 | I83: 1
C84: Non return check valve | D84: 6" | E84: 40 | F84: NR CV 1 | I84: 1
D85: 3/4" | F85: GV 1,2 | I85: 1
D86: 1/2" | F86: GV 1,2,3,4,5 | I86: 1
A87: 56 | B87: A138 | C87: 6"-FGS-0362-AG1C | D87: =LEFT(C87, FIND("""", C87)) -> 6" | I87: 1
A88: 57 | B88: A139 | C88: 6"-FGS-0361-AG1C | D88: =LEFT(C88, FIND("""", C88)) -> 6" | I88: 1
A89: 58 | B89: A140 | C89: 4"-FGS-0361-AG1A | D89: =LEFT(C89, FIND("""", C89)) -> 4" | I89: 1
A90: 59 | B90: A141 | C90: 4"-FNG-9602-AG1C | D90: =LEFT(C90, FIND("""", C90)) -> 4" | F90: - | I90: 1
A91: 60 | B91: A142 | C91: 1-1/2"-FNG-9602-AG1C | D91: =LEFT(C91, FIND("""", C91)) -> 1-1/2" | F91: - | I91: 1
A92: 61 | B92: A143 | C92: 6"-FNG-0112-AG1C | D92: =LEFT(C92, FIND("""", C92)) -> 6" | E92: 40 | F92: - | I92: 1
D93: 3" | F93: GV 1,2 | I93: 1
D94: 2" | F94: GV 2 | I94: 1
D95: 3/4" | F95: GV 1 | I95: 1
D96: 1/2" | F96: GV 1,2,3 | I96: 1
C97: Non Retuern Check valve | D97: 3" | E97: 40 | F97: NR CV 1 | I97: 1
A98: 62 | B98: A144 | C98: 6"-FNG-0112-AG1C | D98: =LEFT(C98, FIND("""", C98)) -> 6" | F98: - | I98: 1
A99: 63 | B99: A145 | C99: 6"-FNG-0112-AG1C | D99: =LEFT(C99, FIND("""", C99)) -> 6" | F99: - | I99: 1
D100: 3" | F100: GV1 | I100: 1
D101: 1/2" | F101: GV1,2 | I101: 1
A102: 64 | B102: A146 | C102: 4"-FNG-9602-AG1C | D102: =LEFT(C102, FIND("""", C102)) -> 4" | I102: 1
...

Sheet 47
D1: EQUIPMENT LIST | I1: Document No. | J1: : MNTC-ME
I2: Revision | J2: : 0
I3: Date of issue | J3: : 2025
A4: PT. PETRO OXO NUSANTARA | I4: Page | J4: :
A5: PIPING LIST SYN GAS
B7: No | C7: Line No. | D7: Size | E7: Service | F7: Fluid | G7: Material | H7: Insulation | I7: ISO Drawing | J7: PAGE NO. | K7: Pipe length ( mm )
B8: 1 | C8: 2"-BBD-0155-BG4A-H25 | D8: =LEFT(C8, FIND("""", C8)) -> 2" | E8: Boiler Blow Down | F8: Water & Steam | G8: CS | H8: H25 | I8: =HYPERLINK("\\CAD-PC\1Data\3.Documentation\Isometric DWG MHI\" & J8 & ".pdf", C8) -> 2"-BBD-0155-BG4A-H25 | J8: A001
B9: 2 | C9: 2"-BBD-0156-BG4A-H25 | D9: =LEFT(C9, FIND("""", C9)) -> 2" | E9: Boiler Blow Down | F9: Water & Steam | G9: CS | H9: H25 | I9: =HYPERLINK("\\CAD-PC\1Data\3.Documentation\Isometric DWG MHI\" & J9 & ".pdf", C9) -> 2"-BBD-0156-BG4A-H25 | J9: A002
B10: 3 | C10: 2"-BBD-0156-AG1B-H25 | D10: =LEFT(C10, FIND("""", C10)) -> 2" | E10: Boiler Blow Down | F10: Water & Steam | G10: CS | H10: H25 | I10: =HYPERLINK("\\CAD-PC\1Data\3.Documentation\Isometric DWG MHI\" & J10 & ".pdf", C10) -> 2"-BBD-0156-AG1B-H25 | J10: A003
B11: 4 | C11: 2"-BBD-0157-BG4A-H25 | D11: =LEFT(C11, FIND("""", C11)) -> 2" | E11: Boiler Blow Down | F11: Water & Steam | G11: CS | H11: H25 | I11: =HYPERLINK("\\CAD-PC\1Data\3.Documentation\Isometric DWG MHI\" & J11 & ".pdf", C11) -> 2"-BBD-0157-BG4A-H25 | J11: A004
B12: 5 | C12: 2"-BBD-0157-BG4A | D12: =LEFT(C12, FIND("""", C12)) -> 2" | E12: Boiler Blow Down | F12: Water & Steam | G12: CS | I12: =HYPERLINK("\\CAD-PC\1Data\3.Documentation\Isometric DWG MHI\" & J12 & ".pdf", C12) -> 2"-BBD-0157-BG4A | J12: A005
B13: 6 | C13: 10"-BBD-0157-BG4A | D13: =LEFT(C13, FIND("""", C13)) -> 10" | E13: Boiler Blow Down | F13: Water & Steam | G13: CS | I13: =HYPERLINK("\\CAD-PC\1Data\3.Documentation\Isometric DWG MHI\" & J13 & ".pdf", C13) -> 10"-BBD-0157-BG4A | J13: A006
B14: 7 | C14: 2"-BBD-0156-AG1B-H25 | D14: =LEFT(C14, FIND("""", C14)) -> 2" | E14: Boiler Blow Down | F14: Water & Steam | G14: CS | H14: H25 | I14: =HYPERLINK("\\CAD-PC\1Data\3.Documentation\Isometric DWG MHI\" & J14 & ".pdf", C14) -> 2"-BBD-0156-AG1B-H25 | J14: A007 | K14: 44545
B15: 8 | C15: 2"-BBD-0156-AG1B-H25 | D15: =LEFT(C15, FIND("""", C15)) -> 2" | E15: Boiler Blow Down | F15: Water & Steam | G15: CS | H15: H25 | I15: =HYPERLINK("\\CAD-PC\1Data\3.Documentation\Isometric DWG MHI\" & J15 & ".pdf", C15) -> 2"-BBD-0156-AG1B-H25 | J15: A008 | K15: 1977
B16: 9 | C16: 4"-BFW-0173-BG4A-H25 | D16: =LEFT(C16, FIND("""", C16)) -> 4" | E16: Boiler Feed Water | F16: Water | G16: CS | H16: H25 | I16: =HYPERLINK("\\CAD-PC\1Data\3.Documentation\Isometric DWG MHI\" & J16 & ".pdf", C16) -> 4"-BFW-0173-BG4A-H25 | J16: A011
B17: 10 | C17: 4"-BFW-0182-BG4A-H30 | D17: =LEFT(C17, FIND("""", C17)) -> 4" | E17: Boiler Feed Water | F17: Water | G17: CS | H17: H30 | I17: =HYPERLINK("\\CAD-PC\1Data\3.Documentation\Isometric DWG MHI\" & J17 & ".pdf", C17) -> 4"-BFW-0182-BG4A-H30 | J17: A012
B18: 11 | C18: 4"-BFW-0182-BG4A-H30 | D18: =LEFT(C18, FIND("""", C18)) -> 4" | E18: Boiler Feed Water | F18: Water | G18: CS | H18: H30 | I18: =HYPERLINK("\\CAD-PC\1Data\3.Documentation\Isometric DWG MHI\" & J18 & ".pdf", C18) -> 4"-BFW-0182-BG4A-H30 | J18: A013
B19: 12 | C19: 4"-BFW-0182-BG4A-H30 | D19: =LEFT(C19, FIND("""", C19)) -> 4" | E19: Boiler Feed Water | F19: Water | G19: CS | H19: H30 | I19: =HYPERLINK("\\CAD-PC\1Data\3.Documentation\Isometric DWG MHI\" & J19 & ".pdf", C19) -> 4"-BFW-0182-BG4A-H30 | J19: A014
B20: 13 | C20: 4"-BFW-0173-BG4A-H25 | D20: =LEFT(C20, FIND("""", C20)) -> 4" | E20: Boiler Feed Water | F20: Water | G20: CS | H20: H25 | I20: =HYPERLINK("\\CAD-PC\1Data\3.Documentation\Isometric DWG MHI\" & J20 & ".pdf", C20) -> 4"-BFW-0173-BG4A-H25 | J20: A015 | K20: 38600
B21: 14 | C21: 4"-BFW-0173-BG4A-H25 | D21: =LEFT(C21, FIND("""", C21)) -> 4" | E21: Boiler Feed Water | F21: Water | G21: CS | H21: H25 | I21: =HYPERLINK("\\CAD-PC\1Data\3.Documentation\Isometric DWG MHI\" & J21 & ".pdf", C21) -> 4"-BFW-0173-BG4A-H25 | J21: A016 | K21: 8855
B22: 15 | C22: 6"-CWR-0274-AG1A | D22: =LEFT(C22, FIND("""", C22)) -> 6" | E22: Cooling Water | F22: Water | G22: CS | I22: =HYPERLINK("\\CAD-PC\1Data\3.Documentation\Isometric DWG MHI\" & J22 & ".pdf", C22) -> 6"-CWR-0274-AG1A | J22: A021
B23: 16 | C23: 6"-CWR-0175-AG1A | D23: =LEFT(C23, FIND("""", C23)) -> 6" | E23: Cooling Water | F23: Water | G23: CS | I23: =HYPERLINK("\\CAD-PC\1Data\3.Documentation\Isometric DWG MHI\" & J23 & ".pdf", C23) -> 6"-CWR-0175-AG1A | J23: A022
B24: 17 | C24: 6"-CWR-0276-AG1A | D24: =LEFT(C24, FIND("""", C24)) -> 6" | E24: Cooling Water | F24: Water | G24: CS | I24: =HYPERLINK("\\CAD-PC\1Data\3.Documentation\Isometric DWG MHI\" & J24 & ".pdf", C24) -> 6"-CWR-0276-AG1A | J24: A023
B25: 18 | C25: 2"-CWR-0278-AG1A | D25: =LEFT(C25, FIND("""", C25)) -> 2" | E25: Cooling Water | F25: Water | G25: CS | I25: =HYPERLINK("\\CAD-PC\1Data\3.Documentation\Isometric DWG MHI\" & J25 & ".pdf", C25) -> 2"-CWR-0278-AG1A | J25: A024
B26: 19 | C26: 3"-CWR-0372-AG1A | D26: =LEFT(C26, FIND("""", C26)) -> 3" | E26: Cooling Water | F26: Water | G26: CS | I26: =HYPERLINK("\\CAD-PC\1Data\3.Documentation\Isometric DWG MHI\" & J26 & ".pdf", C26) -> 3"-CWR-0372-AG1A | J26: A025
B27: 20 | C27: 14"-CWR-9465-AG1A | D27: =LEFT(C27, FIND("""", C27)) -> 14" | E27: Cooling Water | F27: Water | G27: CS | I27: =HYPERLINK("\\CAD-PC\1Data\3.Documentation\Isometric DWG MHI\" & J27 & ".pdf", C27) -> 14"-CWR-9465-AG1A | J27: A026
B28: 21 | C28: 2"-CWR-0072-AG1A | D28: =LEFT(C28, FIND("""", C28)) -> 2" | E28: Cooling Water | F28: Water | G28: CS | I28: =HYPERLINK("\\CAD-PC\1Data\3.Documentation\Isometric DWG MHI\" & J28 & ".pdf", C28) -> 2"-CWR-0072-AG1A | J28: A027
B29: 22 | C29: 2"-CWR-0072-AG1A | D29: =LEFT(C29, FIND("""", C29)) -> 2" | E29: Cooling Water | F29: Water | G29: CS | I29: =HYPERLINK("\\CAD-PC\1Data\3.Documentation\Isometric DWG MHI\" & J29 & ".pdf", C29) -> 2"-CWR-0072-AG1A | J29: A028
B30: 23 | C30: 14"-CWR-9465-AG1A | D30: =LEFT(C30, FIND("""", C30)) -> 14" | E30: Cooling Water | F30: Water | G30: CS | I30: =HYPERLINK("\\CAD-PC\1Data\3.Documentation\Isometric DWG MHI\" & J30 & ".pdf", C30) -> 14"-CWR-9465-AG1A | J30: A029 | K30: 19307
B31: 24 | C31: 3"-CWR-0185-AG1A | D31: =LEFT(C31, FIND("""", C31)) -> 3" | E31: Cooling Water | F31: Water | G31: CS | I31: =HYPERLINK("\\CAD-PC\1Data\3.Documentation\Isometric DWG MHI\" & J31 & ".pdf", C31) -> 3"-CWR-0185-AG1A | J31: A030
B32: 25 | C32: 3"-CWR-0078-AG1A | D32: =LEFT(C32, FIND("""", C32)) -> 3" | E32: Cooling Water | F32: Water | G32: CS | I32: =HYPERLINK("\\CAD-PC\1Data\3.Documentation\Isometric DWG MHI\" & J32 & ".pdf", C32) -> 3"-CWR-0078-AG1A | J32: A031 | K32: 7626
B33: 26 | C33: 8"-CWR-9465-AG1A (1/2) (2/2) | D33: =LEFT(C33, FIND("""", C33)) -> 8" | E33: Cooling Water | F33: Water | G33: CS | I33: =HYPERLINK("\\CAD-PC\1Data\3.Documentation\Isometric DWG MHI\" & J33 & ".pdf", C33) -> 8"-CWR-9465-AG1A (1/2) (2/2) | J33: A032 | K33: 54420
B34: 27 | C34: 4"-CWR-0174-AG1A | D34: =LEFT(C34, FIND("""", C34)) -> 4" | E34: Cooling Water | F34: Water | G34: CS | I34: =HYPERLINK("\\CAD-PC\1Data\3.Documentation\Isometric DWG MHI\" & J34 & ".pdf", C34) -> 4"-CWR-0174-AG1A | J34: A033 | K34: 1872 | M34: =397+220+239+550+466 -> 1872
B35: 28 | C35: 6"-CWR-0176-AG1A | D35: =LEFT(C35, FIND("""", C35)) -> 6" | E35: Cooling Water | F35: Water | G35: CS | I35: =HYPERLINK("\\CAD-PC\1Data\3.Documentation\Isometric DWG MHI\" & J35 & ".pdf", C35) -> 6"-CWR-0176-AG1A | J35: A034 | K35: 3951 | M35: =747+700+356+2148 -> 3951
B36: 29 | C36: 3"-CWR-0181-AG1A | D36: =LEFT(C36, FIND("""", C36)) -> 3" | E36: Cooling Water | F36: Water | G36: CS | I36: =HYPERLINK("\\CAD-PC\1Data\3.Documentation\Isometric DWG MHI\" & J36 & ".pdf", C36) -> 3"-CWR-0181-AG1A | J36: A035 | K36: 6063 | M36: =297+400+900+3200+800+466 -> 6063
B37: 30 | C37: 2"-CWR-0183-AG1A | D37: =LEFT(C37, FIND("""", C37)) -> 2" | E37: Cooling Water | F37: Water | G37: CS | I37: =HYPERLINK("\\CAD-PC\1Data\3.Documentation\Isometric DWG MHI\" & J37 & ".pdf", C37) -> 2"-CWR-0183-AG1A | J37: A036 | K37: 8776 | M37: =385+650+410+3900+650+2340+300+141 -> 8776
B38: 31 | C38: 4"-CWR-0076-AG1A | D38: =LEFT(C38, FIND("""", C38)) -> 4" | E38: Cooling Water | F38: Water | G38: CS | I38: =HYPERLINK("\\CAD-PC\1Data\3.Documentation\Isometric DWG MHI\" & J38 & ".pdf", C38) -> 4"-CWR-0076-AG1A | J38: A037
B39: 32 | C39: 6"-CWS-0273-AG1A | D39: =LEFT(C39, FIND("""", C39)) -> 6" | E39: Cooling Water | F39: Water | G39: CS | I39: =HYPERLINK("\\CAD-PC\1Data\3.Documentation\Isometric DWG MHI\" & J39 & ".pdf", C39) -> 6"-CWS-0273-AG1A | J39: A061
B40: 33 | C40: 6"-CWS-0275-AG1A | D40: =LEFT(C40, FIND("""", C40)) -> 6" | E40: Cooling Water | F40: Water | G40: CS | I40: =HYPERLINK("\\CAD-PC\1Data\3.Documentation\Isometric DWG MHI\" & J40 & ".pdf", C40) -> 6"-CWS-0275-AG1A | J40: A062
B41: 34 | C41: 2"-CWS-0277-AG1A | D41: =LEFT(C41, FIND("""", C41)) -> 2" | E41: Cooling Water | F41: Water | G41: CS | I41: =HYPERLINK("\\CAD-PC\1Data\3.Documentation\Isometric DWG MHI\" & J41 & ".pdf", C41) -> 2"-CWS-0277-AG1A | J41: A063
B42: 35 | C42: 6"-CWS-0174-AG1A | D42: =LEFT(C42, FIND("""", C42)) -> 6" | E42: Cooling Water | F42: Water | G42: CS | I42: =HYPERLINK("\\CAD-PC\1Data\3.Documentation\Isometric DWG MHI\" & J42 & ".pdf", C42) -> 6"-CWS-0174-AG1A | J42: A064
B43: 36 | C43: 3"-CWS-0371-AG1A | D43: =LEFT(C43, FIND("""", C43)) -> 3" | E43: Cooling Water | F43: Water | G43: CS | I43: =HYPERLINK("\\CAD-PC\1Data\3.Documentation\Isometric DWG MHI\" & J43 & ".pdf", C43) -> 3"-CWS-0371-AG1A | J43: A065
B44: 37 | C44: 14"-CWS-9455-AG1A | D44: =LEFT(C44, FIND("""", C44)) -> 14" | E44: Cooling Water | F44: Water | G44: CS | I44: =HYPERLINK("\\CAD-PC\1Data\3.Documentation\Isometric DWG MHI\" & J44 & ".pdf", C44) -> 14"-CWS-9455-AG1A | J44: A066
B45: 38 | C45: 2"-CWS-0071-AG1A | D45: =LEFT(C45, FIND("""", C45)) -> 2" | E45: Cooling Water | F45: Water | G45: CS | I45: =HYPERLINK("\\CAD-PC\1Data\3.Documentation\Isometric DWG MHI\" & J45 & ".pdf", C45) -> 2"-CWS-0071-AG1A | J45: A067
B46: 39 | C46: 2"-CWS-0071-AG1A | D46: =LEFT(C46, FIND("""", C46)) -> 2" | E46: Cooling Water | F46: Water | G46: CS | I46: =HYPERLINK("\\CAD-PC\1Data\3.Documentation\Isometric DWG MHI\" & J46 & ".pdf", C46) -> 2"-CWS-0071-AG1A | J46: A068
B47: 40 | C47: 14"-CWS-9455-AG1A | D47: =LEFT(C47, FIND("""", C47)) -> 14" | E47: Cooling Water | F47: Water | G47: CS | I47: =HYPERLINK("\\CAD-PC\1Data\3.Documentation\Isometric DWG MHI\" & J47 & ".pdf", C47) -> 14"-CWS-9455-AG1A | J47: A069 | K47: 20048
B48: 41 | C48: 3"-CWS-0077-AG1A | D48: =LEFT(C48, FIND("""", C48)) -> 3" | E48: Cooling Water | F48: Water | G48: CS | I48: =HYPERLINK("\\CAD-PC\1Data\3.Documentation\Isometric DWG MHI\" & J48 & ".pdf", C48) -> 3"-CWS-0077-AG1A | J48: A070 | K48: 4271
B49: 42 | C49: 8"-CWS-9455-AG1A | D49: =LEFT(C49, FIND("""", C49)) -> 8" | E49: Cooling Water | F49: Water | G49: CS | I49: =HYPERLINK("\\CAD-PC\1Data\3.Documentation\Isometric DWG MHI\" & J49 & ".pdf", C49) -> 8"-CWS-9455-AG1A | J49: A071 | K49: 35760
B50: 43 | C50: 4"-CWS-0075-AG1A | D50: =LEFT(C50, FIND("""", C50)) -> 4" | E50: Cooling Water | F50: Water | G50: CS | I50: =HYPERLINK("\\CAD-PC\1Data\3.Documentation\Isometric DWG MHI\" & J50 & ".pdf", C50) -> 4"-CWS-0075-AG1A | J50: A073 | K50: 12772 | M50: =247+1073+2410 -> 3730
B51: 44 | C51: 3"-CWS-0173-AG1A | D51: =LEFT(C51, FIND("""", C51)) -> 3" | E51: Cooling Water | F51: Water | G51: CS | I51: =HYPERLINK("\\CAD-PC\1Data\3.Documentation\Isometric DWG MHI\" & J51 & ".pdf", C51) -> 3"-CWS-0173-AG1A | J51: A074 | K51: 1621 | M51: =150+354+312+339+466 -> 1621
B52: 45 | C52: 6"-CWS-0175-AG1A | D52: =LEFT(C52, FIND("""", C52)) -> 6" | E52: Cooling Water | F52: Water | G52: CS | I52: =HYPERLINK("\\CAD-PC\1Data\3.Documentation\Isometric DWG MHI\" & J52 & ".pdf", C52) -> 6"-CWS-0175-AG1A | J52: A075 | K52: 4904 | M52: =3767+700+437 -> 4904
B53: 46 | C53: 3"-CWS-0180-AG1A | D53: =LEFT(C53, FIND("""", C53)) -> 3" | E53: Cooling Water | F53: Water | G53: CS | I53: =HYPERLINK("\\CAD-PC\1Data\3.Documentation\Isometric DWG MHI\" & J53 & ".pdf", C53) -> 3"-CWS-0180-AG1A | J53: A076 | K53: 7373 | M53: =466+1110+3200+900+400+490+807 -> 7373
B54: 47 | C54: 2"-CWS-0182-AG1A | D54: =LEFT(C54, FIND("""", C54)) -> 2" | E54: Cooling Water | F54: Water | G54: CS | I54: =HYPERLINK("\\CAD-PC\1Data\3.Documentation\Isometric DWG MHI\" & J54 & ".pdf", C54) -> 2"-CWS-0182-AG1A | J54: A077 | K54: 7607 | M54: =386+450+400+3760+670+198+1743 -> 7607
B55: 48 | C55: 3"-CWS-0184-AG1A | D55: =LEFT(C55, FIND("""", C55)) -> 3" | E55: Cooling Water | F55: Water | G55: CS | I55: =HYPERLINK("\\CAD-PC\1Data\3.Documentation\Isometric DWG MHI\" & J55 & ".pdf", C55) -> 3"-CWS-0184-AG1A | J55: A078
B56: 49 | C56: 6"-FGS-0360-AG1C | D56: =LEFT(C56, FIND("""", C56)) -> 6" | E56: Fuel Gas | F56: Gas | G56: CS | I56: =HYPERLINK("\\CAD-PC\1Data\3.Documentation\Isometric DWG MHI\" & J56 & ".pdf", C56) -> 6"-FGS-0360-AG1C | J56: A131
B57: 50 | C57: 6"-FGS-0362-AG1C | D57: =LEFT(C57, FIND("""", C57)) -> 6" | E57: Fuel Gas | F57: Gas | G57: CS | I57: =HYPERLINK("\\CAD-PC\1Data\3.Documentation\Isometric DWG MHI\" & J57 & ".pdf", C57) -> 6"-FGS-0362-AG1C | J57: A132
B58: 51 | C58: 6"-FGS-0361-AG1C | D58: =LEFT(C58, FIND("""", C58)) -> 6" | E58: Fuel Gas | F58: Gas | G58: CS | I58: =HYPERLINK("\\CAD-PC\1Data\3.Documentation\Isometric DWG MHI\" & J58 & ".pdf", C58) -> 6"-FGS-0361-AG1C | J58: A133
B59: 52 | C59: 10"-FGS-0360-AG1C | D59: =LEFT(C59, FIND("""", C59)) -> 10" | E59: Fuel Gas | F59: Gas | G59: CS | I59: =HYPERLINK("\\CAD-PC\1Data\3.Documentation\Isometric DWG MHI\" & J59 & ".pdf", C59) -> 10"-FGS-0360-AG1C | J59: A134
B60: 53 | C60: 12"-FGS-0182-AG1C | D60: =LEFT(C60, FIND("""", C60)) -> 12" | E60: Fuel Gas | F60: Gas | G60: CS | I60: =HYPERLINK("\\CAD-PC\1Data\3.Documentation\Isometric DWG MHI\" & J60 & ".pdf", C60) -> 12"-FGS-0182-AG1C | J60: A135
B61: 54 | C61: 10"-FGS-0360-AG1C | D61: =LEFT(C61, FIND("""", C61)) -> 10" | E61: Fuel Gas | F61: Gas | G61: CS | I61: =HYPERLINK("\\CAD-PC\1Data\3.Documentation\Isometric DWG MHI\" & J61 & ".pdf", C61) -> 10"-FGS-0360-AG1C | J61: A136 | K61: 16264
B62: 55 | C62: 6"-FGS-0361-AG1C | D62: =LEFT(C62, FIND("""", C62)) -> 6" | E62: Fuel Gas | F62: Gas | G62: CS | I62: =HYPERLINK("\\CAD-PC\1Data\3.Documentation\Isometric DWG MHI\" & J62 & ".pdf", C62) -> 6"-FGS-0361-AG1C | J62: A137 | K62: 41420
B63: 56 | C63: 6"-FGS-0362-AG1C | D63: =LEFT(C63, FIND("""", C63)) -> 6" | E63: Fuel Gas | F63: Gas | G63: CS | I63: =HYPERLINK("\\CAD-PC\1Data\3.Documentation\Isometric DWG MHI\" & J63 & ".pdf", C63) -> 6"-FGS-0362-AG1C | J63: A138
B64: 57 | C64: 6"-FGS-0361-AG1C | D64: =LEFT(C64, FIND("""", C64)) -> 6" | E64: Fuel Gas | F64: Gas | G64: CS | I64: =HYPERLINK("\\CAD-PC\1Data\3.Documentation\Isometric DWG MHI\" & J64 & ".pdf", C64) -> 6"-FGS-0361-AG1C | J64: A139 | K64: 15104
B65: 58 | C65: 4"-FGS-0361-AG1A | D65: =LEFT(C65, FIND("""", C65)) -> 4" | E65: Fuel Gas | F65: Gas | G65: CS | I65: =HYPERLINK("\\CAD-PC\1Data\3.Documentation\Isometric DWG MHI\" & J65 & ".pdf", C65) -> 4"-FGS-0361-AG1A | J65: A140 | K65: 6213 | M65: =573+410+1200+580+1400+2050 -> 6213
B66: 59 | C66: 4"-FNG-9602-AG1C | D66: =LEFT(C66, FIND("""", C66)) -> 4" | E66: Natural Gas | F66: Gas | G66: CS | I66: =HYPERLINK("\\CAD-PC\1Data\3.Documentation\Isometric DWG MHI\" & J66 & ".pdf", C66) -> 4"-FNG-9602-AG1C | J66: A141
B67: 60 | C67: 1-1/2"-FNG-9602-AG1C | D67: =LEFT(C67, FIND("""", C67)) -> 1-1/2" | E67: Natural Gas | F67: Gas | G67: CS | I67: =HYPERLINK("\\CAD-PC\1Data\3.Documentation\Isometric DWG MHI\" & J67 & ".pdf", C67) -> 1-1/2"-FNG-9602-AG1C | J67: A142
B68: 61 | C68: 6"-FNG-0112-AG1C | D68: =LEFT(C68, FIND("""", C68)) -> 6" | E68: Natural Gas | F68: Gas | G68: CS | I68: =HYPERLINK("\\CAD-PC\1Data\3.Documentation\Isometric DWG MHI\" & J68 & ".pdf", C68) -> 6"-FNG-0112-AG1C | J68: A143
B69: 62 | C69: 6"-FNG-0112-AG1C | D69: =LEFT(C69, FIND("""", C69)) -> 6" | E69: Natural Gas | F69: Gas | G69: CS | I69: =HYPERLINK("\\CAD-PC\1Data\3.Documentation\Isometric DWG MHI\" & J69 & ".pdf", C69) -> 6"-FNG-0112-AG1C | J69: A144
B70: 63 | C70: 6"-FNG-0112-AG1C | D70: =LEFT(C70, FIND("""", C70)) -> 6" | E70: Natural Gas | F70: Gas | G70: CS | I70: =HYPERLINK("\\CAD-PC\1Data\3.Documentation\Isometric DWG MHI\" & J70 & ".pdf", C70) -> 6"-FNG-0112-AG1C | J70: A145
B71: 64 | C71: 4"-FNG-9602-AG1C | D71: =LEFT(C71, FIND("""", C71)) -> 4" | E71: Natural Gas | F71: Gas | G71: CS | I71: =HYPERLINK("\\CAD-PC\1Data\3.Documentation\Isometric DWG MHI\" & J71 & ".pdf", C71) -> 4"-FNG-9602-AG1C | J71: A146
B72: 65 | C72: 4"-FNG-9602-AG1C | D72: =LEFT(C72, FIND("""", C72)) -> 4" | E72: Natural Gas | F72: Gas | G72: CS | I72: =HYPERLINK("\\CAD-PC\1Data\3.Documentation\Isometric DWG MHI\" & J72 & ".pdf", C72) -> 4"-FNG-9602-AG1C | J72: A147 | K72: 17751
B73: 66 | C73: 6"-FWS-9301-AG1A | D73: =LEFT(C73, FIND("""", C73)) -> 6" | E73: Filtered Water | F73: Water | G73: CS | I73: =HYPERLINK("\\CAD-PC\1Data\3.Documentation\Isometric DWG MHI\" & J73 & ".pdf", C73) -> 6"-FWS-9301-AG1A | J73: A151
B74: 67 | C74: 6"-FWS-9301-AG1A | D74: =LEFT(C74, FIND("""", C74)) -> 6" | E74: Filtered Water | F74: Water | G74: CS | I74: =HYPERLINK("\\CAD-PC\1Data\3.Documentation\Isometric DWG MHI\" & J74 & ".pdf", C74) -> 6"-FWS-9301-AG1A | J74: A152 | K74: 44500
B75: 68 | C75: 2"-FWS-9305-AG1A | D75: =LEFT(C75, FIND("""", C75)) -> 2" | E75: Filtered Water | F75: Water | G75: CS | I75: =HYPERLINK("\\CAD-PC\1Data\3.Documentation\Isometric DWG MHI\" & J75 & ".pdf", C75) -> 2"-FWS-9305-AG1A | J75: A153
B76: 69 | C76: 6"-FWS-9301-AG1A | D76: =LEFT(C76, FIND("""", C76)) -> 6" | E76: Filtered Water | F76: Water | G76: CS | I76: =HYPERLINK("\\CAD-PC\1Data\3.Documentation\Isometric DWG MHI\" & J76 & ".pdf", C76) -> 6"-FWS-9301-AG1A | J76: A154
B77: 70 | C77: 2"-FWS-9305-AG1A | D77: =LEFT(C77, FIND("""", C77)) -> 2" | E77: Filtered Water | F77: Water | G77: CS | I77: =HYPERLINK("\\CAD-PC\1Data\3.Documentation\Isometric DWG MHI\" & J77 & ".pdf", C77) -> 2"-FWS-9305-AG1A | J77: A155
B78: 71 | C78: 4"-GHY-0358-BG3A | D78: =LEFT(C78, FIND("""", C78)) -> 4" | E78: Hydrogen | F78: Hydrogen | G78: CS | I78: =HYPERLINK("\\CAD-PC\1Data\3.Documentation\Isometric DWG MHI\" & J78 & ".pdf", C78) -> 4"-GHY-0358-BG3A | J78: A161
B79: 72 | C79: 6"-GHY-0301-AG1C | D79: =LEFT(C79, FIND("""", C79)) -> 6" | E79: Hydrogen | F79: Hydrogen | G79: CS | I79: =HYPERLINK("\\CAD-PC\1Data\3.Documentation\Isometric DWG MHI\" & J79 & ".pdf", C79) -> 6"-GHY-0301-AG1C | J79: A162 | K79: 44500
B80: 73 | C80: 3"-GHY-0303-DG3A | D80: =LEFT(C80, FIND("""", C80)) -> 3" | E80: Hydrogen | F80: Hydrogen | G80: CS | I80: =HYPERLINK("\\CAD-PC\1Data\3.Documentation\Isometric DWG MHI\" & J80 & ".pdf", C80) -> 3"-GHY-0303-DG3A | J80: A163
B81: 74 | C81: 2"-GHY-0306-DG3A | D81: =LEFT(C81, FIND("""", C81)) -> 2" | E81: Hydrogen | F81: Hydrogen | G81: CS | I81: =HYPERLINK("\\CAD-PC\1Data\3.Documentation\Isometric DWG MHI\" & J81 & ".pdf", C81) -> 2"-GHY-0306-DG3A | J81: A165 | K81: 12723
B82: 75 | C82: 3"-GHY-0307-AG1C | D82: =LEFT(C82, FIND("""", C82)) -> 3" | E82: Hydrogen | F82: Hydrogen | G82: CS | I82: =HYPERLINK("\\CAD-PC\1Data\3.Documentation\Isometric DWG MHI\" & J82 & ".pdf", C82) -> 3"-GHY-0307-AG1C | J82: A166 | K82: 12026
B83: 76 | C83: 6"-GHY-0301-AG1C (1/2) (2/2) | D83: =LEFT(C83, FIND("""", C83)) -> 6" | E83: Hydrogen | F83: Hydrogen | G83: CS | I83: =HYPERLINK("\\CAD-PC\1Data\3.Documentation\Isometric DWG MHI\" & J83 & ".pdf", C83) -> 6"-GHY-0301-AG1C (1/2) (2/2) | J83: A167 | K83: 18913
B84: 77 | C84: 3"-GHY-0302-DG3A-H25 | D84: =LEFT(C84, FIND("""", C84)) -> 3" | E84: Hydrogen | F84: Hydrogen | G84: CS | H84: H25 | I84: =HYPERLINK("\\CAD-PC\1Data\3.Documentation\Isometric DWG MHI\" & J84 & ".pdf", C84) -> 3"-GHY-0302-DG3A-H25 | J84: A168 | K84: 11795
B85: 78 | C85: 3"-GHY-0303-DG3A (1/2) (2/2) | D85: =LEFT(C85, FIND("""", C85)) -> 3" | E85: Hydrogen | F85: Hydrogen | G85: CS | I85: =HYPERLINK("\\CAD-PC\1Data\3.Documentation\Isometric DWG MHI\" & J85 & ".pdf", C85) -> 3"-GHY-0303-DG3A (1/2) (2/2) | J85: A169 | K85: 11185
B86: 79 | C86: 3"-GHY-0304-DG3A | D86: =LEFT(C86, FIND("""", C86)) -> 3" | E86: Hydrogen | F86: Hydrogen | G86: CS | I86: =HYPERLINK("\\CAD-PC\1Data\3.Documentation\Isometric DWG MHI\" & J86 & ".pdf", C86) -> 3"-GHY-0304-DG3A | J86: A170 | K86: 9938
B87: 80 | C87: 2"-GHY-0305-AG1C | D87: =LEFT(C87, FIND("""", C87)) -> 2" | E87: Hydrogen | F87: Hydrogen | G87: CS | I87: =HYPERLINK("\\CAD-PC\1Data\3.Documentation\Isometric DWG MHI\" & J87 & ".pdf", C87) -> 2"-GHY-0305-AG1C | J87: A171 | K87: 5182 | M87: =600+1400+1468+383+170+458+703 -> 5182
B88: 81 | C88: 3"-GHY-0307-AG1C | D88: =LEFT(C88, FIND("""", C88)) -> 3" | E88: Hydrogen | F88: Hydrogen | G88: CS | I88: =HYPERLINK("\\CAD-PC\1Data\3.Documentation\Isometric DWG MHI\" & J88 & ".pdf", C88) -> 3"-GHY-0307-AG1C | J88: A172 | K88: 6544 | M88: =3500+2044+1000 -> 6544
B89: 82 | C89: 6"-GOX-0301-BG3A | D89: =LEFT(C89, FIND("""", C89)) -> 6" | E89: Oxo Gas (H2 + CO2) | F89: Gas | G89: CS | I89: =HYPERLINK("\\CAD-PC\1Data\3.Documentation\Isometric DWG MHI\" & J89 & ".pdf", C89) -> 6"-GOX-0301-BG3A | J89: A181
B90: 83 | C90: 6"-GOX-0301-BG3A | D90: =LEFT(C90, FIND("""", C90)) -> 6" | E90: Oxo Gas (H2 + CO2) | F90: Gas | G90: CS | I90: =HYPERLINK("\\CAD-PC\1Data\3.Documentation\Isometric DWG MHI\" & J90 & ".pdf", C90) -> 6"-GOX-0301-BG3A | J90: A182
B91: 84 | C91: 6"-GOX-0301-BG3A | D91: =LEFT(C91, FIND("""", C91)) -> 6" | E91: Oxo Gas (H2 + CO2) | F91: Gas | G91: CS | I91: =HYPERLINK("\\CAD-PC\1Data\3.Documentation\Isometric DWG MHI\" & J91 & ".pdf", C91) -> 6"-GOX-0301-BG3A | J91: A183
B92: 85 | C92: 2"-GPA-9954-AG1A | D92: =LEFT(C92, FIND("""", C92)) -> 2" | E92: Plant Air | F92: Air | G92: CS | I92: =HYPERLINK("\\CAD-PC\1Data\3.Documentation\Isometric DWG MHI\" & J92 & ".pdf", C92) -> 2"-GPA-9954-AG1A | J92: A191
B93: 86 | C93: 2"-GPA-9954-AG1A | D93: =LEFT(C93, FIND("""", C93)) -> 2" | E93: Plant Air | F93: Air | G93: CS | I93: =HYPERLINK("\\CAD-PC\1Data\3.Documentation\Isometric DWG MHI\" & J93 & ".pdf", C93) -> 2"-GPA-9954-AG1A | J93: A192
B94: 87 | C94: 2"-GPI-0342-AG2A | D94: =LEFT(C94, FIND("""", C94)) -> 2" | E94: Instrument Air | F94: Air | G94: CS | I94: =HYPERLINK("\\CAD-PC\1Data\3.Documentation\Isometric DWG MHI\" & J94 & ".pdf", C94) -> 2"-GPI-0342-AG2A | J94: A211
B95: 88 | C95: 2"-GPI-0341-AG2A | D95: =LEFT(C95, FIND("""", C95)) -> 2" | E95: Instrument Air | F95: Air | G95: CS | I95: =HYPERLINK("\\CAD-PC\1Data\3.Documentation\Isometric DWG MHI\" & J95 & ".pdf", C95) -> 2"-GPI-0341-AG2A | J95: A212
B96: 89 | C96: 2"-GPI-9908-AG2A | D96: =LEFT(C96, FIND("""", C96)) -> 2" | E96: Instrument Air | F96: Air | G96: CS | I96: =HYPERLINK("\\CAD-PC\1Data\3.Documentation\Isometric DWG MHI\" & J96 & ".pdf", C96) -> 2"-GPI-9908-AG2A | J96: A213
B97: 90 | C97: 2"-GPI-9908-AG2A | D97: =LEFT(C97, FIND("""", C97)) -> 2" | E97: Instrument Air | F97: Air | G97: CS | I97: =HYPERLINK("\\CAD-PC\1Data\3.Documentation\Isometric DWG MHI\" & J97 & ".pdf", C97) -> 2"-GPI-9908-AG2A | J97: A214
B98: 91 | C98: 4"-LPC-0254-AG1B-H25 | D98: =LEFT(C98, FIND("""", C98)) -> 4" | E98: Condensate | F98: Water | G98: CS | H98: H25 | I98: =HYPERLINK("\\CAD-PC\1Data\3.Documentation\Isometric DWG MHI\" & J98 & ".pdf", C98) -> 4"-LPC-0254-AG1B-H25 | J98: A221
B99: 92 | C99: 3"-LPC-0254-AG1C | D99: =LEFT(C99, FIND("""", C99)) -> 3" | E99: Condensate | F99: Water | G99: CS | I99: =HYPERLINK("\\CAD-PC\1Data\3.Documentation\Isometric DWG MHI\" & J99 & ".pdf", C99) -> 3"-LPC-0254-AG1C | J99: A222
B100: 93 | C100: 4"-LPC-0254-AG1B-H25 | D100: =LEFT(C100, FIND("""", C100)) -> 4" | E100: Condensate | F100: Water | G100: CS | H100: H25 | I100: =HYPERLINK("\\CAD-PC\1Data\3.Documentation\Isometric DWG MHI\" & J100 & ".pdf", C100) -> 4"-LPC-0254-AG1B-H25 | J100: A223
B101: 94 | C101: 4"-LPC-0254-AG1B-H25 | D101: =LEFT(C101, FIND("""", C101)) -> 4" | E101: Condensate | F101: Water | G101: CS | H101: H25 | I101: =HYPERLINK("\\CAD-PC\1Data\3.Documentation\Isometric DWG MHI\" & J101 & ".pdf", C101) -> 4"-LPC-0254-AG1B-H25 | J101: A224
...

Sheet 46
D1: EQUIPMENT LIST | V1: Document No. | Y1: : MNTC-ME
V2: Revision | Y2: : 0
V3: Date of issue | Y3: : 2023
A4: PT. PETRO OXO NUSANTARA | V4: Page | Y4: :
A5: HEAT EXCHANGER (AIR FIN COOLER)
A7: No | B7: Area | C7: Tag no | D7: Service | E7: Fluid | F7: Type | G7: Surface | H7: Design Press. | I7: Hydro Test P. | J7: Design Temp. | K7: Pneu. Test P. | L7: Corrosion | M7: Radio. test | N7: Size Bundle | P7: Material | U7: Code | V7: Manufacture | W7: Category | Y7: Complex Grade | Z7: Spare | AA7: Price | AB7: Installation | AC7: Remark | AH7: 46752
G8: Area | H8: kgf/cm2G | I8: kgf/cm2G | J8: oC | K8: kgf/cm2G | L8: Allowance | M8: % | N8: Width ( mm ) | O8: Length ( mm ) | P8: Header | Q8: Fin | R8: Tube | S8: Flange | T8: Support, | U8: ASME | W8: Score | X8: Grade | Z8: Parts | AA8: USD | AB8: Date | AJ8: EaMS
G9: m2 | H9: Tube | I9: Tube | J9: Tube | T9: leg, lug | AF9: History | AG9: Date | AH9: Rekomendasi S/D 2027 | AJ9: Update
A10: 1 | B10: Syn Gas | C10: E-018A | D10: Air Cooler | E10: Reformed gas | F10: FORCED | H10: 11 | I10: 10.9 | J10: 170 | L10: 0 | R10: A249 TP304 | V10: Nouvo Pignone | W10: 5 | X10: C | Y10: * | Z10: Klik | AA10: 140000 | AD10: S5 | AF10: Replace V-belt SPB 3000 LW ( 3 pcs ) | AG10: 44553 | AJ10: OK
A11: =A10+1 -> 2 | B11: Syn Gas | C11: E-018B | D11: Air Cooler | E11: Reformed gas | F11: FORCED | H11: 11 | I11: 10.9 | J11: 170 | L11: 0 | V11: Nouvo Pignone | W11: 5 | X11: C | Y11: * | Z11: Klik | AA11: 140000 | AD11: S5 | AF11: Replace V-belt SPB 3000 LW ( 3 pcs ) | AG11: 44179 | AJ11: OK
A12: =A11+1 -> 3 | B12: Syn Gas | C12: E-018C | D12: Air Cooler | E12: Reformed gas | F12: FORCED | H12: 11 | I12: 10.9 | J12: 170 | V12: Nouvo Pignone | W12: 5 | X12: C | Y12: * | Z12: Klik | AA12: 140000 | AD12: S5 | AF12: Replace V-belt SPA 2240 ( 2 pcs ) | AG12: 44717 | AJ12: OK
A13: =A12+1 -> 4 | B13: Syn Gas | C13: E-018D | D13: Air Cooler | E13: Reformed gas | F13: FORCED | H13: 11 | I13: 10.9 | J13: 170 | V13: Nouvo Pignone | W13: 5 | X13: C | Y13: * | Z13: Klik | AA13: 140000 | AD13: S5 | AF13: Replace V-belt SPA 2240 ( 2 pcs ) | AG13: 44717 | AJ13: OK
A14: =A13+1 -> 5 | B14: Octanol | C14: E-115A | D14: Recycle Oxo Gas C. | E14: OXO GAS | F14: INDUCED | H14: 23 | I14: 34.5 | J14: 130 | V14: Nouvo Pignone | W14: 5 | X14: C | Y14: * | Z14: Klik | AA14: 140000 | AD14: OP-002 | AF14: Replace bearing top & bottom ,22313 EK, replace bearing adapter H-2313, replace pulley motor | AG14: 43781 | AJ14: OK
A15: =A14+1 -> 6 | B15: Octanol | C15: E-115B | D15: Recycle Oxo Gas C. | E15: OXO GAS | F15: INDUCED | H15: 23 | I15: 34.5 | J15: 130 | V15: Nouvo Pignone | W15: 5 | X15: C | Y15: * | Z15: Klik | AA15: 140000 | AD15: OP-002 | AF15: Replace bearing top & bottom ,22313 EK, replace bearing adapter H-2313 | AG15: 43746 | AJ15: OK
A16: =A15+1 -> 7 | B16: Octanol | C16: E-118A | D16: R - 110 Hot Water C. | E16: WATER | F16: INDUCED | H16: 12 | I16: 18 | J16: 130 | V16: Nouvo Pignone | W16: 5 | X16: C | Y16: * | Z16: Klik | AA16: 77000 | AD16: OP-002 | AF16: Replace bearing top & bottom ,22313 EK , replace bearing adapter H-2313, Replace HTD belt 3500 | AG16: 43822 | AJ16: OK
A17: =A16+1 -> 8 | B17: Octanol | C17: E-118B | D17: R - 110 Hot Water C. | E17: WATER | F17: INDUCED | H17: 12 | I17: 18 | J17: 130 | V17: Nouvo Pignone | W17: 5 | X17: C | Y17: * | Z17: Klik | AA17: 77000 | AD17: OP-002 | AF17: Replace HTD belt 3500 | AG17: 44729 | AJ17: OK
A18: =A17+1 -> 9 | B18: Octanol | C18: E-118C | D18: R - 110 Hot Water C. | E18: WATER | F18: INDUCED | H18: 12 | I18: 18 | J18: 130 | V18: Nouvo Pignone | W18: 5 | X18: C | Y18: * | Z18: Klik | AA18: 77000 | AD18: OP-002 | AF18: Replace HTD belt 3500 | AG18: 44087 | AJ18: OK
A19: =A18+1 -> 10 | B19: Octanol | C19: E-118D | D19: R - 110 Hot Water C. | E19: WATER | F19: INDUCED | H19: 12 | I19: 18 | J19: 130 | V19: Nouvo Pignone | W19: 5 | X19: C | Y19: * | Z19: Klik | AA19: 77000 | AD19: OP-002 | AF19: Replace HTD belt 3500 ,replace pulley motor | AG19: 43560 | AJ19: OK
A20: =A19+1 -> 11 | B20: Octanol | C20: E-143 | D20: TK - 141 Vent Condenser | E20: CAT | F20: INDUCED | H20: 27.5 | I20: 41.3 | J20: 140 | V20: Nouvo Pignone | W20: 5 | X20: C | Y20: * | Z20: Klik | AA20: 63000 | AD20: OP-005 | AF20: Replace V-belt SPB 5000 | AG20: 44414 | AJ20: OK
A21: =A20+1 -> 12 | B21: Octanol | C21: E-145A | D21: E - 140 Condenser | E21: ALD | F21: INDUCED | G21: 157.5 | H21: 15 | I21: 22.5 | J21: 150 | V21: Nouvo Pignone | W21: 5 | X21: C | Y21: * | Z21: Klik | AA21: 210000 | AD21: OP-005 | AF21: Replace V-belt SPB 3550 LW ( 5pcs ) | AG21: 44454 | AJ21: OK
A22: =A21+1 -> 13 | B22: Octanol | C22: E-145B | D22: E - 140 Condenser | E22: ALD | F22: INDUCED | G22: 157.5 | H22: 15 | I22: 22.5 | J22: 150 | V22: Nouvo Pignone | W22: 5 | X22: C | Y22: * | Z22: Klik | AA22: 210000 | AD22: OP-005 | AF22: Replace bearing top & bottom ,22313 EK ( 2pcs ), Replace HTD belt 3500 ( 5pcs ) | AG22: 44657 | AJ22: OK
A23: =A22+1 -> 14 | B23: Octanol | C23: E-145C | D23: E - 140 Condenser | E23: ALD | F23: INDUCED | G23: 157.5 | H23: 15 | I23: 22.5 | J23: 150 | V23: Nouvo Pignone | W23: 5 | X23: C | Y23: * | Z23: Klik | AA23: 210000 | AD23: OP-005 | AF23: Replace bearing top & bottom ,22313 EK ( 2pcs ), replace bearing adapter H-2313 ( 1Pcs ) | AG23: 44603 | AJ23: OK
A24: =A23+1 -> 15 | B24: Octanol | C24: E-145D | D24: E - 140 Condenser | E24: ALD | F24: INDUCED | G24: 157.5 | H24: 15 | I24: 22.5 | J24: 150 | V24: Nouvo Pignone | W24: 5 | X24: C | Y24: * | Z24: Klik | AA24: 210000 | AD24: OP-005 | AF24: Replace bearing top & bottom ,22313 EK ( 2pcs ), Replace HTD belt 3500 ( 5pcs ) | AG24: 44691 | AJ24: OK
A25: =A24+1 -> 16 | B25: Octanol | C25: E-145E | D25: E - 140 Condenser | E25: ALD | F25: INDUCED | G25: 157.5 | H25: 15 | I25: 22.5 | J25: 150 | V25: Nouvo Pignone | W25: 5 | X25: C | Y25: * | Z25: Klik | AA25: 210000 | AD25: OP-005 | AF25: Replace V-belt SPB 3550 LW ( 5pcs ) | AG25: 44249 | AJ25: OK
A26: =A25+1 -> 17 | B26: Octanol | C26: E-145F | D26: E - 140 Condenser | E26: ALD | F26: INDUCED | G26: 157.5 | H26: 15 | I26: 22.5 | J26: 150 | V26: Nouvo Pignone | W26: 5 | X26: C | Y26: * | Z26: Klik | AA26: 210000 | AD26: OP-005 | AF26: Replace V-belt SPB 3550 LW ( 5pcs ) | AG26: 44412 | AJ26: OK
A27: =A26+1 -> 18 | B27: Octanol | C27: E-165A | D27: T - 160 Condenser | E27: IBD | F27: INDUCED | H27: 2 | I27: 3 | J27: 110 | V27: Nouvo Pignone | W27: 5 | X27: C | Y27: * | Z27: Klik | AA27: 210000 | AD27: OP-007 | AF27: Replace V-belt SPB 3550 LW ( 5pcs ) | AG27: 44682 | AJ27: OK
A28: =A27+1 -> 19 | B28: Octanol | C28: E-165B | D28: T - 160 Condenser | E28: IBD | F28: INDUCED | H28: 2 | I28: 3 | J28: 110 | V28: Nouvo Pignone | W28: 5 | X28: C | Y28: * | Z28: Klik | AA28: 210000 | AD28: OP-007 | AF28: Replace V-belt SPB 3550 LW ( 5pcs ) | AG28: 44471 | AJ28: OK
A29: =A28+1 -> 20 | B29: Octanol | C29: E-165C | D29: T - 160 Condenser | E29: IBD | F29: INDUCED | H29: 2 | I29: 3 | J29: 110 | V29: Nouvo Pignone | W29: 5 | X29: C | Y29: * | Z29: Klik | AA29: 210000 | AD29: OP-007 | AF29: Replace V-belt SPB 3550 LW ( 5pcs ), check deflexi | AG29: 43456 | AJ29: OK
A30: =A29+1 -> 21 | B30: Octanol | C30: E-165D | D30: T - 160 Condenser | E30: IBD | F30: INDUCED | H30: 2 | I30: 3 | J30: 110 | V30: Nouvo Pignone | W30: 5 | X30: C | Y30: * | Z30: Klik | AA30: 210000 | AD30: OP-007 | AF30: Replace V-belt SPB 3550 LW ( 5pcs ) | AG30: 44002 | AJ30: OK
A31: =A30+1 -> 22 | B31: Octanol | C31: E-165E | D31: T - 160 Condenser | E31: IBD | F31: INDUCED | H31: 2 | I31: 3 | J31: 110 | V31: Nouvo Pignone | W31: 5 | X31: C | Y31: * | Z31: Klik | AA31: 210000 | AD31: OP-007 | AF31: Replace V-belt SPB 3550 LW ( 5pcs ) | AG31: 44692 | AJ31: OK
A32: =A31+1 -> 23 | B32: Octanol | C32: E-165F | D32: T - 160 Condenser | E32: IBD | F32: INDUCED | H32: 2 | I32: 3 | J32: 110 | V32: Nouvo Pignone | W32: 5 | X32: C | Y32: * | Z32: Klik | AA32: 210000 | AD32: OP-007 | AF32: Replace V-belt SPB 3550 LW ( 5pcs ) | AG32: 44003 | AJ32: OK
A33: =A32+1 -> 24 | B33: Octanol | C33: E-165G | D33: T - 160 Condenser | E33: IBD | F33: INDUCED | H33: 2 | I33: 3 | J33: 110 | V33: Nouvo Pignone | W33: 5 | X33: C | Y33: * | Z33: Klik | AA33: 210000 | AD33: OP-007 | AF33: Check deflexi sebelum nya 10 deg, setelah inspect 17 deg | AG33: 43456 | AJ33: OK
A34: =A33+1 -> 25 | B34: Octanol | C34: E-165H | D34: T - 160 Condenser | E34: IBD | F34: INDUCED | H34: 2 | I34: 3 | J34: 110 | V34: Nouvo Pignone | W34: 5 | X34: C | Y34: * | Z34: Klik | AA34: 210000 | AD34: OP-007 | AF34: Replace V-belt SPB 3550 LW ( 5pcs ) | AG34: 43917 | AJ34: OK
A35: =A34+1 -> 26 | B35: Octanol | C35: E-165I | D35: T - 160 Condenser | E35: IBD | F35: INDUCED | H35: 2 | I35: 3 | J35: 110 | V35: Nouvo Pignone | W35: 5 | X35: C | Y35: * | Z35: Klik | AA35: 210000 | AD35: OP-007 | AF35: Replace bearing housing top & bottom FY65 TF ( 2pcs ), Replace V-belt SPB 3550 LW ( 5pcs ) | AG35: 43878 | AJ35: OK
A36: =A35+1 -> 27 | B36: Octanol | C36: E-165J | D36: T - 160 Condenser | E36: IBD | F36: INDUCED | H36: 2 | I36: 3 | J36: 110 | V36: Nouvo Pignone | W36: 5 | X36: C | Y36: * | Z36: Klik | AA36: 210000 | AD36: OP-007 | AF36: Replace bearing housing top & bottom FY65 TF ( 2pcs ), Replace V-belt SPB 3550 LW ( 5pcs ) | AG36: 43875 | AJ36: OK
A37: =A36+1 -> 28 | B37: Octanol | C37: E-175 | D37: T - 170 Air Fin Cooler | E37: IBD | F37: INDUCED | H37: 2 | I37: 3 | J37: 110 | V37: Berkah Mekatek Jaya | W37: 5 | X37: C | Y37: * | Z37: Klik | AA37: 78000 | AB37: 44727 | AC37: New motor & pulley belt, bundle use existing | AF37: New equipment T-170 | AG37: 44727
A38: =A37+1 -> 29 | B38: Octanol | C38: E-414A | D38: R - 410 Solvent Cooler | E38: 2EH | F38: INDUCED | G38: 2331.82 | H38: 3.8 | I38: 5.7 | J38: 150 | V38: Nouvo Pignone | W38: 125 | X38: C,S,E | Y38: *** | Z38: Klik | AA38: 72800 | AD38: OP15 | AF38: Replace V-belt SPB 3750 LW ( 3 pcs ) | AG38: 44414 | AJ38: OK
A39: =A38+1 -> 30 | B39: Octanol | C39: E-414B | D39: R - 410 Solvent Cooler | E39: 2EH | F39: INDUCED | G39: 2331.82 | H39: 3.8 | I39: 5.7 | J39: 150 | V39: Nouvo Pignone | W39: 125 | X39: C,S,E | Y39: *** | Z39: Klik | AA39: 72800 | AD39: OP15 | AF39: Replace V-belt SPB 3750 LW ( 3 pcs ) | AG39: 43582 | AJ39: OK
A40: =A39+1 -> 31 | B40: Octanol | C40: E-418A | D40: Recycle H2 Cooler | E40: H2 | F40: INDUCED | G40: 3238.51 | H40: 45 | I40: 67.5 | J40: 250 | K40: N/A | L40: 0 | M40: UT & PT | N40: 3430 | O40: 9294 | P40: A240 TP304 | Q40: Al SB214 6060 | R40: A249 TP304 | S40: A182 F316 | T40: A36 | U40: ASME VIII DIV 1 | V40: Berkah Mekatek Jaya | W40: 125 | X40: C,S,E | Y40: *** | Z40: Klik | AA40: 121000 | AB40: 44966 | AC40: Replace tube bundle only | AD40: OP19 | AE40: OP-013 | AF40: New Tube Bundle E-418 A | AG40: 44966 | AH40: Replace bundle E-418AB E-425AB, E-625AB | AJ40: OK
A41: =A40+1 -> 32 | B41: Octanol | C41: E-418B | D41: Recycle H2 Cooler | E41: H2 | F41: INDUCED | G41: 3238.51 | H41: 45 | I41: 67.5 | J41: 250 | K41: N/A | L41: 0 | M41: UT & PT | N41: 3430 | O41: 9294 | P41: A240 TP304 | Q41: Al SB214 6060 | R41: A249 TP304 | S41: A182 F316 | T41: A36 | U41: ASME VIII DIV 1 | V41: Berkah Mekatek Jaya | W41: 125 | X41: C,S,E | Y41: *** | Z41: Klik | AA41: 121000 | AB41: 44966 | AC41: Replace tube bundle only | AD41: OP19 | AE41: OP-013 | AF41: New Tube Bundle E-418 A | AG41: 44966 | AH41: Replace bundle E-418AB E-425AB, E-625AB | AJ41: OK
A42: 33 | B42: Octanol | C42: E-425A | D42: T - 420 Sub Condenser | E42: 2EH | F42: INDUCED | G42: 2014.6 | H42: 2 | I42: 3.3 | J42: 115 | K42: N/A | L42: 0 | M42: UT & PT | N42: 2246 | O42: 9344 | P42: A240 TP304 | Q42: Al SB214 6060 | R42: A249 TP304 | S42: A182 F316 | T42: A36 | U42: ASME VIII DIV 1 | V42: Berkah Mekatek Jaya | W42: 125 | X42: C,S,E | Y42: *** | Z42: Klik | AA42: 91000 | AB42: 44966 | AC42: Replace tube bundle only | AD42: OP-015 | AF42: New Tube Bundle E-425 A | AG42: 44966 | AH42: Replace bundle E-418AB E-425AB, E-625AB | AJ42: OK
A43: 34 | B43: Octanol | C43: E-425B | D43: T - 420 Sub Condenser | E43: 2EH | F43: INDUCED | G43: 2014.6 | H43: 2 | I43: 3.3 | J43: 115 | K43: N/A | L43: 0 | M43: UT & PT | N43: 2246 | O43: 9344 | P43: A240 TP304 | Q43: Al SB214 6060 | R43: A249 TP304 | S43: A182 F316 | T43: A36 | U43: ASME VIII DIV 1 | V43: Berkah Mekatek Jaya | W43: 125 | X43: C,S,E | Y43: *** | Z43: Klik | AA43: 91000 | AB43: 44966 | AC43: Replace tube bundle only | AD43: OP-015 | AF43: New Tube Bundle E-425 B | AG43: 44966 | AH43: Replace bundle E-418AB E-425AB, E-625AB | AJ43: OK
A44: =A43+1 -> 35 | B44: Octanol | C44: E-437A | D44: T - 430 Distillate Cooler | E44: 2EH | F44: INDUCED | H44: 7.2 | I44: 10.8 | J44: 110 | V44: Nouvo Pignone | W44: 125 | X44: C,S,E | Y44: *** | Z44: Klik | AA44: 33600 | AD44: OP-016 | AF44: Replace bearing top & bottom ,22313 EK , replace bearing adapter H-2313, Replace Rubber coupling ( 12.5x33x29 ) | AG44: 43858 | AJ44: OK
A45: =A44+1 -> 36 | B45: Octanol | C45: E-437B | D45: T - 430 Distillate Cooler | E45: 2EH | F45: INDUCED | H45: 7.2 | I45: 10.8 | J45: 110 | V45: Nouvo Pignone | W45: 125 | X45: C,S,E | Y45: *** | Z45: Klik | AA45: 33600 | AD45: OP-016 | AF45: Replace bearing top & bottom ,22313 EK , replace bearing adapter H-2313, Replace sanp ring ID. 12.5 | AG45: 43858 | AJ45: OK
A46: =A45+1 -> 37 | B46: Octanol | C46: E-437C | D46: T - 430 Distillate Cooler | E46: 2EH | F46: INDUCED | H46: 7.2 | I46: 10.8 | J46: 110 | V46: Nouvo Pignone | W46: 125 | X46: C,S,E | Y46: *** | Z46: Klik | AA46: 33600 | AD46: OP-016 | AF46: Replace bolt and rubber coupling | AG46: 44783 | AJ46: OK
A47: =A46+1 -> 38 | B47: Octanol | C47: E-525A | D47: T - 520 Condenser | E47: NBA | F47: INDUCED | H47: 2 | I47: 3 | J47: 150 | V47: Nouvo Pignone | W47: 5 | X47: C | Y47: * | Z47: Klik | AA47: 47600 | AD47: OP-020 | AF47: Replace bearing top & bottom Roller Bearing 22313 EK (2 pcs), Fan Shaft Bearing /Adaptor sleeve H-2313 ( 560 3373803) (2 pcs), replace Rubber Coupling (flexible Shaft Coupling) | AG47: 43871 | AJ47: OK
A48: =A47+1 -> 39 | B48: Octanol | C48: E-525B | D48: T - 520 Condenser | E48: NBA | F48: INDUCED | H48: 2 | I48: 3 | J48: 150 | V48: Nouvo Pignone | W48: 5 | X48: C | Y48: * | Z48: Klik | AA48: 47600 | AD48: OP-020 | AF48: Replace bearing top & bottom Roller Bearing 22313 EK (2 pcs), Fan Shaft Bearing /Adaptor sleeve H-2313 ( 560 3373803) (2 pcs), Snap ring S-62 (ID 58 x 2.15mm) | AG48: 43892 | AJ48: OK
A49: =A48+1 -> 40 | B49: Octanol | C49: E-525C | D49: T - 520 Condenser | E49: NBA | F49: INDUCED | H49: 2 | I49: 3 | J49: 150 | V49: Nouvo Pignone | W49: 5 | X49: C | Y49: * | Z49: Klik | AA49: 47600 | AD49: OP-020 | AF49: Inspect blade inclination, bearing top & bottom, tightening bolt | AG49: 43490 | AJ49: OK
A50: =A49+1 -> 41 | B50: Octanol | C50: E-535A | D50: T - 530 Condenser | E50: NBA | F50: INDUCED | H50: 2 | I50: 3 | J50: 130 | V50: Nouvo Pignone | W50: 5 | X50: C | Y50: * | Z50: Klik | AA50: 39200 | AD50: OP21 | AF50: Replace bearing top & bottom Roller Bearing 22313 EK (2 pcs), Adaptor sleeve H-2313 ( 560 3373803) (2 pcs), inspect shaft & blade | AG50: 43899 | AJ50: OK
A51: =A50+1 -> 42 | B51: Octanol | C51: E-535B | D51: T - 530 Condenser | E51: NBA | F51: INDUCED | H51: 2 | I51: 3 | J51: 130 | V51: Nouvo Pignone | W51: 5 | X51: C | Y51: * | Z51: Klik | AA51: 39200 | AD51: OP21 | AF51: Inspect blade inclination 21 deg, bearing top & bottom, tightening bolt | AG51: 43490 | AJ51: OK
A52: =A51+1 -> 43 | B52: Octanol | C52: E-535C | D52: T - 530 Condenser | E52: NBA | F52: INDUCED | H52: 2 | I52: 3 | J52: 130 | V52: Nouvo Pignone | W52: 5 | X52: C | Y52: * | Z52: Klik | AA52: 39200 | AD52: OP21 | AF52: Replace bearing top & bottom Roller Bearing 22313 EK (2 pcs), Adaptor sleeve H-2313 ( 560 3373803) (2 pcs), inspect shaft & blade | AG52: 43906 | AJ52: OK
A53: 44 | B53: Octanol | C53: E-625A | D53: T - 620 Condenser | E53: IBA | F53: INDUCED | G53: 4796.87 | H53: 2 | I53: 3.3 | J53: 110 | K53: N/A | L53: 0 | M53: UT & PT | N53: 3380 | O53: 9294 | P53: A240 TP304 | Q53: Al SB214 6060 | R53: A249 TP304 | S53: A182 F316 | T53: A36 | U53: ASME VIII DIV 1 | V53: Berkah Mekatek Jaya | W53: 125 | X53: C,S,E | Y53: *** | Z53: Klik | AA53: 135000 | AB53: 44966 | AC53: Replace tube bundle only | AD53: OP-025 | AF53: New Tube Bundle E-625 A | AG53: 44966 | AH53: Replace bundle E-418AB E-425AB, E-625AB, Revitalitation pitch control E-625 | AJ53: OK
A54: 45 | B54: Octanol | C54: E-625B | D54: T - 620 Condenser | E54: IBA | F54: INDUCED | G54: 4796.87 | H54: 2 | I54: 3.3 | J54: 110 | K54: N/A | L54: 0 | M54: UT & PT | N54: 3380 | O54: 9294 | P54: A240 TP304 | Q54: Al SB214 6060 | R54: A249 TP304 | S54: A182 F316 | T54: A36 | U54: ASME VIII DIV 1 | V54: Berkah Mekatek Jaya | W54: 125 | X54: C,S,E | Y54: *** | Z54: Klik | AA54: 135000 | AB54: 44966 | AC54: Replace tube bundle only | AD54: OP-025 | AF54: New Tube Bundle E-625 B | AG54: 44966 | AH54: Replace bundle E-418AB E-425AB, E-625AB, Revitalitation pitch control E-625 | AJ54: OK
A55: =A54+1 -> 46 | B55: Utility | C55: E-922A | D55: D - 922 Vent Condenser | E55: STEAM CONDENSATE | F55: INDUCED | H55: 2.38 FV | I55: 3.4 | J55: 130 | V55: Nouvo Pignone | W55: 5 | X55: C | Y55: * | Z55: Klik | AA55: 97000 | AB55: 39442 | AD55: U15 | AF55: Replce v-belt 2800 ( 2pcs ) | AG55: 44753 | AJ55: OK
A56: =A55+1 -> 47 | B56: Utility | C56: E-922B | D56: D - 922 Vent Condenser | E56: STEAM CONDENSATE | F56: INDUCED | H56: 2.38 FV | I56: 3.4 | J56: 130 | V56: Nouvo Pignone | W56: 5 | X56: C | Y56: * | Z56: Klik | AA56: 97000 | AB56: 39442 | AD56: U15 | AF56: Replace pulley motor ,Replace V belt 2800 ( 5pcs ) | AG56: 44663 | AJ56: OK
A61: Total | AA61: =SUM(AA10:AA60) -> 6043800
A62: Note :
A70: Total Equipment | D70: =COUNTA(C10:C69) -> 47 | AD70: =COUNTA(AD10:AD69) -> 46 | AF70: =COUNTA(AF10:AF69) -> 47

Sheet 45
D1: EQUIPMENT LIST | N1: Document No. | P1: : MNTC-ME
N2: Revision | P2: : 0
N3: Date of issue | P3: : 2023
A4: PT. PETRO OXO NUSANTARA | N4: Page | P4: : 1 of 1
A5: STATIC MIXER
A7: No | B7: TAG No. | C7: Description | D7: Fluid | E7: Type | F7: Design condition | L7: Category | N7: Complex Grade | O7: Spare | P7: Price | Q7: Installation | R7: Remark | W7: 46752
F8: Flow rate (M3/h ) | G8: Design. Pres ( Kg./Cm3G ) | H8: Design. Temp ( 0C ) | I8: visco ( cP ) | J8: velocity ( cm/Sec | K8: Manufacture | L8: Score | M8: Grade | O8: Part | P8: USD | Q8: Date | U8: History | V8: Date | W8: Rekomendasi S/D 2027 | Y8: EaMS update
A9: 1 | B9: LM-024 | D9: - | E9: 1-N10-332-2 | F9: 2926 | G9: 15 | H9: 100 | I9: 1.744 | J9: 140 | O9: Klik | S9: OP-001
A10: 2 | B10: Z-820 | D10: Back wash | E10: 11/2"-N10-331-2 | F10: 5.2 | G10: 2 | H10: 50 | I10: 0.722 | J10: 108 | O10: Klik
A11: 3 | B11: Z-822 | D11: Sludge water | E11: 1"-N10-331-2 | F11: 2 | G11: 2 | H11: 50 | I11: 10 | J11: 107 | O11: Klik
A12: 4 | B12: LM-118 | D12: MPS | E12: SME-M250-2 ( 300 LB ) | F12: 5984 | G12: 18 | H12: 215 | I12: 0.016 | J12: 198 | O12: Klik
A13: 5 | B13: LM-232 | D13: IPA | E13: C38-6-2 ( 3/4) | F13: 8.8 | G13: 2 | H13: 50 | I13: 1.357 | J13: 55.7 | O13: Klik
A14: 6 | B14: LM-411 | D14: P ( EPA ) | E14: 6-N10-331-2 | F14: 54667 | G14: 7.1 | H14: 110 | I14: 4.623 | J14: 137 | O14: Klik | Y14: OK
A15: 7 | B15: LM-511 | D15: P ( EPA ) | E15: 3-N10-331-2 | F15: 14932 | G15: 6 | H15: 50 | I15: 1.76 | J15: 129 | O15: Klik
A16: 8 | B16: LM-611 | D16: P ( EPA ) | E16: 21/2"-N10-331-2 | F16: 9844 | G16: 5.7 | H16: 60 | I16: 2.03 | J16: 130 | O16: Klik
A17: 9 | B17: LM-102 | D17: - | E17: 4-N10-331-2 ( 300 LB ) | F17: 13046 | G17: 45 | H17: 60 | I17: 0.08 | J17: 95 | O17: Klik | S17: OP-002
S18: OP-010
S19: OP-013
S20: OP-019
A40: Total | D40: =COUNTA(B9:B38) -> 9 | S40: =COUNTA(S9:S38) -> 5 | U40: =COUNTA(U9:U38) -> 0
S41: =S40/D40 -> 0.55555556 | U41: =U40/D40 -> 0

Sheet 44
D1: EQUIPMENT LIST | O1: Document No. | Q1: : MNTC-ME
O2: Revision | Q2: : 0
O3: Date of issue | Q3: : 2023
A4: PT. PETRO OXO NUSANTARA | O4: Page | Q4: : 1 of 1
A5: STRAINER
A7: No | B7: TAG No. | C7: Description | D7: Fluid | E7: Model | F7: Design condition | M7: Category | O7: Complex Grade | P7: Spare | Q7: Price | R7: Installation | S7: Remark | X7: 46752
F8: Mesh | G8: Flow rate (M3/h ) | H8: Density (kg/M3 ) | I8: Design. Pres ( Kg./Cm3G ) | J8: Design. Temp ( 0C ) | K8: Class | L8: Manufacture | M8: Score | N8: Grade | P8: Part | Q8: USD | R8: Date | V8: History | W8: Date | X8: Rekomendasi S/D 2027 | Z8: EaMS update
A9: 1 | B9: BS-104 | D9: PPY | F9: 40 | G9: 11.86 | H9: 464 | I9: 28 | J9: 50 | K9: BG3A | P9: Klik | T9: OP-001 | Z9: OK
A10: =A9+1 -> 2 | B10: BS-101 | D10: PPY | F10: 40 | G10: 29 | H10: 464 | I10: 28 | J10: 150 | K10: BG3A | P10: Klik | T10: OP-001 | Z10: OK
A11: =A10+1 -> 3 | B11: YS-852A | C11: S-853 | P11: Klik | T11: U13
A12: =A11+1 -> 4 | B12: BS-103 | D12: TOL | F12: 40 | G12: 7.26 | H12: 843 | I12: 6.75 | J12: 50 | K12: AS1A | P12: Klik | T12: OP-002 | Z12: OK
A13: =A12+1 -> 5 | B13: BS-102 | D13: Catalyst | F13: 60 | G13: 0.01 | H13: 886 | I13: 23 | J13: 130 | K13: BS1A | P13: Klik | T13: OP-002 | Z13: OK
A14: =A13+1 -> 6 | B14: YS-102 | D14: Catalyst | F14: 40 | G14: 0.01 | H14: 886 | I14: 2 | J14: 50 | K14: AG1C | P14: Klik | T14: OP-002 | Z14: OK
A15: =A14+1 -> 7 | B15: TS-112 | D15: Oxo gas | F15: 40 | G15: 30 | H15: 32 | I15: 23 | J15: 50 | K15: BS1A | P15: Klik | T15: OP-002 | Z15: OK
A16: =A15+1 -> 8 | B16: YS-852B | C16: S-853 | P16: Klik | T16: U13
A17: =A16+1 -> 9 | B17: YS-110 | D17: P ( EPA ) | F17: 60 | G17: .- | H17: 780 | I17: 25 | J17: 150 | K17: BS1A | P17: Klik | T17: OP-002 | Z17: OK
A18: =A17+1 -> 10 | B18: TS-121A | D18: P ( EPA ) | F18: 40 | G18: 133 | H18: 780 | I18: 23 | J18: 130 | K18: BS1A | P18: Klik | T18: OP-002 | Z18: OK
A19: =A18+1 -> 11 | B19: TS-121B | D19: P ( EPA ) | F19: 40 | G19: 133 | H19: 780 | I19: 23 | J19: 130 | K19: BS1A | P19: Klik | T19: OP-002 | Z19: OK
A20: =A19+1 -> 12 | B20: YS-021A | D20: Mea Solution | F20: 40 | G20: 68.3 | H20: 981 | I20: 6.7 | J20: 170 | K20: AG1C | P20: Klik | T20: S8 | Z20: OK
A21: =A20+1 -> 13 | B21: TS-118A | D21: Hot Water | F21: 40 | G21: 561 | H21: 980 | I21: 4.8 | J21: 130 | K21: BS1A | P21: Klik | T21: OP-002 | Z21: OK
A22: =A21+1 -> 14 | B22: YS-021B | D22: Mea Solution | F22: 40 | G22: 68.3 | H22: 981 | I22: 6.7 | J22: 170 | K22: AG1C | P22: Klik | T22: S8 | Z22: OK
A23: =A22+1 -> 15 | B23: TS-142A | D23: P ( EPA ) | F23: 40 | G23: 89 | H23: 880 | I23: 2 | J23: 140 | K23: AS1A | P23: Klik | T23: OP-005 | Z23: OK
A24: =A23+1 -> 16 | B24: TS-142B | D24: P ( EPA ) | F24: 40 | G24: 89 | H24: 880 | I24: 2 | J24: 140 | K24: AS1A | P24: Klik | T24: OP-005 | Z24: OK
A25: =A24+1 -> 17 | B25: TS-145A | D25: P ( EPA ) | F25: 40 | G25: 89 | H25: 760 | I25: 2 | J25: 50 | K25: AS1A | P25: Klik | T25: OP-005 | Z25: OK
A26: =A25+1 -> 18 | B26: TS-145B | D26: P ( EPA ) | F26: 40 | G26: 89 | H26: 760 | I26: 2 | J26: 50 | K26: AS1A | P26: Klik | T26: OP-005 | Z26: OK
A27: =A26+1 -> 19 | B27: TS-162A | D27: P ( EPA ) | F27: 40 | G27: 552 | H27: 710 | I27: 2 | J27: 110 | K27: AS1A | P27: Klik | T27: OP-007 | Z27: OK
A28: =A27+1 -> 20 | B28: TS-162B | D28: P ( EPA ) | F28: 40 | G28: 552 | H28: 710 | I28: 2 | J28: 110 | K28: AS1A | P28: Klik | T28: OP-007 | Z28: OK
A29: =A28+1 -> 21 | B29: TS-163 | D29: P ( EPA ) | F29: 40 | G29: 535 | H29: 710 | I29: 2 | J29: 110 | K29: AS1A | P29: Klik | T29: OP-007 | Z29: OK
... A36: =A35+1 -> 28 | B36: TS-226 | D36: P ( EPA ) | F36: 40 | G36: 2.2 | H36: 980 | I36: 2 | J36: 50 | K36: AS1B | P36: Klik | T36: OP-009 | Z36: OK
A37: =A36+1 -> 29 | B37: YS-225A | D37: MPS | F37: 40 | G37: .- | H37: .- | I37: 18 | J37: 215 | K37: BG4A | P37: Klik | T37: OP-009
A38: =A37+1 -> 30 | B38: YS-225B | D38: MPS | F38: 40 | G38: .- | H38: .- | I38: 18 | J38: 215 | K38: BG4A | P38: Klik | T38: OP-009
A39: =A38+1 -> 31 | B39: TS-237 | D39: IPA | F39: 40 | G39: 2.2 | H39: 780 | I39: 2 | J39: 50 | K39: AS1A | P39: Klik | T39: OP-010 | Z39: OK
A40: =A39+1 -> 32 | B40: YS-233 | D40: P ( EPA ) | F40: 40 | G40: 0.19 | H40: 842 | I40: 2 | J40: 50 | K40: AS1A | P40: Klik | T40: OP-010 | Z40: OK
A41: =A40+1 -> 33 | B41: YS-231 | D41: P ( EPA ) | F41: 40 | G41: 0.052 | H41: 980 | I41: 5 | J41: 170 | K41: AS1A | P41: Klik | T41: OP-010 | Z41: OK
A42: =A41+1 -> 34 | B42: TS-243 | D42: P ( EPA ) | F42: 40 | G42: 1.84 | H42: 860 | I42: 2 | J42: 50 | K42: AS1A | P42: Klik | T42: OP-010 | Z42: OK
A43: =A42+1 -> 35 | B43: TS-251 | D43: P ( EPA ) | F43: 40 | G43: 1.406 | H43: 916 | I43: 2 | J43: 50 | K43: AS1A | P43: Klik | T43: OP-010 | Z43: OK
A44: =A43+1 -> 36 | B44: TS-252 | D44: P ( EPA ) | F44: 40 | G44: 26.29 | H44: 1000 | I44: 2 | J44: 160 | K44: AS1A | P44: Klik | T44: OP-010 | Z44: OK
A45: =A44+1 -> 37 | B45: TS-255 | D45: P ( EPA ) | F45: 40 | G45: 1.485 | H45: 840 | I45: 2 | J45: 50 | K45: AS1A | P45: Klik | T45: OP-010 | Z45: OK
A46: =A45+1 -> 38 | B46: TS-312A | D46: P ( EPA ) | F46: 40 | G46: 22.2 | H46: 938 | I46: 2 | J46: 105 | K46: AS1A | P46: Klik | T46: OP-011 | Z46: OK
A47: =A46+1 -> 39 | B47: TS-312B | D47: P ( EPA ) | F47: 40 | G47: 22.2 | H47: 938 | I47: 2 | J47: 105 | K47: AS1A | P47: Klik | T47: OP-011 | Z47: OK
A48: =A47+1 -> 40 | B48: TS-321A | D48: P ( EPA ) | F48: 40 | G48: 22.61 | H48: 798 | I48: 2 | J48: 105 | K48: AS1A | P48: Klik | T48: OP-011 | Z48: OK
A49: =A48+1 -> 41 | B49: TS-321B | D49: P ( EPA ) | F49: 40 | G49: 22.61 | H49: 798 | I49: 2 | J49: 105 | K49: AS1A | P49: Klik | T49: OP-011 | Z49: OK
A50: =A49+1 -> 42 | B50: TS-322A | D50: P ( EPA ) | F50: 40 | G50: 319.5 | H50: 840 | I50: 2 | J50: 170 | K50: AS1B | P50: Klik | T50: OP-012 | Z50: OK
... A55: =A54+1 -> 47 | B55: TS-325B | D55: P ( EPA ) | F55: 40 | G55: 19.82 | H55: 840 | I55: 2 | J55: 50 | K55: AS1B | P55: Klik | T55: OP-012 | Z55: OK
A56: =A55+1 -> 48 | B56: YS-225A | D56: P ( EPA ) | F56: 40 | G56: 2.2 | H56: 860 | I56: 2 | J56: 50 | K56: AS1B | P56: Klik | T56: OP-012
A57: =A56+1 -> 49 | B57: YS-225B | D57: P ( EPA ) | F57: 40 | G57: 2.2 | H57: 860 | I57: 2 | J57: 50 | K57: AS1B | P57: Klik | T57: OP-012
A58: =A57+1 -> 50 | B58: TS-411A | D58: P ( EPA ) | F58: 40 | G58: 85.6 | H58: 799 | I58: 4.6 | J58: 110 | K58: AS1A | P58: Klik | T58: OP-013 | Z58: OK
A59: =A58+1 -> 51 | B59: TS-411B | D59: P ( EPA ) | F59: 40 | G59: 85.6 | H59: 799 | I59: 4.6 | J59: 110 | K59: AS1A | P59: Klik | T59: OP-013 | Z59: OK
A60: =A59+1 -> 52 | B60: BS-410 | D60: P ( EPA ) | F60: 20 | G60: 93.3 | H60: 718 | I60: 45 | J60: 250 | K60: DS1A | P60: Klik | T60: OP-013 | Z60: OK
A61: =A60+1 -> 53 | B61: TS-422A | D61: P ( EPA ) | F61: 40 | G61: 66.8 | H61: 720 | I61: 2 | J61: 150 | K61: AS1B | P61: Klik | T61: OP-015 | Z61: OK
A62: =A61+1 -> 54 | B62: TS-422B | D62: P ( EPA ) | F62: 40 | G62: 66.8 | H62: 720 | I62: 2 | J62: 150 | K62: AS1B | P62: Klik | T62: OP-015 | Z62: OK
A63: =A62+1 -> 55 | B63: TS-426A | D63: P ( EPA ) | F63: 40 | G63: 1.31 | H63: 970 | I63: 2 | J63: 50 | K63: AS1B | P63: Klik | T63: OP-015 | Z63: OK
A64: =A63+1 -> 56 | B64: TS-426B | D64: P ( EPA ) | F64: 40 | G64: 1.31 | H64: 970 | I64: 2 | J64: 50 | K64: AS1B | P64: Klik | T64: OP-015 | Z64: OK
A65: =A64+1 -> 57 | B65: TS-425A | D65: P ( EPA ) | F65: 40 | G65: 5.79 | H65: 830 | I65: 2 | J65: 50 | K65: AS1NB | P65: Klik | T65: OP-015 | Z65: OK
A66: =A65+1 -> 58 | B66: TS-425B | D66: P ( EPA ) | F66: 40 | G66: 5.79 | H66: 830 | I66: 2 | J66: 50 | K66: AS1NB | P66: Klik | T66: OP-015 | Z66: OK
A67: =A66+1 -> 59 | B67: TS-432 | D67: P ( EPA ) | F67: 40 | G67: 27.7 | H67: 720 | I67: 2 | J67: 150 | K67: AS1B | P67: Klik | T67: OP-016 | Z67: OK
A68: =A67+1 -> 60 | B68: TS-435A | D68: P ( EPA ) | F68: 40 | G68: 28.1 | H68: 760 | I68: 2 | J68: 110 | K68: AS1B | P68: Klik | T68: OP-016 | Z68: OK
A69: =A68+1 -> 61 | B69: TS-435B | D69: P ( EPA ) | F69: 40 | G69: 28.1 | H69: 760 | I69: 2 | J69: 110 | K69: AS1B | P69: Klik | T69: OP-016 | Z69: OK
A70: =A69+1 -> 62 | B70: BS-437 | D70: P ( EPA ) | F70: 40 | G70: 15.4 | H70: 811 | I70: 7.2 | J70: 50 | K70: AG1E | P70: Klik | T70: OP-016 | Z70: OK
A73: Total | D73: =COUNTA(B9:B72) -> 62 | T73: =COUNTA(T9:T72) -> 62 | V73: =COUNTA(V9:V72) -> 0
T74: =T73/D73 -> 1 | V74: =V73/D73 -> 0

Sheet 43
D1: EQUIPMENT LIST | L1: Document No. | N1: : MNTC-ME
L2: Revision | N2: : 0
L3: Date of issue | N3: : 2023
A4: PT. PETRO OXO NUSANTARA | L4: Page | N4: : 1 of 1
A5: STEAM TRAP
A7: No | B7: TAG No. | C7: Description | D7: Fluid | E7: Model | F7: service condition | J7: Category | L7: Complex Grade | M7: Spare | N7: Price | O7: Installation | P7: Remark | U7: 46752
F8: Max pres kg/Cm2G | G8: Hydrotest press Kg/Cm2G | H8: Temp 0C | I8: Manufacture | J8: Score | K8: Grade | M8: Part | N8: USD | O8: Date | S8: History | T8: Date | U8: Rekomendasi S/D 2027 | W8: EaMS update
A9: 1 | B9: ST-101 | C9: TLV free float steam trap | D9: HWS/PPY | E9: JH8X-4 | F9: 6172 | G9: 6 | H9: 200 | I9: TLV Co.LTD
A10: 2 | B10: ST-102 | C10: TLV free float steam trap | D10: HWS/PPY | E10: JH5X | F10: 404 | G10: 18 | H10: 240 | I10: TLV Co.LTD | M10: Klik | Q10: OP-004
A11: 3 | B11: ST-121 | C11: TLV free float steam trap | D11: LPS/ALD CAT | E11: JH5X | F11: 505 | G11: 6 | H11: 240 | I11: TLV Co.LTD | M11: Klik | Q11: OP-005
A12: 4 | B12: ST-142 | C12: TLV free float steam trap | D12: MPS/CAT | E12: JH15-21 | F12: 12593 | G12: 18 | H12: 425 | I12: TLV Co.LTD | M12: Klik | Q12: OP-008
A13: 5 | B13: ST-212 | C13: TLV free float steam trap | D13: MPS/CAT | E13: JH3X | F13: 288 | G13: 18 | H13: 200 | I13: TLV Co.LTD | M13: Klik | Q13: OP-009 | W13: OK
A14: 6 | B14: ST-222 | C14: TLV free float steam trap | D14: MPS/CAT | E14: JH3X | F14: 208 | G14: 18 | H14: 215 | I14: TLV Co.LTD | M14: Klik | Q14: OP-010 | W14: OK
A15: 7 | B15: ST-252 | C15: TLV free float steam trap | D15: MPS/CAT | E15: JH3X | F15: 82 | G15: 18 | H15: 200 | I15: TLV Co.LTD | M15: Klik | Q15: OP-011 | W15: OK
A16: 8 | B16: ST-311 | C16: TLV free float steam trap | D16: LPS | E16: JH5X | F16: 500 | G16: 6 | H16: 215 | I16: TLV Co.LTD | M16: Klik | Q16: OP-012
A17: 9 | B17: ST-322 | C17: TLV free float steam trap | D17: MPS/EPA | E17: JH7X, 5 | F17: 3196 | G17: 18 | H17: 215 | I17: TLV Co.LTD
A18: 10 | B18: ST-411 | C18: TLV free float steam trap | D18: MPS/EPA | E18: JH7X, 5 | F18: 2450 | G18: 18 | H18: 215 | I18: TLV Co.LTD | M18: Klik | Q18: OP-015
A19: 11 | B19: ST-422 | C19: TLV free float steam trap | D19: MPS/2EH | E19: JH7X, 5 | F19: 2129 | G19: 18 | H19: 215 | I19: TLV Co.LTD | M19: Klik | Q19: OP-016
A20: 12 | B20: ST-432 | C20: TLV free float steam trap | D20: MPS/2EH | E20: JH7X, 5 | F20: 4034 | G20: 18 | H20: 215 | I20: TLV Co.LTD
A21: 13 | B21: ST-442 | C21: TLV free float steam trap | D21: MPS/2EHHE | E21: JH7X | F21: 593 | G21: 18 | H21: 215 | I21: TLV Co.LTD
A22: 14 | B22: ST-452 | C22: TLV free float steam trap | D22: MPS/2EHLE | E22: JH7X | F22: 744 | G22: 18 | H22: 215 | I22: TLV Co.LTD | M22: Klik | Q22: OP-019
A23: 15 | B23: ST-511 | C23: TLV free float steam trap | D23: MPS(CWS)/NBD | E23: JH7X | F23: 730 | G23: 18 | H23: 215 | I23: TLV Co.LTD
A24: 16 | B24: ST-522 | C24: TLV free float steam trap | D24: LPS/NBA | E24: JH7X | F24: 1216 | G24: 6 | H24: 200 | I24: TLV Co.LTD
A25: 17 | B25: ST-532 | C25: TLV free float steam trap | D25: NBA/RWS | E25: JH7X | F25: 1389 | G25: 6 | H25: 200 | I25: TLV Co.LTD | M25: Klik | Q25: OP-022 | S25: Replace steam trap 3/4" #300 | T25: 40743
A26: 18 | B26: ST-542 | C26: TLV free float steam trap | D26: MPS/NBAHE | E26: JH3X | F26: 288 | G26: 18 | H26: 215 | I26: TLV Co.LTD | W26: OK
A27: 19 | B27: ST-552 | C27: TLV free float steam trap | D27: LPS/NBALE | E27: JH5X | F27: 481 | G27: 6 | H27: 200 | I27: TLV Co.LTD
A28: 20 | B28: ST-611 | C28: TLV free float steam trap | D28: MPS/IBD | E28: JH7X | F28: 670 | G28: 18 | H28: 215 | I28: TLV Co.LTD
A29: 21 | B29: ST-622 | C29: TLV free float steam trap | D29: MPS/IBD | E29: JH7X,5X-5 | F29: 3491 | G29: 6 | H29: 200 | I29: TLV Co.LTD
A30: 22 | B30: ST-632 | C30: TLV free float steam trap | D30: LPS/IBA | E30: JH7X | F30: 1681 | G30: 6 | H30: 240 | I30: TLV Co.LTD
A31: 23 | B31: ST-642 | C31: TLV free float steam trap | D31: MPS/IBAHE | E31: JH5X | F31: 328 | G31: 18 | H31: 240 | I31: TLV Co.LTD
A32: 24 | B32: ST-851 | C32: TLV free float steam trap | D32: NaOH Solution/LP Steam | E32: JH7X | F32: 1700 | G32: 6 | H32: 150 | I32: TLV Co.LTD
A33: 25 | B33: ST-921 | C33: TLV free float steam trap | D33: MPS | E33: P46SR | F33: 150 | G33: 6 | H33: 152 | I33: TLV Co.LTD
A34: 26 | B34: ST-922 | C34: TLV free float steam trap | D34: LPS | E34: P46SR | F34: 150 | G34: 18 | H34: 215 | I34: TLV Co.LTD
A35: 27 | B35: ST-982 | C35: TLV free float steam trap | D35: LPS/WWT | E35: JH7X | F35: 1500 | G35: 6 | H35: 200 | I35: TLV Co.LTD
A41: Total | D41: =COUNTA(B9:B40) -> 27 | Q41: =COUNTA(Q9:Q40) -> 11 | S41: =COUNTA(S9:S40) -> 1
Q42: =Q41/D41 -> 0.40740741 | S42: =S41/D41 -> 0.037037037

Sheet 42
D1: EQUIPMENT LIST | H1: Document No. | J1: : MNTC-ME
H2: Revision | J2: : 0
H3: Date of issue | J3: : 2023
A4: PT. PETRO OXO NUSANTARA | H4: Page | J4: :
A5: SAFETY VALVE
U6: 46752
A7: NO | C7: NO. SV | D7: NO. ALAT | E7: SET POINT | F7: UKURAN | G7: ANSI | I7: Category | K7: Complex Grade | L7: Spare | M7: Price | N7: Installation | O7: Remark | S7: History | T7: Date | U7: Rekomendasi S/D 2027 | X7: EaMS update
H8: Manufacture | I8: Score | J8: Grade | L8: Part | M8: USD | N8: Date
A9: I. | B9: OCTANOL PLANT
B10: 1 | C10: SV-1051 | D10: 4" - Ppy 1002 | E10: 28 kg/cm2G | F10: 1.5" x 2.5" | G10: 300x150 | L10: Klik | Q10: OP-001 | S10: Recertification safety valve | T10: 44957 | X10: OK
B11: =B10+1 -> 2 | C11: SV-1052 | D11: R-102 | E11: 28 kg/cm2G | F11: 1.5" x 2.5" | G11: 300x150 | L11: Klik | Q11: OP-001 | S11: Recertification safety valve | T11: 44954 | X11: OK
B12: =B11+1 -> 3 | C12: SV-1053 | D12: D-101` | E12: 28 kg/cm2G | F12: 1.5" x 2.5" | G12: 300x150 | L12: Klik | Q12: OP-001 | S12: Recertification safety valve | T12: 44765 | U12: Plan replace spring SV next recertification in 2027 | X12: OK
B13: =B12+1 -> 4 | C13: SV-1054 | D13: 4" - Ppy 1001 | E13: 28 kg/cm2G | F13: 1.5" x 2.5" | G13: 300x300 | L13: Klik | Q13: OP-001 | S13: Recertification safety valve | T13: 44954 | U13: Recertification (Repair & Resetting) | X13: OK
B14: =B13+1 -> 5 | C14: SV-1151 | D14: S 115 | E14: 23 kg/cm2G | F14: 1.5" x 2" | G14: 300x150 | L14: Klik | Q14: OP-002 | S14: Recertification safety valve | T14: 44957 | X14: OK
B15: =B14+1 -> 6 | C15: SV-1152 | D15: D-118 | E15: 4.8 kg/cm2G | F15: 4" x 6" | G15: 150x150 | L15: Klik | Q15: OP-002 | S15: Recertification safety valve | T15: 44949 | X15: OK
B16: =B15+1 -> 7 | C16: SV-1351 | D16: D-135 | E16: 23 kg/cm2G | F16: 1.5" x 2.5" | G16: 300x150 | L16: Klik | Q16: OP-003 | S16: Recertification safety valve | T16: 44957 | X16: OK
B17: =B16+1 -> 8 | C17: SV-1251 | D17: 6" - P-1203 | E17: 23 kg/cm2G | F17: 1.5" x 2" | G17: 300x150 | L17: Klik | Q17: OP-004 | S17: Recertification safety valve | T17: 44957 | X17: OK
B18: =B17+1 -> 9 | C18: SV-1252 | D18: D-122 | E18: 6.3 kg/cm2G | F18: 4" x 6" | G18: 150x150 | L18: Klik | Q18: OP-004 | S18: Recertification safety valve | T18: 44958 | X18: OK
B19: =B18+1 -> 10 | C19: SV-1451 | D19: 6" - P-1412 | E19: 2 kg/cm2G | F19: 4" x 6" | G19: 150x150 | L19: Klik | Q19: OP-005 | S19: Recertification safety valve | T19: 44763 | X19: OK
B20: =B19+1 -> 11 | C20: SV-1551 | D20: 6" - P-1501 | E20: 2 kg/cm2G | F20: 1.5" x 3" | G20: 150x150 | L20: Klik | Q20: OP-006 | S20: Recertification safety valve | T20: 44954 | X20: OK
B21: =B20+1 -> 12 | C21: SV-1651 | D21: 8" - P-1622 | E21: 2.0 kg/cm2G | F21: 4" x 6" | G21: 150x150 | L21: Klik | Q21: OP-007 | S21: Recertification safety valve | T21: 44957 | U21: Recertification (Repair & Resetting) | X21: OK
B22: =B21+1 -> 13 | C22: SV-2151 | D22: 3" - P-2103 | E22: 5 kg/cm2G | F22: 1.5" x 2.5" | G22: 150x150 | L22: Klik | Q22: OP-008 | S22: Recertification safety valve | T22: 44959 | X22: OK
B23: =B22+1 -> 14 | C23: SV-2251 | D23: 3" - P-2221 | E23: 2 kg/cm2G | F23: 3" x 4" | G23: 150x150 | L23: Klik | Q23: OP-009 | S23: Recertification safety valve | T23: 44954 | U23: Recertification (Repair & Resetting) | X23: OK
B24: =B23+1 -> 15 | C24: SV-2252 | D24: 3" - P-2203 | E24: 5 kg/cm2G | F24: 1.5" x 2.5" | G24: 150x150 | L24: Klik | Q24: OP-009 | S24: Recertification safety valve | T24: 44959 | X24: OK
B25: =B24+1 -> 16 | C25: SV-2351 | D25: D-230 | E25: 25 kg/cm2G | F25: 1" x 2" | G25: 300x150 | L25: Klik | Q25: OP-010 | S25: Recertification safety valve | T25: 44957 | X25: OK
B26: =B25+1 -> 17 | C26: SV-2551 | D26: 2" - P-2505 | E26: 5 kg/cm2G | F26: 1" x 2" | G26: 150x150 | L26: Klik | Q26: OP-010 | S26: Recertification safety valve | T26: 44949 | U26: Recertification (Repair & Resetting) | X26: OK
B27: =B26+1 -> 18 | C27: SV-4151 | D27: 8" - GHY-4116 | E27: 45 kg/cm2G | F27: 1" x 2" | G27: 600x150 | L27: Klik | Q27: OP-013 | S27: Recertification safety valve | T27: 44958 | U27: Recertification (Repair & Resetting) | X27: OK
B28: =B27+1 -> 19 | C28: SV-4151 B | D28: 8" - GHY-4116 | E28: 45 kg/cm2G | F28: 1" x 2" | G28: 600x150 | L28: Klik | N28: 44905 | S28: New equipment of R-410 B | T28: 44905 | X28: OK
B29: =B28+1 -> 20 | C29: SV-4152 | D29: D-412 | E29: 6.3 kg/cm2G | F29: 6" x 8" | G29: 150x150 | L29: Klik | Q29: OP-013 | S29: Recertification safety valve | T29: 44959 | X29: OK
B30: =B29+1 -> 21 | C30: SV-4152 B | D30: D-412 B | E30: 6.3 kg/cm2G | L30: Klik | S30: New equipment of R-410 B | X30: OK
B31: =B30+1 -> 22 | C31: SV-4153 | D31: 2" - P-4122 | E31: 4.6 kg/cm2G | F31: 3" x 4" | G31: 150x150 | L31: Klik | Q31: OP-013 | S31: Recertification safety valve | T31: 44763 | X31: OK
B32: =B31+1 -> 23 | C32: SV-4153 B | D32: 2" - P-4122 | E32: 4.6 kg/cm2G | L32: Klik | S32: New equipment of R-410 B | X32: OK
B33: =B32+1 -> 24 | C33: SV-5151 | D33: 11/2" - GHY-5109 | E33: 45 kg/cm2G | F33: 1" x 2" | G33: 600x150 | L33: Klik | Q33: OP19 | S33: Recertification safety valve | T33: 44959 | U33: Recertification (Repair & Resetting) | X33: OK
B34: =B33+1 -> 25 | C34: SV-5151 B | D34: 11/2" - GHY-5109 | E34: 45.5 kg/cm2G | F34: 1" x 2" | G34: 600x150 | L34: Klik | N34: 44905 | S34: New equipment of R-510 B | T34: 44905 | X34: OK
B35: =B34+1 -> 26 | C35: SV-5152 | D35: D-512 | E35: 6.3 kg/cm2G | F35: 3" x 4" | G35: 150x150 | L35: Klik | Q35: OP19 | S35: Recertification safety valve | T35: 44765 | X35: OK
B36: =B35+1 -> 27 | C36: SV-5152 B | D36: D-512 B | E36: 6.3 kg/cm2G | L36: Klik | S36: New equipment of R-510 B | X36: OK
B37: =B36+1 -> 28 | C37: SV-5153 | D37: 11/2" - P-5114 | E37: 4.6 kg/cm2G | F37: 1.5" x 2.5" | G37: 150x150 | L37: Klik | Q37: OP-019 | S37: Recertification safety valve | T37: 44763 | X37: OK
B38: =B37+1 -> 29 | C38: SV-5153 B | D38: 3" - PGH - 5150 | E38: 4.5 kg/cm2G | F38: 1.5" x 3" | G38: 150x150 | L38: Klik | N38: 44905 | S38: New equipment of R-510 B | T38: 44905 | X38: OK
B39: =B38+1 -> 30 | C39: SV-6151 | D39: 11/2" - GHY-6109 | E39: 45 kg/cm2G | F39: 1" x 2" | G39: 600x150 | L39: Klik | Q39: OP24 | S39: Recertification safety valve | T39: 44959 | X39: OK
B40: =B39+1 -> 31 | C40: SV-6152 | D40: D-612 | E40: 4.6 kg/cm2G | F40: 4" x 6" | G40: 150x150 | L40: Klik | Q40: OP24 | S40: Recertification safety valve | T40: 44951 | U40: Recertification (Repair & Resetting) | X40: OK
B41: =B40+1 -> 32 | C41: SV-9651 | D41: 5" - FGS-9619 | E41: 3.8 kg/cm2G | F41: 1.5" x 3" | G41: 150x150 | L41: Klik | Q41: OP32 | S41: Recertification safety valve | T41: 44763 | X41: OK
B42: =B41+1 -> 33 | C42: SV-9951 | D42: 3" - NGB-9970 | E42: 1 kg/cm2G | F42: 1,5"x3" | G42: 150x150 | L42: Klik | Q42: U04 | S42: Recertification safety valve | T42: 44761 | X42: OK
B43: =B42+1 -> 34 | C43: SV-9611 | D43: P 961 | E43: 26 kg/cm2G | F43: 3/4" x 1" | G43: 300x150 | L43: Klik | Q43: OP-029 | S43: Recertification safety valve | T43: 44957
A44: II. | B44: SYN GAS | L44: Klik
B45: =B43+1 -> 35 | C45: SV-108 | D45: R-011 | E45: 21 kg/cm2G | F45: 1.5" x 2.5" | G45: 300x150 | L45: Klik | Q45: S1 | S45: Recertification safety valve | T45: 44954 | X45: OK
B46: =B45+1 -> 36 | C46: SV-124 | D46: 10" FGS | E46: 3.5 kg/cm2G | F46: 3" x 4" | G46: 150x150 | L46: Klik | Q46: S3 | S46: Recertification safety valve | T46: 44954 | X46: OK
B47: =B46+1 -> 37 | C47: SV-125 | D47: 14" - P-0107 | E47: 11 kg/cm2G | F47: 6" x 8" | G47: 150x150 | L47: Klik | Q47: S4 | S47: Recertification safety valve | T47: 44952 | U47: Recertification (Repair & Resetting) | X47: OK
B48: =B47+1 -> 38 | C48: SV-126 - 1 | D48: D-011 / WHB | E48: 18.5 kg/cm2G | F48: 4" x 6" | G48: 300x150 | L48: Klik | Q48: S4 | S48: Recertification safety valve | T48: 44952 | X48: OK
B49: =B48+1 -> 39 | C49: SV-126 - 2 | D49: D-011 / WHB | E49: 18.5 kg/cm2G | F49: 4" x 6" | G49: 300x150 | L49: Klik | Q49: S4 | S49: Recertification safety valve | T49: 44952 | X49: OK
B50: =B49+1 -> 40 | C50: SV-106 | D50: T-022 | E50: 4 kg/cm2G | F50: 4" x 6" | G50: 150x150 | L50: Klik | S50: Recertification safety valve | T50: 44952 | U50: Recertification (Repair & Resetting) | X50: OK
C51: SV-107 | D51: 4" - MCS-0205 | E51: 6 kg/cm2G | F51: 3" x 4" | G51: 150x150 | L51: Klik | S51: No safety valve | T51: 0 | X51: OK
B52: =B50+1 -> 41 | C52: SV-110 | D52: D-021 | E52: 4 kg/cm2G | F52: 2" x 3" | G52: 150x150 | L52: Klik | Q52: S7 | S52: Recertification safety valve | T52: 44948 | X52: OK
B53: =B52+1 -> 42 | C53: SV-130 | D53: 1 1/2" - PHS-0192 | E53: 29 kg/cm2G | F53: 3/4" x 1" | G53: 300x150 | L53: Klik | Q53: S4 | X53: OK
B54: =B53+1 -> 43 | C54: SV-131 | D54: 1 1/2" - PHS-0192 | E54: 29 kg/cm2G | F54: 3/4"x1" | G54: 300x150 | L54: Klik | Q54: S4 | X54: OK
B55: =B54+1 -> 44 | C55: SV-134 | D55: 10" - P-0202 | E55: 11 kg/cm2G | F55: 3" x 4" | G55: 150x150 | L55: Klik | Q55: S9 | S55: Recertification safety valve | T55: 44952 | X55: OK
B56: =B55+1 -> 45 | C56: SV-135 | D56: F-022 | E56: 15 kg/cm2G | F56: 1" x 3" | G56: 300x150 | L56: Klik | Q56: S22 | S56: Recertification safety valve | T56: 44949 | X56: OK
B57: =B56+1 -> 46 | C57: SV-116 | D57: 6" - GHY | E57: 12 kg/cm2G | F57: 1.5" x 2.5" | G57: 150x150 | L57: Klik | Q57: S11 | S57: Recertification safety valve | T57: 44957 | U57: Recertification (Repair & Resetting) | X57: OK
B58: =B57+1 -> 47 | C58: SV 02-1082 | D58: CO Guardbed | E58: 10.6 kg/cm2G | F58: 2" x 3" | G58: 300x150 | L58: Klik | S58: Recertification safety valve | T58: 44951 | U58: Recertification (Repair & Resetting)
B59: =B58+1 -> 48 | C59: SV 0031 | D59: CO Guardbed | E59: 14.1 kg/cm2G | F59: 3" x 4" | G59: 300x150 | L59: Klik | S59: Recertification safety valve | T59: 44951 | U59: Recertification (Repair & Resetting)
A60: III. | B60: UTILITY | L60: Klik
B61: =B59+1 -> 49 | C61: SV-920 | D61: 6" - LPS-9260 | E61: 6 kg/cm2G | F61: 4" x 6" | G61: 150x150 | L61: Klik | Q61: U14 | S61: Recertification safety valve | T61: 44954 | U61: Recertification (Repair & Resetting) | X61: OK
B62: =B61+1 -> 50 | C62: SV-922 | D62: D-922 | E62: 2 kg/cm2G | F62: 3" x 4" | G62: 150x150 | L62: Klik | Q62: U15 | S62: Recertification safety valve | T62: 44765 | X62: OK
B63: =B62+1 -> 51 | C63: SV-921 | D63: D-921 | E63: 4 kg/cm2G | F63: 3" x 4" | G63: 150x150 | L63: Klik | Q63: U16 | S63: Recertification safety valve | T63: 44958 | X63: OK
B64: =B63+1 -> 52 | C64: SV-993 | D64: 1 1/2" - GNS-9951 | E64: 1 kg/cm2G | F64: 1,5" x 2,5" | G64: 150x150 | L64: Klik | Q64: U26 | S64: Recertification safety valve | T64: 44765 | U64: Plan replace spring SV next recertification in 2027 | X64: OK
B65: =B64+1 -> 53 | C65: SV-962 | D65: 4" - FNG-9602 | E65: 5.3 kg/cm2G | F65: 1,5"x 3 " | G65: 150x150 | L65: Klik | Q65: U22 | S65: Recertification safety valve | T65: 44954 | X65: OK
A66: IV. | B66: OFFSITE | L66: Klik
B67: =B65+1 -> 54 | C67: SV-715 | D67: 3" - PGH-9513 | E67: 18.7 kg/cm2G | F67: 1" x 2" | G67: 300x150 | L67: Klik | Q67: U31 | S67: Recertification safety valve | T67: 44940 | U67: Recertification (Repair & Resetting) | X67: OK
B68: =B67+1 -> 55 | C68: SV-701 | D68: 10" - Ppy-7101 | E68: 28 kg/cm2G | F68: 1" x 2" | G68: 300x300 | L68: Klik | Q68: U32 | S68: Recertification safety valve | T68: 0 | U68: Recertification (Repair & Resetting) | X68: OK
B69: =B68+1 -> 56 | C69: SV-721 | D69: 6" - 2EH-7204 | E69: 12 kg/cm2G | F69: 3/4" x 1" | G69: 150x150 | L69: Klik | Q69: U33 | S69: Recertification safety valve | T69: 44940 | U69: Recertification (Repair & Resetting) | X69: OK
B70: =B69+1 -> 57 | C70: SV-724 | D70: 3" - 2EH-7202 | E70: 8 kg/cm2G | F70: 3/4" x 1" | G70: 150x150 | L70: Klik | Q70: U33 | S70: Recertification safety valve | T70: 44940 | U70: Recertification (Repair & Resetting) | X70: OK
A71: IV. | B71: OFFSITE | L71: Klik
B72: =B70+1 -> 58 | C72: SV-722 | D72: 6" - NBA-7224 | E72: 12 kg/cm2G | F72: 3/4" x 1" | G72: 150x150 | L72: Klik | Q72: U34 | S72: Recertification safety valve | T72: 44940 | U72: Recertification (Repair & Resetting) | X72: OK
B73: =B72+1 -> 59 | C73: SV-725 | D73: 3" - NBA-7227 | E73: 8 kg/cm2G | F73: 3/4"x1" | G73: 150x150 | L73: Klik | Q73: U34 | S73: Recertification safety valve | T73: 44940 | U73: Recertification (Repair & Resetting) | X73: OK
B74: =B73+1 -> 60 | C74: SV-723 | D74: 6" - IBA-7234 | E74: 12 kg/cm2G | F74: 3/4" x 1" | G74: 150x150 | L74: Klik | Q74: U35 | S74: Recertification safety valve | T74: 44940 | U74: Recertification (Repair & Resetting) | X74: OK
B75: =B74+1 -> 61 | C75: SV-726 | D75: 3" - IBA-7237 | E75: 8 kg/cm2G | F75: 3/4"x1" | G75: 150x150 | L75: Klik | S75: Recertification safety valve | T75: 44940 | U75: Recertification (Repair & Resetting) | X75: OK
C76: SV-727 | D76: 6" - 2EH-7204 | E76: 12 kg/cm2G | F76: 3/4" x 1" | G76: 150x150 | L76: Klik | Q76: U33 | S76: No safety valve | T76: 0 | X76: OK
A77: V. | B77: PERALATAN (PAKET) | L77: Klik
B78: a. Spherical Tank | L78: Klik
B79: =B75+1 -> 62 | C79: SV-711 A | D79: D-711 | E79: 18.69 kg/cm2G | F79: 6" x 8" | G79: 300x150 | L79: Klik | Q79: U32 | S79: Recertification safety valve | T79: 44948
B80: =B79+1 -> 63 | C80: SV-711 B | D80: D-711 | E80: 18.69 kg/cm2G | F80: 6" x 8" | G80: 300x150 | L80: Klik | Q80: U32 | S80: Recertification safety valve | T80: 44961
B81: =B80+1 -> 64 | C81: SV-712 A | D81: D-712 | E81: 18.69 kg/cm2G | F81: 6" x 8" | G81: 300x150 | L81: Klik | Q81: U32 | S81: Recertification safety valve | T81: 44961
B82: =B81+1 -> 65 | C82: SV-712 B | D82: D-712 | E82: 18.69 kg/cm2G | F82: 6" x 8" | G82: 300x150 | L82: Klik | Q82: U32 | S82: Recertification safety valve | T82: 44962
B83: =B82+1 -> 66 | C83: SV-713 A | D83: D-713 | E83: 18.69 kg/cm2G | F83: 6" x 8" | G83: 300x150 | L83: Klik | Q83: U32 | S83: Recertification safety valve | T83: 44961
B84: =B83+1 -> 67 | C84: SV-713 B | D84: D-713 | E84: 18.69 kg/cm2G | F84: 6" x 8" | G84: 300x150 | L84: Klik | Q84: U32 | S84: Recertification safety valve | T84: 44962
B85: =B84+1 -> 68 | C85: SV-714 A | D85: D-714 | E85: 18.69 kg/cm2G | F85: 6" x 8" | G85: 300x150 | L85: Klik | Q85: U32 | S85: Recertification safety valve | T85: 44961
B86: =B85+1 -> 69 | C86: SV-714 B | D86: D-714 | E86: 18.69 kg/cm2G | F86: 6" x 8" | G86: 300x150 | L86: Klik | Q86: U32 | S86: Recertification safety valve | T86: 44962
B87: b. Compressor | L87: Klik
B88: =B86+1 -> 70 | C88: SV-0180 | D88: C-011 | E88: 23.8 kg/cm2G | F88: 1" x 2" | G88: 300x150 | L88: Klik | Q88: S16 | S88: Recertification safety valve | T88: 44951 | X88: OK
B89: =B88+1 -> 71 | C89: SV-117 | D89: C-011 | E89: 45 kg/cm2G | F89: 1" x 2" | G89: 600x150 | L89: Klik | Q89: S16 | S89: Recertification safety valve | T89: 44764 | U89: Plan replace new SV next recertification in 2027 | X89: OK
B90: =B89+1 -> 72 | C90: SV-0182 | D90: C-018 | E90: 16.2 kg/cm2G | F90: 3" x 4" | G90: 300x150 | L90: Klik | Q90: S16 | S90: Recertification safety valve | T90: 44951
B91: =B90+1 -> 73 | C91: SV-132 | D91: C-018 | E91: 26.5 kg/cm2G | F91: 3" x 4" | G91: 300x150 | L91: Klik | Q91: S9 | S91: Recertification safety valve | T91: 44763
B92: =B91+1 -> 74 | C92: SV-0184 | D92: C-012 | E92: 7.5 kg/cm2G | F92: 1.5" x 3" | G92: 150x150 | L92: Klik | Q92: S17 | S92: Recertification safety valve | T92: 44951 | X92: OK
B93: =B92+1 -> 75 | C93: SV-112 | D93: C-012 | E93: 17 kg/cm2G | F93: 1.5" x 3" | G93: 300x150 | L93: Klik | Q93: S7 | S93: Recertification safety valve | T93: 44951 | X93: OK
B94: =B93+1 -> 76 | C94: SV-1580 | D94: C-150 | E94: 3.9 kg/cm2G | F94: 1.5" x 3" | G94: 150x150 | L94: Klik | S94: Recertification safety valve | T94: 44957 | X94: OK
B95: =B94+1 -> 77 | C95: SV-1552 | D95: C-150 | E95: 7.8 kg/cm2G | F95: 1.5" x 2" | G95: 150x150 | L95: Klik | Q95: OP-006 | S95: Recertification safety valve | T95: 44954 | X95: OK
B96: =B95+1 -> 78 | C96: SV-4156 | D96: C-412 | E96: 45 kg/cm2G | F96: 2" x 3" | G96: 600x150 | L96: Klik | Q96: OP-014 | S96: Recertification safety valve | T96: 44957 | X96: OK
B97: =B96+1 -> 79 | C97: SV-009 | D97: C-009 | E97: 19 kg/cm2G | F97: 1.5" x 3" | G97: 300x150 | L97: Klik | Q97: U22 | S97: Recertification safety valve | T97: 44957
B98: =B97+1 -> 80 | C98: SV-008 | D98: C-008 | E98: 19 kg/cm2G | F98: 2" x 3" | G98: 300x150 | L98: Klik | Q98: U22 | S98: Recertification safety valve | T98: 44763
B99: c. PSA | L99: Klik
B100: =B98+1 -> 81 | C100: SV-451 | D100: PSA | E100: 12 kg/cm2G | F100: 1" x 2" | G100: 300x150 | L100: Klik | Q100: S14 | S100: Recertification safety valve | T100: 44951
...

Sheet 41
D1: EQUIPMENT LIST | P1: Document No. | Q1: : MNTC-ME
P2: Revision | Q2: : 0
P3: Date of issue | Q3: : 2023
A4: PT. PETRO OXO NUSANTARA | P4: Page | Q4: : 1 of 1
A5: EJECTOR
A7: No | B7: TAG No. | C7: Description | D7: Design data | N7: Material contruction | Q7: Category | S7: Complex Grade | T7: Spare | U7: Price | V7: Installation | W7: Remark | AB7: 46752
D8: TEMA | E8: Dimension | F8: Heat Duty | G8: Surface Area | H8: Stream Fluid Service | J8: Pressure (kg/cm2) | L8: Temperature (oC) | P8: Manufacture | Q8: Score | R8: Grade | T8: Part | U8: USD | V8: Date | AD8: EaMS update
D9: Type | E9: (OD x L. mm) | F9: (kcal/h) | G9: (m2) | H9: Hot - Shell Side | I9: Cold - Tube Side | J9: Hot | K9: Cold | L9: Hot | M9: Cold | N9: Shell | O9: Tube | Z9: History | AA9: Date | AB9: Rekomendasi S/D 2027
A10: 1 | B10: J-225 | C10: Steam | D10: R | E10: Inter Condenser : 10" x 2200, After Condenser : 6" x 1400 | F10: 0.0004 | G10: Inter Cond : 7.8, After Cond : 1.7 | H10: Steam + Vapour + Condensate | I10: CWS | J10: 20 | K10: 4 | L10: 250 | M10: 60 | N10: SUS304 | O10: SUS304 | P10: GEA, Leewon | T10: Klik | V10: 44717 | X10: OP-009 | Z10: Replace Unit | AA10: 44717 | AD10: OK
A11: 2 | B11: J-335 | C11: Steam | D11: R | E11: 10" X 2000 | F11: 0.0004 | G11: 5.7 | H11: Steam + Vapour + Condensate | I11: CWS | J11: 15 | K11: 3.5 | L11: 201 | M11: 32 - 45 | N11: STPG370-S | O11: STB340-S | T11: Klik | Z11: Revamping, operated using ex-J-435 | AA11: 39419
A12: 3 | B12: J-435 | C12: Steam | D12: R | E12: 6" X 3457 | F12: * | G12: * | H12: Steam + Vapour + Condensate | I12: CWS | J12: 18 | K12: 15 | L12: 215 | M12: 80 | N12: SST304 | O12: SST304 | T12: Klik | U12: 49000 | Z12: Modified line pipe to J-435 | AA12: 41333 | AD12: OK
A13: 4 | B13: J-425 | C13: Steam | D13: BEM | E13: 10" X 2200 | F13: 0.0004 | G13: 7.8 | H13: Steam + Vapour + Condensate | I13: CWS | J13: 18 | K13: 32 | L13: 215 | M13: 40 | N13: SUS 304 | O13: SUS 304 | P13: GEA | T13: Klik | Z13: New equipment | AA13: 43299
A21: Total | U21: =SUM(U10:U20) -> 49000
A22: Note :
A29: Total Equipment | D29: =COUNTA(B10:B28) -> 4 | X29: =COUNTA(X10:X28) -> 1 | Z29: =COUNTA(Z10:Z28) -> 4
X30: =X29/D29 -> 0.25 | Z30: =Z29/D29 -> 1

Sheet 40
D1: EQUIPMENT LIST | T1: Document No. | V1: : MNTC-ME
T2: Revision | V2: : 0
T3: Date of issue | V3: : 2023
A4: PT. PETRO OXO NUSANTARA | T4: Page | V4: :
A5: CANNED PUMP
AL6: 46752
A7: No | B7: Area | C7: Tag No | D7: Service | E7: Fluid | F7: Type | G7: Serial No | H7: Head | I7: Design Capacity | J7: Temp . Pump | K7: Spect | L7: Vis. At pump | M7: Disc. press | N7: Suct. press | O7: Diff. Press | P7: NPSH avail | Q7: Material | T7: RPM | U7: BHP | V7: Motor | Y7: Manufacture | Z7: Category | AB7: Complex grade | AC7: Spare | AD7: Instruksi | AE7: Price | AF7: Installation | AG7: Remark | AN7: EaMS update
H8: m | I8: m3/h | J8: 0C | K8: Gravity | L8: Cp | M8: Kg/cm2G | N8: Kg/cm2G | O8: Kg/cm2G | P8: m | Q8: Casing | R8: Impeller | S8: Shaft | U8: KW | V8: Cycle ( HZ ) | W8: Pole | X8: Volt / Phase | Z8: Score | AA8: Grade | AC8: part | AD8: Kerja | AE8: USD | AF8: Date | AJ8: History | AK8: Date | AL8: Rekomendasi S/D 2027
A9: 1 | B9: Syn Gas | C9: P-022A | D9: Stripper Reflux Pump | E9: Water + CO | F9: F41-216 F4M C204TIBI-BV | G9: CL-2169-1/-2 | H9: 39 | I9: 4,6 | J9: 40 | K9: 0.992 | L9: 0.65 | M9: 5.66 | N9: 1.79 | O9: 3.87 | P9: 4.2 | Q9: 304 | R9: 304 | S9: 304 | T9: 2860 | U9: 1.76 | V9: 50 | X9: 380 | Y9: Teikoku | AC9: Klik | AE9: 37000 | AG9: Canned pump | AH9: S7 | AJ9: Replace bearing A & B | AK9: 40648 | AN9: OK
A10: =A9+1 -> 2 | B10: Syn Gas | C10: P-022B | D10: Stripper Reflux Pump | E10: Water + CO | F10: F41-216 F4M C204TIBI-BV | G10: CL-2169-1/-2 | H10: 39 | I10: 4,6 | J10: 40 | K10: 0.992 | L10: 0.65 | M10: 5.66 | N10: 1.79 | O10: 3.87 | P10: 4.2 | Q10: 304 | R10: 304 | S10: 304 | T10: 2860 | U10: 1.76 | V10: 50 | X10: 380 | Y10: Teikoku | AC10: Klik | AE10: 37000 | AG10: Canned pump | AH10: S7 | AJ10: Replace bearing A & B | AK10: 36297 | AN10: OK
A11: =A10+1 -> 3 | B11: Syn Gas | C11: P-023 | D11: MEA Make Up Pump | E11: MEA | F11: F41-416 F4M 040 5VIBI-BV | G11: CL-2170 | H11: 53.3 | I11: 10 | J11: 30 | K11: 1.007 | L11: 1.8 | M11: 5.08 | N11: -0.29 | O11: 5.37 | P11: 7.4 | Q11: 304 | R11: 304 | S11: 304 | T11: 2900 | U11: 7.4 | V11: 50 | X11: 380 | Y11: Teikoku | AC11: Klik | AE11: 4400 | AH11: S23 | AJ11: Replace bearing A & B | AK11: 38673 | AN11: OK
A12: =A11+1 -> 4 | B12: Syn Gas | C12: P-024 | D12: Inhibitor A + B Pump | E12: IHB A+B | F12: F41-215F4AM020451-BV | G12: CL-2171 | H12: 28.2 | I12: 1,7 | J12: 80 | K12: 0.977 | L12: 0.42 | M12: 2.76 | N12: 0 | O12: 2.76 | P12: 5.8 | Q12: 304 | R12: 304 | S12: 304 | T12: 2900 | U12: 0.94 | V12: 50 | X12: 380 / 3 | Y12: Teikoku | AC12: Klik | AE12: 3900 | AH12: S22 | AJ12: New unit running with bearing A & B | AK12: 35733 | AN12: OK
A13: =A12+1 -> 5 | B13: Syn Gas | C13: P-025A | D13: Filter Pump | E13: MEA | F13: F41-316F4AM0204TIBI-BV | G13: CL-2172 | H13: 50.2 | I13: 5,2 | J13: 80 | K13: 1 | L13: 1.744 | M13: 5.02 | N13: 0 | O13: 5.02 | P13: 9.3 | Q13: 304 | R13: 304 | S13: 304 | T13: 2900 | U13: 3.3 | V13: 50 | X13: 380 / 3 | Y13: Teikoku | AC13: Klik | AE13: 10200 | AH13: S22 | AJ13: Replace bearing A & B | AK13: 44827 | AN13: OK
A14: =A13+1 -> 6 | B14: Syn Gas | C14: P-025B | D14: Filter Pump | E14: MEA | F14: F41-316F4AM0204TIBI-BV | G14: CL-2172 | H14: 50.2 | I14: 5,2 | J14: 80 | K14: 1 | L14: 1.744 | M14: 5.02 | N14: 0 | O14: 5.02 | P14: 9.3 | Q14: 304 | R14: 304 | S14: 304 | T14: 2900 | U14: 3.3 | V14: 50 | X14: 380 / 3 | Y14: Teikoku | AC14: Klik | AE14: 10200 | AH14: S9 | AI14: S22 | AJ14: Not operated, change tag no. to P-027 service BFW recycle T-023 to E-026 B | AN14: OK
A15: =A14+1 -> 7 | B15: Syn Gas | C15: P-027 A (EXP-025B) | D15: Cooling Water | E15: Water | F15: F41-316F4AM0204TIBI-BV | G15: CL-2172 | H15: 50.2 | I15: 5,2 | J15: 80 | K15: 1 | L15: 1.744 | M15: 5.02 | N15: 0 | O15: 5.02 | P15: 9.3 | Q15: 304 | R15: 304 | S15: 304 | T15: 2900 | U15: 3.3 | V15: 50 | X15: 380 / 3 | Y15: Teikoku | AC15: Klik | AE15: 10200 | AJ15: Replace bearing A & B, replace shaft sleeve, ex P-025 B | AK15: 44827
A16: =A15+1 -> 8 | B16: Octanol | C16: P-110A | D16: A-110 Pressure Unit | E16: 2EH | F16: F60-3215N4BL-0204TF1-BV | G16: FP-1454A | H16: 48.8 | I16: 3 | J16: 50 | K16: 0.799 | L16: 0.8 | M16: 5 | N16: 0.2 | O16: 4.8 | P16: 2.1 | Q16: CF-8M 316SS | R16: CF-8M 316SS | S16: SUS316 | T16: 3000 | U16: 3.7 | V16: 50 | W16: 2 | X16: 380 | Y16: Teikoku | AC16: Klik | AE16: 11000 | AF16: 44945 | AG16: Canned pump | AJ16: New pump P-110 A Teikoku | AK16: 44945 | AN16: OK
A17: =A16+1 -> 9 | B17: Octanol | C17: P-110B | D17: A-110 Pressure Unit | E17: 2EH | F17: F60-3215N4BL-0204TF1-BV | G17: FP-1454A | H17: 48.8 | I17: 3 | J17: 50 | K17: 0.799 | L17: 0.8 | M17: 5 | N17: 0.2 | O17: 4.8 | P17: 2.1 | Q17: CF-8M 316SS | R17: CF-8M 316SS | S17: SUS317 | T17: 3000 | U17: 3.7 | V17: 50 | W17: 2 | X17: 380 | Y17: Teikoku | AG17: Installed 2022 | AJ17: Remove from P-230 | AN17: OK
A18: =A17+1 -> 10 | B18: Octanol | C18: P-117 | D18: Oxo CAT Pump | E18: OXO CAT | F18: F41-416F4M0506TI-BV | G18: CL-2173 | H18: 39 | I18: 30 | J18: 50 | K18: 0.95 | L18: 2.392 | M18: 3.26 | N18: 0.43 | O18: 3.69 | P18: 5 | Q18: 304 | R18: 304 | S18: 304 | T18: 2900 | U18: 7.4 | V18: 50 | X18: 380 / 3 | Y18: Teikoku | AC18: Klik | AE18: 7400 | AJ18: Replace bearing A & B | AK18: 38492 | AN18: OK
A19: =A18+1 -> 11 | B19: Octanol | C19: P-121A | D19: T - 120 Feed Pump | E19: OXO | F19: FA43-617J4BM 1012 VIV-FV | G19: CL-2174 | H19: 66 | I19: 133 | J19: 100 | K19: 0.78 | L19: 0.46 | M19: 23.02 | N19: 17.9 | O19: 5.12 | P19: 5 | Q19: 304 | R19: 304 | S19: 304 | T19: 2900 | U19: 38.7 | V19: 50 | X19: 380 / 3 | Y19: Teikoku | AC19: Klik | AE19: 31500 | AH19: OP-002 | AJ19: Replace bearing A & B | AK19: 43727 | AN19: OK
A20: =A19+1 -> 12 | B20: Octanol | C20: P-121B | D20: T - 120 Feed Pump | E20: OXO | F20: FA43-617J4BM 1012 VIV-FV | G20: CL-2174 | H20: 66 | I20: 133 | J20: 100 | K20: 0.78 | L20: 0.46 | M20: 23.02 | N20: 17.9 | O20: 5.12 | P20: 5 | Q20: 304 | R20: 304 | S20: 304 | T20: 2900 | U20: 38.7 | V20: 50 | X20: 380 / 3 | Y20: Teikoku | AC20: Klik | AE20: 31500 | AH20: OP-002 | AJ20: Replace bearing A & B | AK20: 39093 | AN20: OK
A21: =A20+1 -> 13 | B21: Octanol | C21: P-145A | D21: T - 140 Reflux Pump | E21: Crude Ald | F21: F41-518C4M0810VI-BV | G21: CL-2175 | H21: 44 | I21: 89 | J21: 40 | K21: 0.76 | L21: .0.745 | M21: 3.71 | N21: 0.39 | O21: 3.32 | P21: 10 | Q21: 304 | R21: 304 | S21: 304 | T21: 2900 | U21: 22.4 | V21: 50 | X21: 380 / 3 | Y21: Teikoku | AC21: Klik | AE21: 11600 | AH21: OP-005 | AJ21: Replace bearing A & B | AK21: 40998 | AN21: OK
A22: =A21+1 -> 14 | B22: Octanol | C22: P-145B | D22: T - 140 Reflux Pump | E22: Crude Ald | F22: F41-518C4M0810VI-BV | G22: CL-2175 | H22: 44 | I22: 89 | J22: 40 | K22: 0.76 | L22: .0.745 | M22: 3.71 | N22: 0.39 | O22: 3.32 | P22: 10 | Q22: 304 | R22: 304 | S22: 304 | T22: 2900 | U22: 22.4 | V22: 50 | X22: 380 / 3 | Y22: Teikoku | AC22: Klik | AE22: 11600 | AH22: OP-005 | AJ22: New unit running with bearing A & B | AK22: 36030 | AN22: OK
A23: =A22+1 -> 15 | B23: Octanol | C23: P-147A | D23: T - 160 Feed Pump | E23: Crude Ald | F23: F41-416F4M0506UI-BV | G23: CL-2176 | H23: 55 | I23: 28 | J23: 40 | K23: 0.76 | L23: 0.375 | M23: 4.05 | N23: -0.1 | O23: 4.15 | P23: 8 | Q23: 304 | R23: 304 | S23: 304 | T23: 2900 | U23: 7.3 | V23: 50 | X23: 380 / 3 | Y23: Teikoku | AC23: Klik | AE23: 8300 | AJ23: Replace bearing A & B | AK23: 42249 | AN23: OK
A24: =A23+1 -> 16 | B24: Octanol | C24: P-147B | D24: T - 160 Feed Pump | E24: Crude Ald | F24: F41-416F4M0506UI-BV | G24: CL-2176 | H24: 55 | I24: 28 | J24: 40 | K24: 0.76 | L24: 0.375 | M24: 4.05 | N24: -0.1 | O24: 4.15 | P24: 8 | Q24: 304 | R24: 304 | S24: 304 | T24: 2900 | U24: 7.3 | V24: 50 | X24: 380 / 3 | Y24: Teikoku | AC24: Klik | AE24: 8300 | AJ24: New unit running with bearing A & B | AK24: 36012 | AN24: OK
A25: =A24+1 -> 17 | B25: Octanol | C25: P-165A | D25: T - 160 Reflux Pump | E25: IBD | F25: F41-518L4M 081OUI-BV | G25: CL-2177 | H25: 57 | I25: 75 | J25: 50 | K25: 0.75 | L25: 0.4 | M25: 4.81 | N25: 0.52 | O25: 4.29 | P25: 10 | Q25: 304 | R25: 304 | S25: 304 | T25: 2900 | U25: 21.7 | V25: 50 | X25: 380 / 3 | Y25: Teikoku | AC25: Klik | AE25: 12200 | AH25: OP-007 | AJ25: New unit running with bearing A & B | AK25: 35782 | AN25: OK
A26: =A25+1 -> 18 | B26: Octanol | C26: P-165B | D26: T - 160 Reflux Pump | E26: IBD | F26: F41-518L4M 081OUI-BV | G26: CL-2177 | H26: 57 | I26: 75 | J26: 50 | K26: 0.75 | L26: 0.4 | M26: 4.81 | N26: 0.52 | O26: 4.29 | P26: 10 | Q26: 304 | R26: 304 | S26: 304 | T26: 2900 | U26: 21.7 | V26: 50 | X26: 380 / 3 | Y26: Teikoku | AC26: Klik | AE26: 12200 | AH26: OP-007 | AJ26: New unit running with bearing A & B | AK26: 35782 | AN26: OK
A27: =A26+1 -> 19 | B27: Octanol | C27: P-167A | D27: NBD Pump | E27: NBD | F27: F41 416F4M0506UI-BV | G27: CL-2178 | H27: 63 | I27: 26,8 | J27: 40 | K27: 756 | L27: 0.37 | M27: 4.686 | N27: 0.82 | O27: 4.768 | P27: 10 | Q27: 304 | R27: 304 | S27: 304 | T27: 2900 | U27: 8.2 | V27: 50 | X27: 380 / 3 | Y27: Teikoku | AC27: Klik | AE27: 8300 | AJ27: New unit running with bearing A & B | AK27: 35836 | AN27: OK
A28: =A27+1 -> 20 | B28: Octanol | C28: P-167B | D28: NBD Pump | E28: NBD | F28: F41 416F4M0506UI-BV | G28: CL-2178 | H28: 63 | I28: 26,8 | J28: 40 | K28: 756 | L28: 0.37 | M28: 4.686 | N28: 0.82 | O28: 4.768 | P28: 10 | Q28: 304 | R28: 304 | S28: 304 | T28: 2900 | U28: 8.2 | V28: 50 | X28: 380 / 3 | Y28: Teikoku | AC28: Klik | AE28: 8300 | AJ28: New unit running with bearing A & B | AK28: 35836 | AN28: OK
A29: =A28+1 -> 21 | B29: Octanol | C29: P-169A | D29: IBD Pump | E29: IBD | F29: F41 316 F4M 0405UIBI-BV | G29: CL-2179 | H29: 60 | I29: 2,62 | J29: 49.9 | K29: 753 | L29: 0.399 | M29: 4.514 | N29: 0.04 | O29: 4.518 | P29: 5 | Q29: 304 | R29: 304 | S29: 304 | T29: 2900 | U29: 3.7 | V29: 50 | X29: 380 | Y29: Teikoku | AC29: Klik | AJ29: Replace bearing A & B | AK29: 36543 | AN29: OK
A30: =A29+1 -> 22 | B30: Octanol | C30: P-169B | D30: IBD Pump | E30: IBD | F30: F41 316 F4M 0405UIBI-BV | G30: CL-2179 | H30: 60 | I30: 2,62 | J30: 49.9 | K30: 753 | L30: 0.399 | M30: 4.514 | N30: 0.04 | O30: 4.518 | P30: 5 | Q30: 304 | R30: 304 | S30: 304 | T30: 2900 | U30: 3.7 | V30: 50 | X30: 380 | Y30: Teikoku | AC30: Klik | AJ30: New unit running with bearing A & B | AK30: 35842 | AN30: OK
A31: =A30+1 -> 23 | B31: Octanol | C31: P-172 | D31: IBD Pump | E31: IBD | F31: R41-215F4DM-0204S1-B | G31: FP-1686A | H31: 25.9 | I31: 1.28 | J31: 67.48 | K31: 0.737 | L31: 0.26 | M31: 1 | N31: 0.091 | O31: =M31-N31 -> 0.909 | P31: 0.957 | Q31: 304 | R31: 304 | S31: 304 | T31: 3000 | U31: 1.1 | V31: 50 | X31: 380 | Y31: Teikoku | AC31: Klik | AE31: 3500 | AF31: 44727 | AJ31: Install new unit of T-170 | AK31: 44727 | AN31: OK
A32: =A31+1 -> 24 | B32: Octanol | C32: P-174 | D32: IBD Pump | E32: IBD | F32: R41-216F4BM-0204T1B1-B | G32: FP-1687A | H32: 39.7 | I32: 3.22 | J32: 66.33 | K32: 0.737 | L32: 0.26 | M32: 3 | N32: 0.074 | O32: =M32-N32 -> 2.926 | P32: 3.33 | Q32: 304 | R32: 304 | S32: 304 | T32: 3000 | U32: 2.2 | V32: 50 | X32: 380 | Y32: Teikoku | AC32: Klik | AE32: 4500 | AF32: 44727 | AJ32: Install new unit of T-170 | AK32: 44727 | AN32: OK
A33: =A32+1 -> 25 | B33: Octanol | C33: P-175 | D33: IBD Pump | E33: IBD | F33: F60-3215N4BL-0204TF1-BV | G33: FP-1688A | H33: 38.48 | I33: 6.33 | J33: 45 | K33: 0.764 | L33: 0.332 | M33: 3 | N33: 0.06 | O33: =M33-N33 -> 2.94 | P33: 8.065 | Q33: 304 | R33: 304 | S33: 304 | T33: 3000 | U33: 2.2 | V33: 50 | X33: 380 | Y33: Teikoku | AC33: Klik | AE33: 4500 | AF33: 44727 | AJ33: Install new unit of T-170 | AK33: 44727 | AN33: OK
A34: =A33+1 -> 26 | B34: Octanol | C34: P-179 | D34: IBD Pump | E34: IBD | F34: F41-616C4BM-0810V1-BV | G34: FP-2039A | H34: 91.9 | I34: 30 | J34: 50 | K34: 0.755 | L34: 0.303 | M34: 7 | N34: 0.06 | O34: =M34-N34 -> 6.94 | P34: 5 | Q34: 304 | R34: 304 | S34: 304 | T34: 3000 | U34: 30 | V34: 50 | X34: 380 | Y34: Teikoku | AE34: 20000 | AF34: 44727 | AJ34: Install new unit of T-170 | AK34: 44727
A35: =A34+1 -> 27 | B35: Octanol | C35: P-212 | D35: T - 210 Bottom Pump | E35: Heavy End | F35: F41 416 J4BM0608T-BV | G35: CL-2180 | H35: 24.1 | I35: 51 | J35: 129 | K35: 0.96 | L35: 3.57 | M35: 1.71 | N35: .-0.60 | O35: 2.31 | P35: 3 | Q35: 304 | R35: 304 | S35: 304 | T35: 2900 | U35: 8.1 | V35: 50 | X35: 380 / 3 | Y35: Teikoku | Z35: 5 | AA35: C | AB35: * | AC35: Klik | AE35: 6100 | AH35: OP-008 | AJ35: Replace bearing A & B | AK35: 44825 | AN35: OK
A36: =A35+1 -> 28 | B36: Octanol | C36: P-215 | D36: T - 210 Reflux Pump | E36: TOL | F36: F41-216F4M0204TIBI BM | G36: CL-2181 | H36: 33 | I36: 2 | J36: 40 | K36: 0.84 | L36: 0.49 | M36: 2.25 | N36: .-0.53 | O36: 2.78 | P36: 5 | Q36: 304 | R36: 304 | S36: 304 | T36: 2900 | U36: 1.32 | V36: 50 | X36: 380 / 3 | Y36: Teikoku | Z36: 5 | AA36: C | AB36: * | AC36: Klik | AE36: 3900 | AH36: OP-008 | AJ36: Replace bearing A & B | AK36: 44826 | AN36: OK
A37: =A36+1 -> 29 | B37: Octanol | C37: P-217 | D37: Tol Pump | E37: TOL | F37: F41-217C4M0405 TI-BV | G37: CL-2182 | H37: 32 | I37: 8.1 | J37: . | K37: 843 | L37: 0.08 | M37: 2.658 | N37: .-0.04 | O37: 2.698 | P37: 10 | Q37: 304 | R37: 304 | S37: 304 | T37: 2900 | U37: 1.9 | V37: 50 | X37: 380 / 3 | Y37: Teikoku | Z37: 5 | AA37: C | AB37: * | AC37: Klik | AE37: 3900 | AJ37: Replace bearing A & B | AK37: 36875 | AN37: OK
A38: =A37+1 -> 30 | B38: OSBL | C38: P-217C | D38: Tol Pump | E38: TOL | AC38: Klik | AJ38: PM, check external, retightening bolt | AK38: 41680
A39: =A38+1 -> 31 | B39: Octanol | C39: P-222 | D39: T - 220 Bottom Pump | E39: Heavy End | F39: F41-416J4BM0608 TI-BV | G39: CL-2183 | H39: 27 | I39: 39 | J39: 150 | K39: 0.98 | L39: 4.38 | M39: 2.04 | N39: .-0.61 | O39: 2.65 | P39: 3 | Q39: 304 | R39: 304 | S39: 304 | T39: 2900 | U39: 11 | V39: 50 | X39: 380 / 3 | Y39: Teikoku | Z39: 5 | AA39: C | AB39: * | AC39: Klik | AE39: 6100 | AH39: OP-009 | AJ39: Replace bearing A & B | AK39: 38411 | AN39: OK
A40: =A39+1 -> 32 | B40: Octanol | C40: P-222B | D40: T - 220 Bottom Pump | E40: Heavy End | F40: F41-416J4BM0810 TI-FV | G40: CL-2183 | H40: 27 | I40: 49 | J40: 150 | K40: 0.98 | L40: 4.38 | M40: 2.04 | N40: .-0.61 | O40: 2.65 | P40: 3 | Q40: 304 | R40: 304 | S40: 304 | T40: 2900 | U40: 11 | V40: 50 | X40: 380 / 3 | Y40: Teikoku | Z40: 5 | AA40: C | AB40: * | AC40: Klik | AE40: 6100 | AG40: New Pump | AH40: OP-009 | AN40: OK
A41: =A40+1 -> 33 | B41: Octanol | C41: P-225 | D41: T - 220 Reflux Pump | E41: FOL | F41: F41-216F4M0204TIBI-BV | G41: CL-2184 | H41: 39 | I41: 1 | J41: 40 | K41: 0.86 | L41: 2.26 | M41: 2.84 | N41: .-051 | O41: 3.35 | P41: 5 | Q41: 304 | R41: 304 | S41: 304 | T41: 2900 | U41: 1.5 | V41: 50 | X41: 380 / 3 | Y41: Teikoku | Z41: 5 | AA41: C | AB41: * | AC41: Klik | AE41: 4500 | AH41: OP-009 | AJ41: Replace bearing A & B | AK41: 44826 | AN41: OK
A42: =A41+1 -> 34 | B42: Octanol | C42: P-226 | D42: T - 220 Water Pump | E42: WWT | F42: F41-215 F4AM 020431-BV | G42: CL-2185 | H42: 23 | I42: 1 | J42: 40 | K42: 0.99 | L42: 1.01 | M42: 1.88 | N42: .-0.42 | O42: 2.3 | P42: 5 | Q42: 304 | R42: 304 | S42: 304 | T42: 2900 | U42: 0.8 | V42: 50 | X42: 380 / 3 | Y42: Teikoku | Z42: 5 | AA42: C | AB42: * | AC42: Klik | AE42: 3900 | AH42: OP-009 | AJ42: Replace bearing A & B | AK42: 44826 | AN42: OK
A43: =A42+1 -> 35 | B43: Octanol | C43: P-230A | D43: A-230 Pressure Unit | E43: 2EH | F43: EX10C-HB403GA6-S4 | H43: 48.8 | I43: 3 | J43: 50 | K43: 0.82 | L43: 9.3 | M43: 33.99 | N43: 30 | O43: 3.9 | P43: 1.5 | Q43: SCS313 | R43: SCS313 | S43: 304 | T43: 2950 | U43: 7.5 | V43: 50 | W43: 2 | X43: 380/3 | Y43: Halla | AC43: Klik | AJ43: New pump P-230 Halla EX10C-HB403GA6-S4 | AK43: 43046 | AN43: OK
A44: =A43+1 -> 36 | B44: Octanol | C44: P-230B | D44: A-230 Pressure Unit | E44: 2EH | F44: EX10C-HB403GA6-S4 | H44: 48.8 | I44: 3 | J44: 50 | K44: 0.82 | L44: 9.3 | M44: 33.99 | N44: 30 | O44: 3.9 | P44: 1.5 | Q44: SCS313 | R44: SCS313 | S44: 304 | T44: 2950 | U44: 7.5 | V44: 50 | W44: 2 | X44: 380/3 | Y44: Halla | AC44: Klik | AJ44: Pompa new 2010 Mod=HN220-BL | AK44: 40361 | AN44: OK
A45: =A44+1 -> 37 | B45: Octanol | C45: P-237 | D45: IPA Pump | E45: IPA | F45: F41 215F4AM 0204SISI-BV | G45: CL-2186 | H45: 12 | I45: 1 | J45: 40 | K45: 0.78 | L45: 1..36 | M45: 0.863 | N45: .-0.06 | O45: 0.932 | P45: 10 | Q45: 304 | R45: 304 | S45: 304 | T45: 2900 | U45: 0.8 | V45: 50 | X45: 380 / 3 | Y45: Teikoku | AC45: Klik | AE45: 6600 | AH45: OP-010 | AJ45: Replace bearing A & B | AK45: 44822 | AN45: OK
A46: =A45+1 -> 38 | B46: Octanol | C46: P-243 | D46: Recovered CAT Pump | E46: TOL | F46: F41-215F4AM 0204 SI-BV | G46: CL-2187 | H46: 20 | I46: 0.64 | J46: 40 | K46: 0.86 | L46: 0.489 | M46: 1.71 | N46: .-0.01 | O46: 1.72 | P46: 10 | Q46: 304 | R46: 304 | S46: 304 | T46: 2900 | U46: 0.6 | V46: 50 | X46: 380 / 3 | Y46: Teikoku | AC46: Klik | AE46: 3500 | AF46: 38488 | AH46: OP-010 | AJ46: Replace bearing A & B | AK46: 36656 | AN46: OK
A47: =A46+1 -> 39 | B47: Octanol | C47: P-251 | D47: T - 250 Feed Pump | E47: IPA SOLUTION | F47: F41-215 F4AM 020451-BV | G47: CL-2188 | H47: 20 | I47: 1,4 | J47: 20 | K47: 916 | L47: 4.3 | M47: 1.882 | N47: 0.049 | O47: 1.833 | P47: 10 | Q47: 304 | R47: 304 | S47: 304 | T47: 2900 | U47: 0.65 | V47: 50 | X47: 380 / 3 | Y47: Teikoku | AC47: Klik | AE47: 3500 | AH47: OP-010 | AJ47: Replace bearing A & B | AK47: 44822 | AN47: OK
A48: =A47+1 -> 40 | B48: Octanol | C48: P-252 | D48: T - 250 Bottom Pump | E48: SPENT CAT | F48: F41-317 J4BM 0506TI-BV | G48: CL-2189 | H48: 32 | I48: 26,29 | J48: 148 | K48: 1 | L48: 2.73 | M48: 3.659 | N48: 0.462 | O48: 3.197 | P48: 4 | Q48: 304 | R48: 304 | S48: 304 | T48: 2900 | U48: 5.2 | V48: 50 | X48: 380 / 3 | Y48: Teikoku | AC48: Klik | AE48: 6200 | AH48: OP-010 | AJ48: Replace bearing A & B | AK48: 44822 | AN48: OK
A49: =A48+1 -> 41 | B49: Octanol | C49: p-255 | D49: T - 250 Reflux Pump | E49: IPA SOLUTION | F49: F41-215F4AM 0204 SI-BV | G49: CL-2190 | H49: 22 | I49: 1458 | J49: 40 | K49: 0.84 | L49: 0.859 | M49: 2.398 | N49: 0.552 | O49: 1.846 | P49: 12 | Q49: 304 | R49: 304 | S49: 304 | T49: 2900 | U49: 0.6 | V49: 50 | X49: 380 / 3 | Y49: Teikoku | AC49: Klik | AE49: 3700 | AH49: OP-010 | AJ49: Replace bearing A & B | AK49: 36833 | AN49: OK
